Workbook
Name _0128_ILOCOS_NORTE: CITY!$B$1:$X$1
Name _0129_ILOCOS_SUR: CITY!$B$2:$AI$2
Name _0133_LA_UNION: CITY!$B$3:$V$3
Name _0155_PANGASINAN: CITY!$B$4:$AW$4
Name _0209_BATANES: CITY!$B$5:$G$5
Name _0215_CAGAYAN: CITY!$B$6:$AD$6
Name _0231_ISABELA: CITY!$B$7:$AL$7
Name _0250_NUEVA_VIZCAYA: CITY!$B$8:$P$8
Name _0257_QUIRINO: CITY!$B$9:$G$9
Name _0308_BATAAN: CITY!$B$10:$M$10
Name _0314_BULACAN: CITY!$B$11:$Y$11
Name _0349_NUEVA_ECIJA: CITY!$B$12:$AG$12
Name _0354_PAMPANGA: CITY!$B$13:$W$13
Name _0369_TARLAC: CITY!$B$14:$S$14
Name _0371_ZAMBALES: CITY!$B$15:$O$15
Name _0377_AURORA: CITY!$B$16:$I$16
Name _0410_BATANGAS: CITY!$B$17:$AI$17
Name _0421_CAVITE: CITY!$B$18:$X$18
Name _0434_LAGUNA: CITY!$B$19:$AE$19
Name _0456_QUEZON: CITY!$B$20:$AP$20
Name _0458_RIZAL: CITY!$B$21:$O$21
Name _0505_ALBAY: CITY!$B$22:$S$22
Name _0516_CAMARINES_NORTE: CITY!$B$23:$M$23
Name _0517_CAMARINES_SUR: CITY!$B$24:$AL$24
Name _0520_CATANDUANES: CITY!$B$25:$L$25
Name _0541_MASBATE: CITY!$B$26:$V$26
Name _0562_SORSOGON: CITY!$B$27:$P$27
Name _0604_AKLAN: CITY!$B$28:$R$28
Name _0606_ANTIQUE: CITY!$B$29:$V$29
Name _0619_CAPIZ: CITY!$B$30:$R$30
Name _0630_ILOILO: CITY!$B$31:$AV$31
Name _0645_NEGROS_OCCIDENTAL: CITY!$B$33:$AI$33
Name _0679_GUIMARAS: CITY!$B$32:$F$32
Name _0712_BOHOL: CITY!$B$34:$AW$34
Name _0722_CEBU: CITY!$B$35:$BB$35
Name _0746_NEGROS_ORIENTAL: CITY!$B$37:$Z$37
Name _0761_SIQUIJOR: CITY!$B$36:$G$36
Name _0826_EASTERN_SAMAR: CITY!$B$38:$X$38
Name _0837_LEYTE: CITY!$B$39:$AR$39
Name _0848_NORTHERN_SAMAR: CITY!$B$40:$Y$40
Name _0860_SAMAR__WESTERN_SAMAR: CITY!$B$41:$XFD$41
Name _0860_SAMAR_WESTERN_SAMAR: CITY!$B$41:$AA$41
Name _0864_SOUTHERN_LEYTE: CITY!$B$42:$T$42
Name _0878_BILIRAN: CITY!$B$43:$I$43
Name _0972_ZAMBOANGA_DEL_NORTE: CITY!$B$44:$AB$44
Name _0973_ZAMBOANGA_DEL_SUR: CITY!$B$45:$AC$45
Name _0983_ZAMBOANGA_SIBUGAY: CITY!$B$46:$Q$46
Name _0997_CITY_OF_ISABELA: CITY!$B$47
Name _0997_CITY_OF_ISABELA__Not_a_Province: CITY!$B$47:$BE$47
Name _1013_BUKIDNON: CITY!$B$48:$W$48
Name _101301_BAUNGON: BARANGAY!$B$1094:$XFD$1094
Name _101302_DAMULOG: BARANGAY!$B$1098:$XFD$1098
Name _101303_DANGCAGAN: BARANGAY!$B$1099:$XFD$1099
Name _101304_DON_CARLOS: BARANGAY!$B$1100:$XFD$1100
Name _101305_IMPASUG_ONG: BARANGAY!$B$1101:$XFD$1101
Name _101306_KADINGILAN: BARANGAY!$B$1102:$XFD$1102
Name _101307_KALILANGAN: BARANGAY!$B$1103:$XFD$1103
Name _101308_KIBAWE: BARANGAY!$B$1104:$XFD$1104
Name _101309_KITAOTAO: BARANGAY!$B$1105:$XFD$1105
Name _101310_LANTAPAN: BARANGAY!$B$1106:$XFD$1106

Sheet Eligible Population
A1: Priority Group* | B1: Sub-Priority Group* | C1: Last_Name* | D1: First_Name* | E1: Middle_Name* | F1: Suffix | G1: Mobile number (format:9170123456)* | H1: Current_Residence:_Region* | I1: Current_Residence: Province* | J1: Current_Residence: Municipality/City* | K1: Current_Residence: Barangay* | L1: Sex* | M1: Birthdate_mm/dd/yyyy_* | N1: Occupation* | O1: Allergy to vaccines or components of vaccines* | P1: With_Comorbidity?* | Q1: Email* | R1: Employee Number*

Sheet Key
A1: Categories | B1: Category_ID | C1: Sex | D1: Civil_Status | E1: Employment_Status | F1: With_Allergy? | G1: Name_of_Allergy | H1: With_Comorbidity? | I1: Patient_was_diagnosed_with_COVID_19 | J1: Provided_Consent? | K1: COVID_19_Classification | L1: Pregnancy | M1: Breastfeeding | N1: Role | O1: Profession | P1: Directly_in_interaction_with_COVID_patient | Q1: Name_of_Comorbidity | S1: Code | T1: Description | V1: CODE | W1: PROVINCE | X1: FINAL_PROVINCE | Y1: CODE | Z1: CITY | AA1: FINAL_CITY | AB1: CODE | AC1: BARANGAY | AD1: FINAL_BARANGAY | AF1: Reason_for_Refusal | AG1: Reason_for_Not_FIT | AH1: Vaccine Manufacturer | AI1: 1st Dose | AJ1: 2nd Dose | AK1: Bakuna center id
A2: 01_Health_Care_Worker | B2: 01_PRC_number | C2: 01_Female | D2: 01_Single | E2: 01_Government_Employed | F2: 01_Yes | G2: 01_Drug | H2: 01_Yes | I2: 01_Yes | J2: 01_Yes | K2: 01_Asymptomatic | L2: 01_Pregnant | M2: Yes_ | N2: Team_Lead | O2: 01_Dental_Hygienist | P2: 01_Yes | Q2: 01_Hypertension | S2: 175301 | T2: ABORLAN | U2: 175301_ABORLAN | V2: 1339 | W2: NCR,_CITY_OF_MANILA,_FIRST_DISTRICT_Not_a_Province) | X2: =CONCATENATE(V2," - ",W2) -> 1339 - NCR,_CITY_OF_MANILA,_FIRST_DISTRICT_Not_a_Province) | Y2: 137501 | Z2: CALOOCAN_CITY | AA2: =CONCATENATE(Y2," - ",Z2) -> 137501 - CALOOCAN_CITY | AB2: 133901001 | AC2: BARANGAY_1 | AD2: =CONCATENATE(AB2," - ",AC2) -> 133901001 - BARANGAY_1 | AF2: I do not think this vaccine is safe | AG2: Fever | AH2: Pfizer | AI2: 01_Yes | AJ2: 01_Yes | AK2: CBC000000000004211
A3: 02_Senior_Citizen | B3: 02_OSCA_number | C3: 02_Male | D3: 02_Married | E3: 02_Private_Employed | F3: 02_None | G3: 02_Food | H3: 02_None | I3: 02_No | J3: 02_No | K3: 02_Mild | L3: 02_Not_Pregnant | M3: No | N3: Counseling_Nurse | O3: 02_Dental_Technologist | P3: 02_No | Q3: 02_Heart_disease | S3: 1401 | T3: ABRA | U3: 1401_ABRA | V3: 1374 | W3: NCR,_SECOND_DISTRICT_(Not_a_Province) | X3: =CONCATENATE(V3," - ",W3) -> 1374 - NCR,_SECOND_DISTRICT_(Not_a_Province) | Y3: 137601 | Z3: CITY_OF_LAS_PIÑAS | AA3: =CONCATENATE(Y3," - ",Z3) -> 137601 - CITY_OF_LAS_PIÑAS | AB3: 133901002 | AC3: BARANGAY_2 | AD3: =CONCATENATE(AB3," - ",AC3) -> 133901002 - BARANGAY_2 | AF3: I do not think this vaccine is effective | AG3: Headache | AH3: Astrazeneca | AI3: 02_No | AJ3: 02_No | AK3: CBC000000000001886
A4: 03_Indigent | B4: 03_Facility_ID_number | D4: 03_Widow/Widower | E4: 03_Self_employed | G4: 03_Insect | I4: 00_UNKNOWN | K4: 03_Moderate | L4: 00_UNKNOWN | N4: Encoder | O4: 03_Dentist | P4: 00_UNKNOWN | Q4: 03_Kidney_disease | S4: 175101 | T4: ABRA_DE_ILOG | U4: =CONCATENATE(S4," - ",T4) -> 175101 - ABRA_DE_ILOG | V4: 1375 | W4: NCR,_THIRD_DISTRICT_(Not_a_Province) | X4: =CONCATENATE(V4," - ",W4) -> 1375 - NCR,_THIRD_DISTRICT_(Not_a_Province) | Y4: 137602 | Z4: CITY_OF_MAKATI | AA4: =CONCATENATE(Y4," - ",Z4) -> 137602 - CITY_OF_MAKATI | AB4: 133901003 | AC4: BARANGAY_3 | AD4: =CONCATENATE(AB4," - ",AC4) -> 133901003 - BARANGAY_3 | AF4: I do not trust a vaccine that has come from another country | AG4: Cough | AH4: Sinovac | AI4: 00_UNKNOWN | AJ4: 00_UNKNOWN | AK4: CBC000000000001113
A5: 04_Uniformed_Personnel | B5: 04_Other_ID | D5: 04_Separated/Annulled | E5: 04_Private_practitioner | G5: 04_Latex | K5: 04_Severe | O5: 04_Medical_Technologist | Q5: 04_Diabetes_mellitus | S5: 30801 | T5: ABUCAY | U5: =CONCATENATE(S5," - ",T5) -> 30801 - ABUCAY | V5: 1376 | W5: NCR,_FOURTH_DISTRICT_(Not_a_Province) | X5: =CONCATENATE(V5," - ",W5) -> 1376 - NCR,_FOURTH_DISTRICT_(Not_a_Province) | Y5: 137502 | Z5: CITY_OF_MALABON | AA5: =CONCATENATE(Y5," - ",Z5) -> 137502 - CITY_OF_MALABON | AB5: 133901004 | AC5: BARANGAY_4 | AD5: =CONCATENATE(AB5," - ",AC5) -> 133901004 - BARANGAY_4 | AF5: I have religious beliefs that do not allow me to be vaccinated | AG5: Colds | AK5: CBC000000000002742
A6: 05_Essential_Worker | B6: 00_UNKNOWN | D6: 05_Living_with_Partner | E6: 05_Others | G6: 05_Mold | K6: 05_Critical | O6: 05_Midwife | Q6: 05_Bronchial_Asthma | S6: 21501 | T6: ABULUG | U6: =CONCATENATE(S6," - ",T6) -> 21501 - ABULUG | X6: =CONCATENATE(V6," - ",W6) -> - | Y6: 137401 | Z6: CITY_OF_MANDALUYONG | AA6: =CONCATENATE(Y6," - ",Z6) -> 137401 - CITY_OF_MANDALUYONG | AB6: 133901005 | AC6: BARANGAY_5 | AD6: =CONCATENATE(AB6," - ",AC6) -> 133901005 - BARANGAY_5 | AF6: Others | AG6: Sore Throat | AK6: CBC000000000000495
A7: 06_Other | G7: 06_Pet | K7: 00_UNKNOWN | O7: 06_Nurse | Q7: 06_Immunodeficiency_state* | S7: 83701 | T7: ABUYOG | U7: =CONCATENATE(S7," - ",T7) -> 83701 - ABUYOG | X7: =CONCATENATE(V7," - ",W7) -> - | Y7: 133900 | Z7: CITY_OF_MANILA | AA7: =CONCATENATE(Y7," - ",Z7) -> 133900 - CITY_OF_MANILA | AB7: 133901006 | AC7: BARANGAY_6 | AD7: =CONCATENATE(AB7," - ",AC7) -> 133901006 - BARANGAY_6 | AG7: Shortness of Breath or Difficulty in Breathing | AK7: CBC000000000001090
A8: 07_Comorbidities | G8: 07_Pollen | O8: 07_Nutritionist_Dietician | Q8: 07_Cancer | S8: 12801 | T8: ADAMS | U8: =CONCATENATE(S8," - ",T8) -> 12801 - ADAMS | Y8: 137402 | Z8: CITY_OF_MARIKINA | AA8: =CONCATENATE(Y8," - ",Z8) -> 137402 - CITY_OF_MARIKINA | AB8: 133901007 | AC8: BARANGAY_7 | AD8: =CONCATENATE(AB8," - ",AC8) -> 133901007 - BARANGAY_7 | AG8: Chest Pain | AK8: CBC000000000003181
A9: 08_Teachers_Social_Workers | O9: 08_Occupational_Therapist | Q9: 08_Others | S9: 45601 | T9: AGDANGAN | U9: =CONCATENATE(S9," - ",T9) -> 45601 - AGDANGAN | Y9: 137603 | Z9: CITY_OF_MUNTINLUPA | AA9: =CONCATENATE(Y9," - ",Z9) -> 137603 - CITY_OF_MUNTINLUPA | AB9: 133901008 | AC9: BARANGAY_8 | AD9: =CONCATENATE(AB9," - ",AC9) -> 133901008 - BARANGAY_8 | AG9: Abdominal Pain | AK9: CBC000000000001890
A10: 09_Other_Govt_Wokers | O10: 09_Optometrist | S10: 25701 | T10: AGLIPAY | U10: =CONCATENATE(S10," - ",T10) -> 25701 - AGLIPAY | Y10: 137503 | Z10: CITY_OF_NAVOTAS | AA10: =CONCATENATE(Y10," - ",Z10) -> 137503 - CITY_OF_NAVOTAS | AB10: 133901009 | AC10: BARANGAY_9 | AD10: =CONCATENATE(AB10," - ",AC10) -> 133901009 - BARANGAY_9 | AG10: Changes in Bowel Movement | AK10: CBC000000000001855
A11: 10_Other_High_Risk | O11: 10_Pharmacist | S11: 15501 | T11: AGNO | U11: =CONCATENATE(S11," - ",T11) -> 15501 - AGNO | Y11: 137604 | Z11: CITY_OF_PARAÑAQUE | AA11: =CONCATENATE(Y11," - ",Z11) -> 137604 - CITY_OF_PARAÑAQUE | AB11: 133901010 | AC11: BARANGAY_10 | AD11: =CONCATENATE(AB11," - ",AC11) -> 133901010 - BARANGAY_10 | AG11: Loss of taste/smell | AK11: CBC000000000003544
A12: 11_OFW | O12: 11_Physical_Therapist | S12: 41001 | T12: AGONCILLO | U12: =CONCATENATE(S12," - ",T12) -> 41001 - AGONCILLO | Y12: 137403 | Z12: CITY_OF_PASIG | AA12: =CONCATENATE(Y12," - ",Z12) -> 137403 - CITY_OF_PASIG | AB12: 133901011 | AC12: BARANGAY_11 | AD12: =CONCATENATE(AB12," - ",AC12) -> 133901011 - BARANGAY_11 | AG12: Fatigue/weakness | AK12: CBC000000000001063
A13: 12_Remaining_Workforce | O13: 12_Physician | S13: 13301 | T13: AGOO | U13: =CONCATENATE(S13," - ",T13) -> 13301 - AGOO | Y13: 137405 | Z13: CITY_OF_SAN_JUAN | AA13: =CONCATENATE(Y13," - ",Z13) -> 137405 - CITY_OF_SAN_JUAN | AB13: 133901012 | AC13: BARANGAY_12 | AD13: =CONCATENATE(AB13," - ",AC13) -> 133901012 - BARANGAY_12 | AG13: COVID-19 in the past 90 days? | AK13: CBC000000000004142
A14: 00_UNKNOWN | O14: 13_Radiologic_Technologist | S14: 15502 | T14: AGUILAR | U14: =CONCATENATE(S14," - ",T14) -> 15502 - AGUILAR | Y14: 137504 | Z14: CITY_OF_VALENZUELA | AA14: =CONCATENATE(Y14," - ",Z14) -> 137504 - CITY_OF_VALENZUELA | AB14: 133901013 | AC14: BARANGAY_13 | AD14: =CONCATENATE(AB14," - ",AC14) -> 133901013 - BARANGAY_13 | AG14: Bleeding disorder or blood thinner | AK14: CBC000000000004222
O15: 14_Respiratory_Therapist | S15: 142708 | T15: AGUINALDO | U15: =CONCATENATE(S15," - ",T15) -> 142708 - AGUINALDO | Y15: 137605 | Z15: PASAY_CITY | AA15: =CONCATENATE(Y15," - ",Z15) -> 137605 - PASAY_CITY | AB15: 133901014 | AC15: BARANGAY_14 | AD15: =CONCATENATE(AB15," - ",AC15) -> 133901014 - BARANGAY_14 | AG15: Autoimmune disorder, HIV, AIDS, Cancer | AK15: CBC000000000003619
O16: 15_X_ray_Technologist | S16: 1602 | T16: AGUSAN_DEL_NORTE | U16: =CONCATENATE(S16," - ",T16) -> 1602 - AGUSAN_DEL_NORTE | Y16: 137606 | Z16: PATEROS | AA16: =CONCATENATE(Y16," - ",Z16) -> 137606 - PATEROS | AB16: 133901015 | AC16: BARANGAY_15 | AD16: =CONCATENATE(AB16," - ",AC16) -> 133901015 - BARANGAY_15 | AG16: Received any vaccine 4 weeks ago | AK16: CBC000000000003957
O17: 16_Barangay_Health_Worker | S17: 1603 | T17: AGUSAN_DEL_SUR | U17: =CONCATENATE(S17," - ",T17) -> 1603 - AGUSAN_DEL_SUR | Y17: 137404 | Z17: QUEZON_CITY | AA17: =CONCATENATE(Y17," - ",Z17) -> 137404 - QUEZON_CITY | AB17: 133901016 | AC17: BARANGAY_16 | AD17: =CONCATENATE(AB17," - ",AC17) -> 133901016 - BARANGAY_16 | AG17: Reaction from any previous vaccine? | AK17: CBC000000000004907
O18: 17_Maintenance_Staff | S18: 175302 | T18: AGUTAYA | U18: =CONCATENATE(S18," - ",T18) -> 175302 - AGUTAYA | Y18: 137607 | Z18: TAGUIG_CITY | AA18: =CONCATENATE(Y18," - ",Z18) -> 137607 - TAGUIG_CITY | AB18: 133901017 | AC18: BARANGAY_17 | AD18: =CONCATENATE(AB18," - ",AC18) -> 133901017 - BARANGAY_17 | AG18: Pregnant, Breastfeeding, Planning Pregnancy | AK18: CBC000000000002629
C19: Priority Group* | D19: Sub-Priority Group* | O19: 18_Administrative_Staff | S19: 63001 | T19: AJUY | U19: =CONCATENATE(S19," - ",T19) -> 63001 - AJUY | AA19: =CONCATENATE(Y19," -",Z19) -> - | AB19: 133901018 | AC19: BARANGAY_18 | AD19: =CONCATENATE(AB19," - ",AC19) -> 133901018 - BARANGAY_18 | AG19: Multiple conditions | AK19: CBC000000000005250
C20: 01_A1: Health Care Workers | D20: 01_A1.1: COVID-19 Referral Hospitals | O20: 19_Others_ | S20: 150708 | T20: AKBAR | U20: =CONCATENATE(S20," - ",T20) -> 150708 - AKBAR | AA20: =CONCATENATE(Y20," -",Z20) -> - | AB20: 133901019 | AC20: BARANGAY_19 | AD20: =CONCATENATE(AB20," - ",AC20) -> 133901019 - BARANGAY_19 | AG20: Hypertension | AK20: CBC000000000000891
C21: 02_A2: Senior Citizens | D21: 02_A1.2: Hopitals Catering to C19 Cases | S21: 604 | T21: AKLAN | U21: =CONCATENATE(S21," - ",T21) -> 604 - AKLAN | AA21: =CONCATENATE(Y21," -",Z21) -> - | AB21: 133901020 | AC21: BARANGAY_20 | AD21: =CONCATENATE(AB21," - ",AC21) -> 133901020 - BARANGAY_20 | AG21: 00_UNKNOWN | AK21: CBC000000000004542
A22: Suffix | C22: 03_A3: Adult with Comorbidity | D22: 03_A1.3: Quarantine Isolation Facilities | S22: 150709 | T22: AL_BARKA | U22: =CONCATENATE(S22," - ",T22) -> 150709 - AL_BARKA | AA22: =CONCATENATE(Y22," -",Z22) -> - | AB22: 133901025 | AC22: BARANGAY_25 | AD22: =CONCATENATE(AB22," - ",AC22) -> 133901025 - BARANGAY_25 | AK22: CBC000000000005510
A23: I | C23: 04_A4: Frontline Personnel in Essential Sector | D23: 04_A1.4: Remaining Hospitals | S23: 45602 | T23: ALABAT | U23: =CONCATENATE(S23," - ",T23) -> 45602 - ALABAT | AA23: =CONCATENATE(Y23," -",Z23) -> - | AB23: 133901026 | AC23: BARANGAY_26 | AD23: =CONCATENATE(AB23," - ",AC23) -> 133901026 - BARANGAY_26 | AK23: CBC000000000003063
A24: II | C24: 05_A5: Poor Population | D24: 05_A1.5: Government Owned Community Based Primary Care Facilities | S24: 128001 | T24: ALABEL_ | U24: =CONCATENATE(S24," - ",T24) -> 128001 - ALABEL_ | AA24: =CONCATENATE(Y24," -",Z24) -> - | AB24: 133901028 | AC24: BARANGAY_28 | AD24: =CONCATENATE(AB24," - ",AC24) -> 133901028 - BARANGAY_28 | AK24: CBC000000000004693
A25: III | C25: 06_B1: Teachers and Social Workers | D25: 06_A1.6: Stand-alone Clinics and Diagnostics | S25: 124701 | T25: ALAMADA | U25: =CONCATENATE(S25," - ",T25) -> 124701 - ALAMADA | AA25: =CONCATENATE(Y25," -",Z25) -> - | AB25: 133901029 | AC25: BARANGAY_29 | AD25: =CONCATENATE(AB25," - ",AC25) -> 133901029 - BARANGAY_29 | AK25: CBC000000000005545
A26: IV | C26: 07_B2: Other Government Workers | D26: 07_A1.7: Closed Settings and Institutions | S26: 43401 | T26: ALAMINOS | U26: =CONCATENATE(S26," - ",T26) -> 43401 - ALAMINOS | AA26: =CONCATENATE(Y26," -",Z26) -> - | AB26: 133901030 | AC26: BARANGAY_30 | AD26: =CONCATENATE(AB26," - ",AC26) -> 133901030 - BARANGAY_30 | AK26: CBC000000000000064
A27: JR | C27: 08_B3: Other Essential Workers | S27: 83702 | T27: ALANGALANG | U27: =CONCATENATE(S27," - ",T27) -> 83702 - ALANGALANG | AA27: =CONCATENATE(Y27," -",Z27) -> - | AB27: 133901031 | AC27: BARANGAY_31 | AD27: =CONCATENATE(AB27," - ",AC27) -> 133901031 - BARANGAY_31 | AK27: CBC000000000002933
A28: NA | C28: 09_B4: Socio-demographic Groups | S28: 505 | T28: ALBAY | U28: =CONCATENATE(S28," - ",T28) -> 505 - ALBAY | AA28: =CONCATENATE(Y28," -",Z28) -> - | AB28: 133901032 | AC28: BARANGAY_32 | AD28: =CONCATENATE(AB28," - ",AC28) -> 133901032 - BARANGAY_32 | AK28: CBC000000000002775
A29: SR | C29: 10_B5: Overseas Filipino Workers | S29: 83703 | T29: ALBUERA | U29: =CONCATENATE(S29," - ",T29) -> 83703 - ALBUERA | AA29: =CONCATENATE(Y29," -",Z29) -> - | AB29: 133901033 | AC29: BARANGAY_33 | AD29: =CONCATENATE(AB29," - ",AC29) -> 133901033 - BARANGAY_33 | AK29: CBC000000000003001
A30: V | C30: 11_B6: Other Remaing Workforce | S30: 71201 | T30: ALBURQUERQUE | U30: =CONCATENATE(S30," - ",T30) -> 71201 - ALBURQUERQUE | AA30: =CONCATENATE(Y30," -",Z30) -> - | AB30: 133901034 | AC30: BARANGAY_34 | AD30: =CONCATENATE(AB30," - ",AC30) -> 133901034 - BARANGAY_34 | AK30: CBC000000000003647
A31: 00_UNKNOWN | C31: 12_C: Rest of the Population | S31: 15504 | T31: ALCALA | U31: =CONCATENATE(S31," - ",T31) -> 15504 - ALCALA | AA31: =CONCATENATE(Y31," -",Z31) -> - | AB31: 133901035 | AC31: BARANGAY_35 | AD31: =CONCATENATE(AB31," - ",AC31) -> 133901035 - BARANGAY_35 | AK31: CBC000000000001718
S32: 21502 | T32: ALCALA | U32: =CONCATENATE(S32," - ",T32) -> 21502 - ALCALA | AA32: =CONCATENATE(Y32," -",Z32) -> - | AB32: 133901036 | AC32: BARANGAY_36 | AD32: =CONCATENATE(AB32," - ",AC32) -> 133901036 - BARANGAY_36 | AK32: CBC000000000005125
S33: 72201 | T33: ALCANTARA | U33: =CONCATENATE(S33," - ",T33) -> 72201 - ALCANTARA | AA33: =CONCATENATE(Y33," -",Z33) -> - | AB33: 133901037 | AC33: BARANGAY_37 | AD33: =CONCATENATE(AB33," - ",AC33) -> 133901037 - BARANGAY_37 | AK33: CBC000000000003897
S34: 175901 | T34: ALCANTARA | U34: =CONCATENATE(S34," - ",T34) -> 175901 - ALCANTARA | AA34: =CONCATENATE(Y34," -",Z34) -> - | AB34: 133901038 | AC34: BARANGAY_38 | AD34: =CONCATENATE(AB34," - ",AC34) -> 133901038 - BARANGAY_38 | AK34: CBC000000000001199
S35: 72202 | T35: ALCOY | U35: =CONCATENATE(S35," - ",T35) -> 72202 - ALCOY | AA35: =CONCATENATE(Y35," -",Z35) -> - | AB35: 133901039 | AC35: BARANGAY_39 | AD35: =CONCATENATE(AB35," - ",AC35) -> 133901039 - BARANGAY_39 | AK35: CBC000000000002732
S36: 72203 | T36: ALEGRIA | U36: =CONCATENATE(S36," - ",T36) -> 72203 - ALEGRIA | AA36: =CONCATENATE(Y36," -",Z36) -> - | AB36: 133901041 | AC36: BARANGAY_41 | AD36: =CONCATENATE(AB36," - ",AC36) -> 133901041 - BARANGAY_41 | AK36: CBC000000000001893
S37: 166701 | T37: ALEGRIA | U37: =CONCATENATE(S37," - ",T37) -> 166701 - ALEGRIA | AA37: =CONCATENATE(Y37," -",Z37) -> - | AB37: 133901042 | AC37: BARANGAY_42 | AD37: =CONCATENATE(AB37," - ",AC37) -> 133901042 - BARANGAY_42 | AK37: CBC000000000002516
S38: 124717 | T38: ALEOSAN | U38: =CONCATENATE(S38," - ",T38) -> 124717 - ALEOSAN | AA38: =CONCATENATE(Y38," -",Z38) -> - | AB38: 133901043 | AC38: BARANGAY_43 | AD38: =CONCATENATE(AB38," - ",AC38) -> 133901043 - BARANGAY_43 | AK38: CBC000000000002873
S39: 42101 | T39: ALFONSO | U39: =CONCATENATE(S39," - ",T39) -> 42101 - ALFONSO | AA39: =CONCATENATE(Y39," -",Z39) -> - | AB39: 133901044 | AC39: BARANGAY_44 | AD39: =CONCATENATE(AB39," - ",AC39) -> 133901044 - BARANGAY_44 | AK39: CBC000000000005299
S40: 25015 | T40: ALFONSO_CASTANEDA | U40: =CONCATENATE(S40," - ",T40) -> 25015 - ALFONSO_CASTANEDA | AA40: =CONCATENATE(Y40," -",Z40) -> - | AB40: 133901045 | AC40: BARANGAY_45 | AD40: =CONCATENATE(AB40," - ",AC40) -> 133901045 - BARANGAY_45 | AK40: CBC000000000001956
S41: 142707 | T41: ALFONSO_LISTA_(POTIA) | U41: =CONCATENATE(S41," - ",T41) -> 142707 - ALFONSO_LISTA_(POTIA) | AA41: =CONCATENATE(Y41," -",Z41) -> - | AB41: 133901046 | AC41: BARANGAY_46 | AD41: =CONCATENATE(AB41," - ",AC41) -> 133901046 - BARANGAY_46 | AK41: CBC000000000005521
S42: 34901 | T42: ALIAGA | U42: =CONCATENATE(S42," - ",T42) -> 34901 - ALIAGA | AA42: =CONCATENATE(Y42," -",Z42) -> - | AB42: 133901047 | AC42: BARANGAY_47 | AD42: =CONCATENATE(AB42," - ",AC42) -> 133901047 - BARANGAY_47 | AK42: CBC000000000001563
S43: 23101 | T43: ALICIA | U43: =CONCATENATE(S43," - ",T43) -> 23101 - ALICIA | AA43: =CONCATENATE(Y43," -",Z43) -> - | AB43: 133901048 | AC43: BARANGAY_48 | AD43: =CONCATENATE(AB43," - ",AC43) -> 133901048 - BARANGAY_48 | AK43: CBC000000000001031
... S1705: 140127 | T1705: VILLAVICIOSA | U1705: =CONCATENATE(S1705," - ",T1705) -> 140127 - VILLAVICIOSA | AA1705: =CONCATENATE(Y1705," -",Z1705) -> - | AB1705: 137607028 | AC1705: SOUTH_SIGNAL_VILLAGE | AD1705: =CONCATENATE(AB1705," - ",AC1705) -> 137607028 - SOUTH_SIGNAL_VILLAGE | AK1705: CBC000000000002269
S1706: 97341 | T1706: VINCENZO_A._SAGUN | U1706: =CONCATENATE(S1706," - ",T1706) -> 97341 - VINCENZO_A._SAGUN | AA1706: =CONCATENATE(Y1706," -",Z1706) -> - | AD1706: =CONCATENATE(AB1706," - ",AC1706) -> - | AK1706: CBC000000000002333
S1707: 12823 | T1707: VINTAR | U1707: =CONCATENATE(S1707," - ",T1707) -> 12823 - VINTAR | AA1707: =CONCATENATE(Y1707," -",Z1707) -> - | AD1707: =CONCATENATE(AB1707," - ",AC1707) -> - | AK1707: CBC000000000002344
S1708: 51612 | T1708: VINZONS | U1708: =CONCATENATE(S1708," - ",T1708) -> 51612 - VINZONS | AA1708: =CONCATENATE(Y1708," -",Z1708) -> - | AD1708: =CONCATENATE(AB1708," - ",AC1708) -> - | AK1708: CBC000000000002555
S1709: 52011 | T1709: VIRAC_ | U1709: =CONCATENATE(S1709," - ",T1709) -> 52011 - VIRAC_ | AA1709: =CONCATENATE(Y1709," -",Z1709) -> - | AD1709: =CONCATENATE(AB1709," - ",AC1709) -> - | AK1709: CBC000000000002557
S1710: 153630 | T1710: WAO | U1710: =CONCATENATE(S1710," - ",T1710) -> 153630 - WAO | AA1710: =CONCATENATE(Y1710," -",Z1710) -> - | AD1710: =CONCATENATE(AB1710," - ",AC1710) -> - | AK1710: CBC000000000002536
S1711: 371 | T1711: ZAMBALES | U1711: =CONCATENATE(S1711," - ",T1711) -> 371 - ZAMBALES | AA1711: =CONCATENATE(Y1711," -",Z1711) -> - | AD1711: =CONCATENATE(AB1711," - ",AC1711) -> - | AK1711: CBC000000000003391
S1712: 97332 | T1712: ZAMBOANGA_CITY | U1712: =CONCATENATE(S1712," - ",T1712) -> 97332 - ZAMBOANGA_CITY | AA1712: =CONCATENATE(Y1712," -",Z1712) -> - | AD1712: =CONCATENATE(AB1712," - ",AC1712) -> - | AK1712: CBC000000000003162
S1713: 972 | T1713: ZAMBOANGA_DEL_NORTE | U1713: =CONCATENATE(S1713," - ",T1713) -> 972 - ZAMBOANGA_DEL_NORTE | AA1713: =CONCATENATE(Y1713," -",Z1713) -> - | AD1713: =CONCATENATE(AB1713," - ",AC1713) -> - | AK1713: CBC000000000005410
S1714: 973 | T1714: ZAMBOANGA_DEL_SUR | U1714: =CONCATENATE(S1714," - ",T1714) -> 973 - ZAMBOANGA_DEL_SUR | AA1714: =CONCATENATE(Y1714," -",Z1714) -> - | AD1714: =CONCATENATE(AB1714," - ",AC1714) -> - | AK1714: CBC000000000003461
S1715: 983 | T1715: ZAMBOANGA_SIBUGAY | U1715: =CONCATENATE(S1715," - ",T1715) -> 983 - ZAMBOANGA_SIBUGAY | AA1715: =CONCATENATE(Y1715," -",Z1715) -> - | AD1715: =CONCATENATE(AB1715," - ",AC1715) -> - | AK1715: CBC000000000003106
S1716: 74625 | T1716: ZAMBOANGUITA | U1716: =CONCATENATE(S1716," - ",T1716) -> 74625 - ZAMBOANGUITA | AA1716: =CONCATENATE(Y1716," -",Z1716) -> - | AD1716: =CONCATENATE(AB1716," - ",AC1716) -> - | AK1716: CBC000000000002415
S1717: 34932 | T1717: ZARAGOZA | U1717: =CONCATENATE(S1717," - ",T1717) -> 34932 - ZARAGOZA | AA1717: =CONCATENATE(Y1717," -",Z1717) -> - | AD1717: =CONCATENATE(AB1717," - ",AC1717) -> - | AK1717: CBC000000000001940
... S1719: 86023 | T1719: ZUMARRAGA | U1719: =CONCATENATE(S1719," - ",T1719) -> 86023 - ZUMARRAGA | AA1719: =CONCATENATE(Y1719," -",Z1719) -> - | AD1719: =CONCATENATE(AB1719," - ",AC1719) -> - | AK1719: CBC000000000001943
AD1720: =CONCATENATE(AB1720," - ",AC1720) -> - | AK1720: CBC000000000001492
AD1721: =CONCATENATE(AB1721," - ",AC1721) -> - | AK1721: CBC000000000004113
AD1722: =CONCATENATE(AB1722," - ",AC1722) -> - | AK1722: CBC000000000004319
AD1723: =CONCATENATE(AB1723," - ",AC1723) -> - | AK1723: CBC000000000003373
AD1724: =CONCATENATE(AB1724," - ",AC1724) -> - | AK1724: CBC000000000001710
AD1725: =CONCATENATE(AB1725," - ",AC1725) -> - | AK1725: CBC000000000004541
AD1726: =CONCATENATE(AB1726," - ",AC1726) -> - | AK1726: CBC000000000000858
AD1727: =CONCATENATE(AB1727," - ",AC1727) -> - | AK1727: CBC000000000000390
AD1728: =CONCATENATE(AB1728," - ",AC1728) -> - | AK1728: CBC000000000000600
AD1729: =CONCATENATE(AB1729," - ",AC1729) -> - | AK1729: CBC000000000001306
AD1730: =CONCATENATE(AB1730," - ",AC1730) -> - | AK1730: CBC000000000000583
AD1731: =CONCATENATE(AB1731," - ",AC1731) -> - | AK1731: CBC000000000003980
... AD4391: =CONCATENATE(AB4391," - ",AC4391) -> - | AK4391: CBC000000000000584
AK4392: CBC000000000000959
AK4393: CBC000000000001480
AK4394: CBC000000000003790
AK4395: CBC000000000004971
AK4396: CBC000000000001057
AK4397: CBC000000000001958
AK4398: CBC000000000003276
AK4399: CBC000000000001289
AK4400: CBC000000000001190
AK4401: CBC000000000002670
AK4402: CBC000000000002432
AK4403: CBC000000000003180
... AK5248: CBC000000000002086

Sheet Vaccinators
A1: NAME_OF_FACILITY_ | B1: PRC_LICENSE_NUMBER | C1: LAST_NAME | D1: FIRST_NAME | E1: MIDDLE_NAME_ | F1: POSITION | G1: ROLE
H2: (team_lead,counseling_nurse,encoder)

Sheet READ ME
A1: Updates
A2: 44255 | B2: Added new Categories in Column A
A3: 44260 | B3: Reduced the Columns to be filled out
A4: 44260 | B4: Added 'others' in reason for refusal
A5: 44260 | B5: Added 'multiple reasons' for reason for deferral
A6: 44263 | B6: Added "I" in the suffix
A10: Guidelines
A11: 44260 | B11: Per NVOC Advisory #15, please submit the completed line list at 11am and 6pm daily
B12: Submit to the following link: | D12: http://bit.ly/VIMSVASupload
A13: 44260 | B13: Use the Bakuna Center ID and name from CBCR

Sheet Region
D2: Region | F2: Region
D3: Ilocos | F3: 01_Ilocos
D4: CagayanValley | F4: 02_Cagayan_Valley
D5: CentralLuzon | F5: 03_Central_Luzon
D6: CALABARZON | F6: 04_CALABARZON
D7: BicolRegion | F7: 05_Bicol_Region
D8: WesternVisayas | F8: 06_Western_Visayas
D9: CentralVisayas | F9: 07_Central_Visayas
D10: EasternVisayas | F10: 08_Eastern_Visayas
D11: ZamboangaPeninsula | F11: 09_Zamboanga_Peninsula
D12: NorthernMindanao | F12: 10_Northern_Mindanao
D13: DavaoRegion | F13: 11_Davao_Region
... D19: MIMAROPA | F19: 17_MIMAROPA

Sheet Province References
A1: cagayan_province
A2: 0209 | B2: BATANES | C2: =CONCATENATE("_",A2,"_",B2) -> _0209_BATANES | F2: =C2 -> _0209_BATANES | H2: =E2 -> 0
A3: 0215 | B3: CAGAYAN | C3: =CONCATENATE("_",A3,"_",B3) -> _0215_CAGAYAN | F3: =C3 -> _0215_CAGAYAN | H3: =E3 -> 0
A4: 0231 | B4: ISABELA | C4: =CONCATENATE("_",A4,"_",B4) -> _0231_ISABELA | F4: =C4 -> _0231_ISABELA | H4: =E4 -> 0
A5: 0250 | B5: NUEVA_VIZCAYA | C5: =CONCATENATE("_",A5,"_",B5) -> _0250_NUEVA_VIZCAYA | F5: =C5 -> _0250_NUEVA_VIZCAYA | H5: =E5 -> 0
A6: 0257 | B6: QUIRINO | C6: =CONCATENATE("_",A6,"_",B6) -> _0257_QUIRINO | F6: =C6 -> _0257_QUIRINO | H6: =E6 -> 0
A7: Central_Luzon
A8: 0308 | B8: BATAAN | C8: =CONCATENATE("_",'Province References'!A8,"_",B8) -> _0308_BATAAN
A9: 0314 | B9: BULACAN | C9: =CONCATENATE("_",'Province References'!A9,"_",B9) -> _0314_BULACAN
A10: 0349 | B10: NUEVA_ECIJA | C10: =CONCATENATE("_",'Province References'!A10,"_",B10) -> _0349_NUEVA_ECIJA
A11: 0354 | B11: PAMPANGA | C11: =CONCATENATE("_",'Province References'!A11,"_",B11) -> _0354_PAMPANGA
A12: 0369 | B12: TARLAC | C12: =CONCATENATE("_",'Province References'!A12,"_",B12) -> _0369_TARLAC
A13: 0371 | B13: ZAMBALES | C13: =CONCATENATE("_",'Province References'!A13,"_",B13) -> _0371_ZAMBALES
A14: 0377 | B14: AURORA | C14: =CONCATENATE("_",'Province References'!A14,"_",B14) -> _0377_AURORA
A15: Calabarzon
A16: 0410 | B16: BATANGAS | C16: =CONCATENATE("_",A16,"_",B16) -> _0410_BATANGAS
A17: 0421 | B17: CAVITE | C17: =CONCATENATE("_",A17,"_",B17) -> _0421_CAVITE
A18: 0434 | B18: LAGUNA | C18: =CONCATENATE("_",A18,"_",B18) -> _0434_LAGUNA
A19: 0456 | B19: QUEZON | C19: =CONCATENATE("_",A19,"_",B19) -> _0456_QUEZON
A20: 0458 | B20: RIZAL | C20: =CONCATENATE("_",A20,"_",B20) -> _0458_RIZAL
A21: BICOL
A22: 0505 | B22: ALBAY | C22: =CONCATENATE("_",A22,"_",B22) -> _0505_ALBAY | E22: =CONCATENATE(A22," - ",B22) -> 0505 - ALBAY | F22: =CONCATENATE(B22," - ",C22) -> ALBAY - _0505_ALBAY | G22: =CONCATENATE(C22," - ",D22) -> _0505_ALBAY - | H22: =CONCATENATE(D22," - ",E22) -> - 0505 - ALBAY | I22: =CONCATENATE(E22," - ",F22) -> 0505 - ALBAY - ALBAY - _0505_ALBAY | J22: =CONCATENATE(F22," - ",G22) -> ALBAY - _0505_ALBAY - _0505_ALBAY - | K22: =CONCATENATE(G22," - ",H22) -> _0505_ALBAY - - - 0505 - ALBAY
A23: 0516 | B23: CAMARINES_NORTE | C23: =CONCATENATE("_",A23,"_",B23) -> _0516_CAMARINES_NORTE
A24: 0517 | B24: CAMARINES_SUR | C24: =CONCATENATE("_",A24,"_",B24) -> _0517_CAMARINES_SUR
A25: 0520 | B25: CATANDUANES | C25: =CONCATENATE("_",A25,"_",B25) -> _0520_CATANDUANES
A26: 0541 | B26: MASBATE | C26: =CONCATENATE("_",A26,"_",B26) -> _0541_MASBATE
A27: 0562 | B27: SORSOGON | C27: =CONCATENATE("_",A27,"_",B27) -> _0562_SORSOGON
A29: WESTERN
A30: 0604 | B30: AKLAN | C30: =CONCATENATE("_",A30,"_",B30) -> _0604_AKLAN
A31: 0606 | B31: ANTIQUE | C31: =CONCATENATE("_",A31,"_",B31) -> _0606_ANTIQUE
A32: 0619 | B32: CAPIZ | C32: =CONCATENATE("_",A32,"_",B32) -> _0619_CAPIZ
A33: 0630 | B33: ILOILO | C33: =CONCATENATE("_",A33,"_",B33) -> _0630_ILOILO
A34: 0679 | B34: GUIMARAS | C34: =CONCATENATE("_",A34,"_",B34) -> _0679_GUIMARAS
A35: 0645 | B35: NEGROS_OCCIDENTAL | C35: =CONCATENATE("_",A35,"_",B35) -> _0645_NEGROS_OCCIDENTAL
A37: CENTRAL_VISAYAS
A38: 0712 | B38: BOHOL | C38: =CONCATENATE("_",A38,"_",B38) -> _0712_BOHOL
A39: 0722 | B39: CEBU | C39: =CONCATENATE("_",A39,"_",B39) -> _0722_CEBU
A40: 0761 | B40: SIQUIJOR | C40: =CONCATENATE("_",A40,"_",B40) -> _0761_SIQUIJOR
A41: 0746 | B41: NEGROS_ORIENTAL | C41: =CONCATENATE("_",A41,"_",B41) -> _0746_NEGROS_ORIENTAL
A43: EASTERN_VISAYAS
A44: 0826 | B44: EASTERN_SAMAR | C44: =CONCATENATE("_",A44,"_",B44) -> _0826_EASTERN_SAMAR
A45: 0837 | B45: LEYTE | C45: =CONCATENATE("_",A45,"_",B45) -> _0837_LEYTE
A46: 0848 | B46: NORTHERN_SAMAR | C46: =CONCATENATE("_",A46,"_",B46) -> _0848_NORTHERN_SAMAR
A47: 0860 | B47: SAMAR_(WESTERN_SAMAR) | C47: =CONCATENATE("_",A47,"_",B47) -> _0860_SAMAR_(WESTERN_SAMAR)
A48: 0864 | B48: SOUTHERN_LEYTE | C48: =CONCATENATE("_",A48,"_",B48) -> _0864_SOUTHERN_LEYTE
A49: 0878 | B49: BILIRAN | C49: =CONCATENATE("_",A49,"_",B49) -> _0878_BILIRAN
A51: Zamboanga
A52: 0972 | B52: ZAMBOANGA_DEL_NORTE | C52: =CONCATENATE("_",A52,"_",B52) -> _0972_ZAMBOANGA_DEL_NORTE
A53: 0973 | B53: ZAMBOANGA_DEL_SUR | C53: =CONCATENATE("_",A53,"_",B53) -> _0973_ZAMBOANGA_DEL_SUR
A54: 0983 | B54: ZAMBOANGA_SIBUGAY | C54: =CONCATENATE("_",A54,"_",B54) -> _0983_ZAMBOANGA_SIBUGAY
A55: 0997 | B55: CITY_OF_ISABELA_(Not_a_Province) | C55: =CONCATENATE("_",A55,"_",B55) -> _0997_CITY_OF_ISABELA_(Not_a_Province)
A57: NM
A58: 1013 | B58: BUKIDNON | C58: =CONCATENATE("_",A58,"_",B58) -> _1013_BUKIDNON
A59: 1018 | B59: CAMIGUIN | C59: =CONCATENATE("_",A59,"_",B59) -> _1018_CAMIGUIN
A60: 1035 | B60: LANAO_DEL_NORTE | C60: =CONCATENATE("_",A60,"_",B60) -> _1035_LANAO_DEL_NORTE
A61: 1042 | B61: MISAMIS_OCCIDENTAL | C61: =CONCATENATE("_",A61,"_",B61) -> _1042_MISAMIS_OCCIDENTAL
A62: 1043 | B62: MISAMIS_ORIENTAL | C62: =CONCATENATE("_",A62,"_",B62) -> _1043_MISAMIS_ORIENTAL
A64: DAVAO
A65: 1123 | B65: DAVAO_DEL_NORTE | C65: =CONCATENATE("_",A65,"_",B65) -> _1123_DAVAO_DEL_NORTE
A66: 1124 | B66: DAVAO_DEL_SUR | C66: =CONCATENATE("_",A66,"_",B66) -> _1124_DAVAO_DEL_SUR
A67: 1125 | B67: DAVAO_ORIENTAL | C67: =CONCATENATE("_",A67,"_",B67) -> _1125_DAVAO_ORIENTAL
A68: 1182 | B68: COMPOSTELA_VALLEY | C68: =CONCATENATE("_",A68,"_",B68) -> _1182_COMPOSTELA_VALLEY
A69: 1186 | B69: DAVAO_OCCIDENTAL | C69: =CONCATENATE("_",A69,"_",B69) -> _1186_DAVAO_OCCIDENTAL
A71: SOCC
A72: 1247 | B72: COTABATO_(NORTH_COTABATO) | C72: =CONCATENATE("_",A72,"_",B72) -> _1247_COTABATO_(NORTH_COTABATO)
A73: 1263 | B73: SOUTH_COTABATO | C73: =CONCATENATE("_",A73,"_",B73) -> _1263_SOUTH_COTABATO
A74: 1265 | B74: SULTAN_KUDARAT | C74: =CONCATENATE("_",A74,"_",B74) -> _1265_SULTAN_KUDARAT
A75: 1280 | B75: SARANGANI | C75: =CONCATENATE("_",A75,"_",B75) -> _1280_SARANGANI
A76: 1298 | B76: COTABATO_CITY_(Not_a_Province) | C76: =CONCATENATE("_",A76,"_",B76) -> _1298_COTABATO_CITY_(Not_a_Province)
A78: NCR
A79: 1339 | B79: NCR,_CITY_OF_MANILA,_FIRST_DISTRICT_(Not_a_Province) | C79: =CONCATENATE("_",A79,"_",B79) -> _1339_NCR,_CITY_OF_MANILA,_FIRST_DISTRICT_(Not_a_Province)
A80: 1374 | B80: NCR,_SECOND_DISTRICT_(Not_a_Province) | C80: =CONCATENATE("_",A80,"_",B80) -> _1374_NCR,_SECOND_DISTRICT_(Not_a_Province)
A81: 1375 | B81: NCR,_THIRD_DISTRICT_(Not_a_Province) | C81: =CONCATENATE("_",A81,"_",B81) -> _1375_NCR,_THIRD_DISTRICT_(Not_a_Province)
A82: 1376 | B82: NCR,_FOURTH_DISTRICT_(Not_a_Province) | C82: =CONCATENATE("_",A82,"_",B82) -> _1376_NCR,_FOURTH_DISTRICT_(Not_a_Province)
A84: CAR
A85: 1401 | B85: ABRA | C85: =CONCATENATE("_",A85,"_",B85) -> _1401_ABRA
A86: 1411 | B86: BENGUET | C86: =CONCATENATE("_",A86,"_",B86) -> _1411_BENGUET
A87: 1427 | B87: IFUGAO | C87: =CONCATENATE("_",A87,"_",B87) -> _1427_IFUGAO
A88: 1432 | B88: KALINGA | C88: =CONCATENATE("_",A88,"_",B88) -> _1432_KALINGA
A89: 1444 | B89: MOUNTAIN_PROVINCE | C89: =CONCATENATE("_",A89,"_",B89) -> _1444_MOUNTAIN_PROVINCE
A90: 1481 | B90: APAYAO | C90: =CONCATENATE("_",A90,"_",B90) -> _1481_APAYAO
A92: BARMM
A93: 1507 | B93: BASILAN | C93: =CONCATENATE("_",A93,"_",B93) -> _1507_BASILAN
A94: 1536 | B94: LANAO_DEL_SUR | C94: =CONCATENATE("_",A94,"_",B94) -> _1536_LANAO_DEL_SUR
A95: 1538 | B95: MAGUINDANAO | C95: =CONCATENATE("_",A95,"_",B95) -> _1538_MAGUINDANAO
A96: 1566 | B96: SULU | C96: =CONCATENATE("_",A96,"_",B96) -> _1566_SULU
A97: 1570 | B97: TAWI_TAWI | C97: =CONCATENATE("_",A97,"_",B97) -> _1570_TAWI_TAWI
A99: CARAGA
A100: 1602 | B100: AGUSAN_DEL_NORTE | C100: =CONCATENATE("_",A100,"_",B100) -> _1602_AGUSAN_DEL_NORTE
A101: 1603 | B101: AGUSAN_DEL_SUR | C101: =CONCATENATE("_",A101,"_",B101) -> _1603_AGUSAN_DEL_SUR
A102: 1667 | B102: SURIGAO_DEL_NORTE | C102: =CONCATENATE("_",A102,"_",B102) -> _1667_SURIGAO_DEL_NORTE
A103: 1668 | B103: SURIGAO_DEL_SUR | C103: =CONCATENATE("_",A103,"_",B103) -> _1668_SURIGAO_DEL_SUR
A104: 1685 | B104: DINAGAT_ISLANDS | C104: =CONCATENATE("_",A104,"_",B104) -> _1685_DINAGAT_ISLANDS
A106: MIMAROPA
A107: 1740 | B107: MARINDUQUE | C107: =CONCATENATE("_",A107,"_",B107) -> _1740_MARINDUQUE
A108: 1751 | B108: OCCIDENTAL_MINDORO | C108: =CONCATENATE("_",A108,"_",B108) -> _1751_OCCIDENTAL_MINDORO
A109: 1752 | B109: ORIENTAL_MINDORO | C109: =CONCATENATE("_",A109,"_",B109) -> _1752_ORIENTAL_MINDORO
A110: 1753 | B110: PALAWAN | C110: =CONCATENATE("_",A110,"_",B110) -> _1753_PALAWAN
A111: 1759 | B111: ROMBLON | C111: =CONCATENATE("_",A111,"_",B111) -> _1759_ROMBLON

Sheet Province
A1: 01_Ilocos | B1: 02_Cagayan_Valley | C1: 03_Central_Luzon | D1: 04_CALABARZON | E1: 05_Bicol_Region | F1: 06_Western_Visayas | G1: 07_Central_Visayas | H1: 08_Eastern_Visayas | I1: 09_Zamboanga_Peninsula | J1: 10_Northern_Mindanao | K1: 11_Davao_Region | L1: 12_Soccsksargen | M1: 13_National_Capital_Region | N1: 14_Cordillera_Administrative_Region | O1: 15_Bangsamoro_Autonomous_Region_in_Muslim_Mindanao | P1: 16_CARAGA | Q1: 17_MIMAROPA
A2: 0128_ILOCOS_NORTE | B2: A | C2: E | D2: I | E2: M | F2: Q | G2: U | H2: Y | I2: CC | J2: GG | K2: KK | L2: OO | M2: SS | N2: WW | O2: AAA | P2: EEE | Q2: III
A3: 0129_ILOCOS_SUR | B3: B | C3: F | D3: J | E3: N | F3: R | G3: V | H3: Z | I3: DD | J3: HH | K3: LL | L3: PP | M3: TT | N3: XX | O3: BBB | P3: FFF | Q3: JJJ
A4: 0133_LA_UNION | B4: C | C4: G | D4: K | E4: O | F4: S | G4: W | H4: AA | I4: EE | J4: II | K4: MM | L4: QQ | M4: UU | N4: YY | O4: CCC | P4: GGG | Q4: KKK
A5: 0155_PANGASINAN | B5: D | C5: H | D5: L | E5: P | F5: T | G5: X | H5: BB | I5: FF | J5: JJ | K5: NN | L5: RR | M5: VV | N5: ZZ | O5: DDD | P5: HHH | Q5: LLL
A9: Ilocos | B9: _0128_ILOCOS_NORTE | C9: _0129_ILOCOS_SUR | D9: _0133_LA_UNION | E9: _0155_PANGASINAN
A10: CagayanValley | B10: _0209_BATANES | C10: _0215_CAGAYAN | D10: _0231_ISABELA | E10: _0250_NUEVA_VIZCAYA | F10: _0257_QUIRINO
A11: CentralLuzon | B11: _0308_BATAAN | C11: _0314_BULACAN | D11: _0349_NUEVA_ECIJA | E11: _0354_PAMPANGA | F11: _0369_TARLAC | G11: _0371_ZAMBALES | H11: _0377_AURORA
A12: CALABARZON | B12: _0410_BATANGAS | C12: _0421_CAVITE | D12: _0434_LAGUNA | E12: _0456_QUEZON | F12: _0458_RIZAL
A13: BicolRegion | B13: _0505_ALBAY | C13: _0516_CAMARINES_NORTE | D13: _0517_CAMARINES_SUR | E13: _0520_CATANDUANES | F13: _0541_MASBATE | G13: _0562_SORSOGON
A14: WesternVisayas | B14: _0604_AKLAN | C14: _0606_ANTIQUE | D14: _0619_CAPIZ | E14: _0630_ILOILO | F14: _0679_GUIMARAS | G14: _0645_NEGROS_OCCIDENTAL
A15: CentralVisayas | B15: _0712_BOHOL | C15: _0722_CEBU | D15: _0761_SIQUIJOR | E15: _0746_NEGROS_ORIENTAL
A16: EasternVisayas | B16: _0826_EASTERN_SAMAR | C16: _0837_LEYTE | D16: _0848_NORTHERN_SAMAR | E16: _0860_SAMAR_WESTERN_SAMAR | F16: _0864_SOUTHERN_LEYTE | G16: _0878_BILIRAN
A17: ZamboangaPeninsula | B17: _0972_ZAMBOANGA_DEL_NORTE | C17: _0973_ZAMBOANGA_DEL_SUR | D17: _0983_ZAMBOANGA_SIBUGAY | E17: _0997_CITY_OF_ISABELA
A18: NorthernMindanao | B18: _1013_BUKIDNON | C18: _1018_CAMIGUIN | D18: _1035_LANAO_DEL_NORTE | E18: _1042_MISAMIS_OCCIDENTAL | F18: _1043_MISAMIS_ORIENTAL
A19: DavaoRegion | B19: _1123_DAVAO_DEL_NORTE | C19: _1124_DAVAO_DEL_SUR | D19: _1125_DAVAO_ORIENTAL | E19: _1182_COMPOSTELA_VALLEY | F19: _1186_DAVAO_OCCIDENTAL
A20: Soccsksargen | B20: _1247_NORTH_COTABATO | C20: _1263_SOUTH_COTABATO | D20: _1265_SULTAN_KUDARAT | E20: _1280_SARANGANI | F20: _1298_COTABATO_CITY
A21: NationalCapitalRegion | B21: _1339_NCR_CITY_OF_MANILA_FIRST_DISTRICT | C21: _1374_NCR_SECOND_DISTRICT | D21: _1375_NCR_THIRD_DISTRICT | E21: _1376_NCR_FOURTH_DISTRICT
A22: CordilleraAdministrativeRegion | B22: _1401_ABRA | C22: _1411_BENGUET | D22: _1427_IFUGAO | E22: _1432_KALINGA | F22: _1444_MOUNTAIN_PROVINCE | G22: _1481_APAYAO
A23: BangsamoroAutonomousRegioninMuslimMindanao | B23: _1507_BASILAN | C23: _1536_LANAO_DEL_SUR | D23: _1538_MAGUINDANAO | E23: _1566_SULU | F23: _1570_TAWI_TAWI
A24: CARAGA | B24: _1602_AGUSAN_DEL_NORTE | C24: _1603_AGUSAN_DEL_SUR | D24: _1667_SURIGAO_DEL_NORTE | E24: _1668_SURIGAO_DEL_SUR | F24: _1685_DINAGAT_ISLANDS
A25: MIMAROPA | B25: _1740_MARINDUQUE | C25: _1751_OCCIDENTAL_MINDORO | D25: _1752_ORIENTAL_MINDORO | E25: _1753_PALAWAN | F25: _1759_ROMBLON
B27: _0128_ILOCOS_NORTE | C27: _0129_ILOCOS_SUR | D27: _0133_LA_UNION | E27: _0155_PANGASINAN
B28: _0209_BATANES | C28: _0215_CAGAYAN | D28: _0231_ISABELA | E28: _0250_NUEVA_VIZCAYA | F28: _0257_QUIRINO
B29: _0308_BATAAN | C29: _0314_BULACAN | D29: _0349_NUEVA_ECIJA | E29: _0354_PAMPANGA | F29: _0369_TARLAC | G29: _0371_ZAMBALES | H29: _0377_AURORA
B30: _0410_BATANGAS | C30: _0421_CAVITE | D30: _0434_LAGUNA | E30: _0456_QUEZON | F30: _0458_RIZAL
B31: _0505_ALBAY | C31: _0516_CAMARINES_NORTE | D31: _0517_CAMARINES_SUR | E31: _0520_CATANDUANES | F31: _0541_MASBATE | G31: _0562_SORSOGON
B32: _0604_AKLAN | C32: _0606_ANTIQUE | D32: _0619_CAPIZ | E32: _0630_ILOILO | F32: _0679_GUIMARAS | G32: _0645_NEGROS_OCCIDENTAL
B33: _0712_BOHOL | C33: _0722_CEBU | D33: _0761_SIQUIJOR | E33: _0746_NEGROS_ORIENTAL
B34: _0826_EASTERN_SAMAR | C34: _0837_LEYTE | D34: _0848_NORTHERN_SAMAR | E34: _0860_SAMAR_WESTERN_SAMAR | F34: _0864_SOUTHERN_LEYTE | G34: _0878_BILIRAN
B35: _0972_ZAMBOANGA_DEL_NORTE | C35: _0973_ZAMBOANGA_DEL_SUR | D35: _0983_ZAMBOANGA_SIBUGAY | E35: _0997_CITY_OF_ISABELA_(Not_a_Province)
B36: _1013_BUKIDNON | C36: _1018_CAMIGUIN | D36: _1035_LANAO_DEL_NORTE | E36: _1042_MISAMIS_OCCIDENTAL | F36: _1043_MISAMIS_ORIENTAL
B37: _1123_DAVAO_DEL_NORTE | C37: _1124_DAVAO_DEL_SUR | D37: _1125_DAVAO_ORIENTAL | E37: _1182_COMPOSTELA_VALLEY | F37: _1186_DAVAO_OCCIDENTAL
B38: _1247_COTABATO_(NORTH_COTABATO) | C38: _1263_SOUTH_COTABATO | D38: _1265_SULTAN_KUDARAT | E38: _1280_SARANGANI | F38: _1298_COTABATO_CITY_(Not_a_Province)
B39: _1339_NCR,_CITY_OF_MANILA,_FIRST_DISTRICT_(Not_a_Province) | C39: _1374_NCR,_SECOND_DISTRICT_(Not_a_Province) | D39: _1375_NCR,_THIRD_DISTRICT_(Not_a_Province) | E39: NCR,_FOURTH_DISTRICT_(Not_a_Province)
B40: _1401_ABRA | C40: _1411_BENGUET | D40: _1427_IFUGAO | E40: _1432_KALINGA | F40: _1444_MOUNTAIN_PROVINCE | G40: _1481_APAYAO
B41: _1507_BASILAN | C41: _1536_LANAO_DEL_SUR | D41: _1538_MAGUINDANAO | E41: _1566_SULU | F41: _1570_TAWI_TAWI
B42: _1602_AGUSAN_DEL_NORTE | C42: _1603_AGUSAN_DEL_SUR | D42: _1667_SURIGAO_DEL_NORTE | E42: _1668_SURIGAO_DEL_SUR | F42: _1685_DINAGAT_ISLANDS
B43: _1740_MARINDUQUE | C43: _1751_OCCIDENTAL_MINDORO | D43: _1752_ORIENTAL_MINDORO | E43: _1753_PALAWAN | F43: _1759_ROMBLON

Sheet bakuna center
A1: _1401_ABRA | B1: _1602_AGUSAN_DEL_NORTE | C1: _0604_AKLAN | D1: _0505_ALBAY | E1: _0606_ANTIQUE | F1: _1481_APAYAO | G1: _0377_AURORA | H1: _1507_BASILAN | I1: _0308_BATAAN | J1: _0209_BATANES | K1: _0410_BATANGAS | L1: _1411_BENGUET | M1: _0878_BILIRAN | N1: _0712_BOHOL | O1: _1013_BUKIDNON | P1: _0314_BULACAN | Q1: _0215_CAGAYAN | R1: _0516_CAMARINES_NORTE | S1: _0517_CAMARINES_SUR | T1: _1018_CAMIGUIN | U1: _0619_CAPIZ | V1: _0520_CATANDUANES | W1: _0421_CAVITE | X1: _0722_CEBU | Y1: _0997_CITY_OF_ISABELA | Z1: _1247_NORTH_COTABATO | AA1: _1298_COTABATO_CITY | AB1: _1182_COMPOSTELA_VALLEY | AC1: _1123_DAVAO_DEL_NORTE | AD1: _1124_DAVAO_DEL_SUR | AE1: _1186_DAVAO_OCCIDENTAL | AF1: _1125_DAVAO_ORIENTAL | AG1: _1685_DINAGAT_ISLANDS | AH1: _0826_EASTERN_SAMAR | AI1: _0679_GUIMARAS | AJ1: _1427_IFUGAO | AK1: _0128_ILOCOS_NORTE | AL1: _0129_ILOCOS_SUR | AM1: _0630_ILOILO | AN1: _0231_ISABELA | AO1: _1432_KALINGA | AP1: _0133_LA_UNION | AQ1: _0434_LAGUNA | AR1: _1035_LANAO_DEL_NORTE | AS1: _1536_LANAO_DEL_SUR | AT1: _0837_LEYTE | AU1: _1538_MAGUINDANAO | AV1: _1740_MARINDUQUE | AW1: _0541_MASBATE | AX1: _1042_MISAMIS_OCCIDENTAL | AY1: _1043_MISAMIS_ORIENTAL | AZ1: _1444_MOUNTAIN_PROVINCE | BA1: _1339_NCR_CITY_OF_MANILA_FIRST_DISTRICT | BB1: _1374_NCR_SECOND_DISTRICT | BC1: _1375_NCR_THIRD_DISTRICT | BD1: _1376_NCR_FOURTH_DISTRICT | BE1: _0645_NEGROS_OCCIDENTAL | BF1: _0746_NEGROS_ORIENTAL | BG1: _0848_NORTHERN_SAMAR | BH1: _0349_NUEVA_ECIJA | BI1: _0250_NUEVA_VIZCAYA | BJ1: _1751_OCCIDENTAL_MINDORO | BK1: _1752_ORIENTAL_MINDORO | BL1: _1753_PALAWAN | BM1: _0354_PAMPANGA | BN1: _0155_PANGASINAN | BO1: _0456_QUEZON | BP1: _0257_QUIRINO | BQ1: _0458_RIZAL | BR1: _1759_ROMBLON | BS1: _0860_SAMAR_WESTERN_SAMAR | BT1: _1280_SARANGANI | BU1: _0761_SIQUIJOR | BV1: _0562_SORSOGON | BW1: _1263_SOUTH_COTABATO | BX1: _0864_SOUTHERN_LEYTE | BY1: _1265_SULTAN_KUDARAT | BZ1: _1566_SULU | CA1: _1667_SURIGAO_DEL_NORTE | CB1: _1668_SURIGAO_DEL_SUR | CC1: _0369_TARLAC | CD1: _1570_TAWI_TAWI | CE1: _0371_ZAMBALES | CF1: _0972_ZAMBOANGA_DEL_NORTE | CG1: _0973_ZAMBOANGA_DEL_SUR | CH1: _0983_ZAMBOANGA_SIBUGAY
A2: CBC000000000003619 | B2: CBC000000000002202 | C2: CBC000000000003441 | D2: CBC000000000002053 | E2: CBC000000000004715 | F2: CBC000000000004646 | G2: CBC000000000003166 | H2: CBC000000000004144 | I2: CBC000000000003152 | J2: CBC000000000001956 | K2: CBC000000000005414 | L2: CBC000000000003654 | M2: CBC000000000005051 | N2: CBC000000000000033 | O2: CBC000000000001890 | P2: CBC000000000002752 | Q2: CBC000000000004907 | R2: CBC000000000001924 | S2: CBC000000000000958 | T2: CBC000000000001496 | U2: CBC000000000004220 | V2: CBC000000000001063 | W2: CBC000000000003551 | X2: CBC000000000001090 | Y2: CBC000000000005409 | Z2: CBC000000000002040 | AA2: CBC000000000002128 | AB2: CBC000000000002868 | AC2: CBC000000000002013 | AD2: CBC000000000002742 | AE2: CBC000000000002606 | AF2: CBC000000000004528 | AG2: CBC000000000001077 | AH2: CBC000000000003750 | AI2: CBC000000000005492 | AJ2: CBC000000000005431 | AK2: CBC000000000000064 | AL2: CBC000000000000164 | AM2: CBC000000000004082 | AN2: CBC000000000002933 | AO2: CBC000000000005299 | AP2: CBC000000000005257 | AQ2: CBC000000000004991 | AR2: CBC000000000001199 | AS2: CBC000000000004443 | AT2: CBC000000000003957 | AU2: CBC000000000004222 | AV2: CBC000000000004694 | AW2: CBC000000000001735 | AX2: CBC000000000002408 | AY2: CBC000000000005521 | AZ2: CBC000000000002775 | BA2: CBC000000000001611 | BB2: CBC000000000003001 | BC2: CBC000000000000495 | BD2: CBC000000000003063 | BE2: CBC000000000003544 | BF2: CBC000000000004542 | BG2: CBC000000000005545 | BH2: CBC000000000003181 | BI2: CBC000000000002629 | BJ2: CBC000000000005281 | BK2: CBC000000000005372 | BL2: CBC000000000004142 | BM2: CBC000000000004943 | BN2: CBC000000000002968 | BO2: CBC000000000003368 | BP2: CBC000000000000575 | BQ2: CBC000000000002378 | BR2: CBC000000000004062 | BS2: CBC000000000003108 | BT2: CBC000000000002919 | BU2: CBC000000000004754 | BV2: CBC000000000001886 | BW2: CBC000000000003042 | BX2: CBC000000000003253 | BY2: CBC000000000002516 | BZ2: CBC000000000003607 | CA2: CBC000000000000906 | CB2: CBC000000000003647 | CC2: CBC000000000002436 | CD2: CBC000000000004132 | CE2: CBC000000000003439 | CF2: CBC000000000004533 | CG2: CBC000000000004211 | CH2: CBC000000000001935
A3: CBC000000000000737 | B3: CBC000000000001733 | C3: CBC000000000003086 | D3: CBC000000000001316 | E3: CBC000000000004814 | F3: CBC000000000001514 | G3: CBC000000000004930 | H3: CBC000000000004433 | I3: CBC000000000003154 | J3: CBC000000000001960 | K3: CBC000000000005417 | L3: CBC000000000001561 | M3: CBC000000000002299 | N3: CBC000000000000036 | O3: CBC000000000001893 | P3: CBC000000000005462 | Q3: CBC000000000002873 | R3: CBC000000000001457 | S3: CBC000000000001348 | T3: CBC000000000002396 | U3: CBC000000000004044 | V3: CBC000000000001563 | W3: CBC000000000004312 | X3: CBC000000000001855 | Y3: CBC000000000001235 | Z3: CBC000000000003393 | AA3: CBC000000000002126 | AB3: CBC000000000003497 | AC3: CBC000000000002766 | AD3: CBC000000000002218 | AE3: CBC000000000003162 | AF3: CBC000000000002032 | AG3: CBC000000000000977 | AH3: CBC000000000003969 | AI3: CBC000000000003415 | AJ3: CBC000000000000935 | AK3: CBC000000000000079 | AL3: CBC000000000000226 | AM3: CBC000000000004666 | AN3: CBC000000000001718 | AO3: CBC000000000005285 | AP3: CBC000000000000180 | AQ3: CBC000000000005520 | AR3: CBC000000000003478 | AS3: CBC000000000004815 | AT3: CBC000000000005250 | AU3: CBC000000000004581 | AV3: CBC000000000004696 | AW3: CBC000000000001760 | AX3: CBC000000000001897 | AY3: CBC000000000003447 | AZ3: CBC000000000004254 | BA3: CBC000000000001606 | BB3: CBC000000000003310 | BC3: CBC000000000000891 | BD3: CBC000000000002732 | BE3: CBC000000000003897 | BF3: CBC000000000000588 | BG3: CBC000000000005531 | BH3: CBC000000000002426 | BI3: CBC000000000000464 | BJ3: CBC000000000004493 | BK3: CBC000000000005373 | BL3: CBC000000000005174 | BM3: CBC000000000004112 | BN3: CBC000000000000066 | BO3: CBC000000000003380 | BP3: CBC000000000001537 | BQ3: CBC000000000002380 | BR3: CBC000000000004360 | BS3: CBC000000000004032 | BT3: CBC000000000002897 | BU3: CBC000000000002384 | BV3: CBC000000000001113 | BW3: CBC000000000002847 | BX3: CBC000000000003254 | BY3: CBC000000000002019 | BZ3: CBC000000000003825 | CA3: CBC000000000000640 | CB3: CBC000000000004681 | CC3: CBC000000000005049 | CD3: CBC000000000004164 | CE3: CBC000000000003384 | CF3: CBC000000000002452 | CG3: CBC000000000005510 | CH3: CBC000000000002529
A4: CBC000000000000739 | B4: CBC000000000001761 | C4: CBC000000000004858 | D4: CBC000000000001469 | E4: CBC000000000003717 | F4: CBC000000000003646 | G4: CBC000000000004931 | H4: CBC000000000004441 | I4: CBC000000000003710 | J4: CBC000000000000883 | K4: CBC000000000003065 | L4: CBC000000000001560 | M4: CBC000000000003113 | N4: CBC000000000000037 | O4: CBC000000000002591 | P4: CBC000000000003484 | Q4: CBC000000000002214 | R4: CBC000000000001553 | S4: CBC000000000000762 | T4: CBC000000000001907 | U4: CBC000000000003672 | V4: CBC000000000001031 | W4: CBC000000000003487 | X4: CBC000000000005125 | Y4: CBC000000000005403 | Z4: CBC000000000004210 | AA4: CBC000000000002135 | AB4: CBC000000000002229 | AC4: CBC000000000003889 | AD4: CBC000000000003391 | AE4: CBC000000000002580 | AF4: CBC000000000003010 | AG4: CBC000000000001488 | AH4: CBC000000000002920 | AI4: CBC000000000003408 | AJ4: CBC000000000000931 | AK4: CBC000000000000080 | AL4: CBC000000000001799 | AM4: CBC000000000004577 | AN4: CBC000000000001557 | AO4: CBC000000000005297 | AP4: CBC000000000003313 | AQ4: CBC000000000004714 | AR4: CBC000000000003235 | AS4: CBC000000000004788 | AT4: CBC000000000003814 | AU4: CBC000000000004861 | AV4: CBC000000000004975 | AW4: CBC000000000000802 | AX4: CBC000000000003047 | AY4: CBC000000000001091 | AZ4: CBC000000000003075 | BA4: CBC000000000001630 | BB4: CBC000000000002448 | BC4: CBC000000000004693 | BD4: CBC000000000000884 | BE4: CBC000000000004287 | BF4: CBC000000000004969 | BG4: CBC000000000002419 | BH4: CBC000000000005480 | BI4: CBC000000000000439 | BJ4: CBC000000000004494 | BK4: CBC000000000005370 | BL4: CBC000000000004952 | BM4: CBC000000000005539 | BN4: CBC000000000000063 | BO4: CBC000000000003530 | BP4: CBC000000000001575 | BQ4: CBC000000000002368 | BR4: CBC000000000004363 | BS4: CBC000000000004027 | BT4: CBC000000000002894 | BU4: CBC000000000004742 | BV4: CBC000000000001804 | BW4: CBC000000000003623 | BX4: CBC000000000002849 | BY4: CBC000000000002735 | BZ4: CBC000000000003836 | CA4: CBC000000000001285 | CB4: CBC000000000001082 | CC4: CBC000000000005263 | CD4: CBC000000000004145 | CE4: CBC000000000003400 | CF4: CBC000000000002455 | CG4: CBC000000000004538 | CH4: CBC000000000002838
A5: CBC000000000004130 | B5: CBC000000000001762 | C5: CBC000000000003117 | D5: CBC000000000001397 | E5: CBC000000000004338 | F5: CBC000000000001548 | G5: CBC000000000004932 | H5: CBC000000000003866 | I5: CBC000000000002751 | J5: CBC000000000001950 | K5: CBC000000000004896 | L5: CBC000000000003665 | M5: CBC000000000002609 | N5: CBC000000000005124 | O5: CBC000000000002582 | P5: CBC000000000002750 | Q5: CBC000000000004335 | R5: CBC000000000001874 | S5: CBC000000000001768 | T5: CBC000000000001512 | U5: CBC000000000004037 | V5: CBC000000000001787 | W5: CBC000000000003527 | X5: CBC000000000000013 | Y5: CBC000000000005412 | Z5: CBC000000000001968 | AA5: CBC000000000002162 | AB5: CBC000000000002222 | AC5: CBC000000000003890 | AD5: CBC000000000003243 | AE5: CBC000000000002034 | AF5: CBC000000000003016 | AG5: CBC000000000000814 | AH5: CBC000000000002071 | AI5: CBC000000000004009 | AJ5: CBC000000000005103 | AK5: CBC000000000000083 | AL5: CBC000000000005452 | AM5: CBC000000000003282 | AN5: CBC000000000002208 | AO5: CBC000000000002275 | AP5: CBC000000000003206 | AQ5: CBC000000000004184 | AR5: CBC000000000001246 | AS5: CBC000000000004774 | AT5: CBC000000000004074 | AU5: CBC000000000004624 | AV5: CBC000000000004636 | AW5: CBC000000000000842 | AX5: CBC000000000002189 | AY5: CBC000000000001660 | AZ5: CBC000000000002770 | BA5: CBC000000000004203 | BB5: CBC000000000002874 | BC5: CBC000000000000438 | BD5: CBC000000000002459 | BE5: CBC000000000003548 | BF5: CBC000000000000617 | BG5: CBC000000000002420 | BH5: CBC000000000005153 | BI5: CBC000000000000429 | BJ5: CBC000000000004489 | BK5: CBC000000000005243 | BL5: CBC000000000005175 | BM5: CBC000000000004790 | BN5: CBC000000000000067 | BO5: CBC000000000005109 | BP5: CBC000000000000435 | BQ5: CBC000000000002355 | BR5: CBC000000000004460 | BS5: CBC000000000005018 | BT5: CBC000000000002898 | BU5: CBC000000000004739 | BV5: CBC000000000001808 | BW5: CBC000000000002858 | BX5: CBC000000000002883 | BY5: CBC000000000002057 | BZ5: CBC000000000003742 | CA5: CBC000000000000913 | CB5: CBC000000000001508 | CC5: CBC000000000002330 | CD5: CBC000000000004128 | CE5: CBC000000000003374 | CF5: CBC000000000002458 | CG5: CBC000000000000355 | CH5: CBC000000000003260
A6: CBC000000000000741 | B6: CBC000000000000649 | C6: CBC000000000004830 | D6: CBC000000000001367 | E6: CBC000000000004237 | F6: CBC000000000001529 | G6: CBC000000000004933 | H6: CBC000000000004423 | I6: CBC000000000002686 | J6: CBC000000000005338 | K6: CBC000000000005254 | L6: CBC000000000002117 | M6: CBC000000000003115 | N6: CBC000000000005155 | O6: CBC000000000002599 | P6: CBC000000000003783 | Q6: CBC000000000005388 | R6: CBC000000000001884 | S6: CBC000000000001717 | T6: CBC000000000002398 | U6: CBC000000000003650 | V6: CBC000000000001389 | W6: CBC000000000003519 | X6: CBC000000000000028 | Y6: CBC000000000000633 | Z6: CBC000000000002716 | AA6: CBC000000000002157 | AB6: CBC000000000002223 | AC6: CBC000000000003891 | AD6: CBC000000000005095 | AE6: CBC000000000002659 | AF6: CBC000000000003018 | AG6: CBC000000000000895 | AH6: CBC000000000003751 | AI6: CBC000000000004201 | AJ6: CBC000000000000947 | AK6: CBC000000000000088 | AL6: CBC000000000005457 | AM6: CBC000000000004954 | AN6: CBC000000000001859 | AO6: CBC000000000002273 | AP6: CBC000000000003208 | AQ6: CBC000000000003351 | AR6: CBC000000000002414 | AS6: CBC000000000004768 | AT6: CBC000000000003849 | AU6: CBC000000000004276 | AV6: CBC000000000004105 | AW6: CBC000000000001766 | AX6: CBC000000000002188 | AY6: CBC000000000001515 | AZ6: CBC000000000004393 | BA6: CBC000000000002166 | BB6: CBC000000000001980 | BC6: CBC000000000000486 | BD6: CBC000000000001770 | BE6: CBC000000000003780 | BF6: CBC000000000002327 | BG6: CBC000000000002402 | BH6: CBC000000000003512 | BI6: CBC000000000000516 | BJ6: CBC000000000004456 | BK6: CBC000000000005244 | BL6: CBC000000000004893 | BM6: CBC000000000003503 | BN6: CBC000000000000069 | BO6: CBC000000000003385 | BP6: CBC000000000000619 | BQ6: CBC000000000002381 | BR6: CBC000000000004480 | BS6: CBC000000000003698 | BT6: CBC000000000002902 | BU6: CBC000000000004755 | BV6: CBC000000000001706 | BW6: CBC000000000004087 | BX6: CBC000000000003239 | BY6: CBC000000000002553 | BZ6: CBC000000000003839 | CA6: CBC000000000000920 | CB6: CBC000000000000701 | CC6: CBC000000000003671 | CD6: CBC000000000004116 | CE6: CBC000000000003375 | CF6: CBC000000000002491 | CG6: CBC000000000000367 | CH6: CBC000000000001866
A7: CBC000000000000744 | B7: CBC000000000001783 | C7: CBC000000000004827 | D7: CBC000000000000991 | E7: CBC000000000004750 | F7: CBC000000000004951 | G7: CBC000000000004934 | H7: CBC000000000004427 | I7: CBC000000000002678 | J7: CBC000000000001957 | K7: CBC000000000002818 | L7: CBC000000000002268 | M7: CBC000000000003122 | N7: CBC000000000000040 | O7: CBC000000000001800 | P7: CBC000000000004897 | Q7: CBC000000000002793 | R7: CBC000000000001295 | S7: CBC000000000001333 | T7: CBC000000000001507 | U7: CBC000000000003649 | V7: CBC000000000001725 | W7: CBC000000000002979 | X7: CBC000000000001946 | Y7: CBC000000000000607 | Z7: CBC000000000002560 | AA7: CBC000000000002154 | AB7: CBC000000000002224 | AC7: CBC000000000003886 | AD7: CBC000000000005298 | AE7: CBC000000000002573 | AF7: CBC000000000003019 | AG7: CBC000000000000728 | AH7: CBC000000000002942 | AI7: CBC000000000003353 | AJ7: CBC000000000005327 | AK7: CBC000000000000090 | AL7: CBC000000000005481 | AM7: CBC000000000004569 | AN7: CBC000000000001948 | AO7: CBC000000000002282 | AP7: CBC000000000000177 | AQ7: CBC000000000004190 | AR7: CBC000000000001608 | AS7: CBC000000000004430 | AT7: CBC000000000003772 | AU7: CBC000000000004607 | AV7: CBC000000000004639 | AW7: CBC000000000001833 | AX7: CBC000000000000792 | AY7: CBC000000000001260 | AZ7: CBC000000000002778 | BA7: CBC000000000001534 | BB7: CBC000000000003427 | BC7: CBC000000000000285 | BD7: CBC000000000004829 | BE7: CBC000000000003550 | BF7: CBC000000000005007 | BG7: CBC000000000002841 | BH7: CBC000000000003702 | BI7: CBC000000000005056 | BJ7: CBC000000000005387 | BK7: CBC000000000004394 | BL7: CBC000000000004583 | BM7: CBC000000000003634 | BN7: CBC000000000000074 | BO7: CBC000000000003964 | BP7: CBC000000000001861 | BQ7: CBC000000000002359 | BR7: CBC000000000005221 | BS7: CBC000000000003699 | BT7: CBC000000000002903 | BU7: CBC000000000004751 | BV7: CBC000000000001085 | BW7: CBC000000000004101 | BX7: CBC000000000003496 | BY7: CBC000000000002100 | BZ7: CBC000000000004198 | CA7: CBC000000000003628 | CB7: CBC000000000001449 | CC7: CBC000000000003068 | CD7: CBC000000000004136 | CE7: CBC000000000003003 | CF7: CBC000000000002464 | CG7: CBC000000000001169 | CH7: CBC000000000000760
A8: CBC000000000000748 | B8: CBC000000000002095 | C8: CBC000000000004076 | D8: CBC000000000001180 | E8: CBC000000000002650 | F8: CBC000000000001522 | G8: CBC000000000004929 | H8: CBC000000000004439 | I8: CBC000000000002684 | J8: CBC000000000005332 | K8: CBC000000000005394 | L8: CBC000000000002266 | M8: CBC000000000003175 | N8: CBC000000000000041 | O8: CBC000000000004367 | P8: CBC000000000004879 | Q8: CBC000000000005316 | R8: CBC000000000001309 | S8: CBC000000000001495 | T8: CBC000000000002399 | U8: CBC000000000002416 | V8: CBC000000000001395 | W8: CBC000000000005283 | X8: CBC000000000004214 | Y8: CBC000000000000627 | Z8: CBC000000000002562 | AA8: CBC000000000003312 | AB8: CBC000000000002225 | AC8: CBC000000000002091 | AD8: CBC000000000002910 | AE8: CBC000000000002731 | AF8: CBC000000000003021 | AG8: CBC000000000001723 | AH8: CBC000000000002993 | AI8: CBC000000000003459 | AJ8: CBC000000000004839 | AK8: CBC000000000000126 | AL8: CBC000000000005483 | AM8: CBC000000000005062 | AN8: CBC000000000002109 | AO8: CBC000000000002298 | AP8: CBC000000000003314 | AQ8: CBC000000000004187 | AR8: CBC000000000005382 | AS8: CBC000000000003645 | AT8: CBC000000000004843 | AU8: CBC000000000004737 | AV8: CBC000000000004110 | AW8: CBC000000000001836 | AX8: CBC000000000000841 | AY8: CBC000000000001220 | AZ8: CBC000000000002819 | BA8: CBC000000000001696 | BB8: CBC000000000003892 | BC8: CBC000000000000310 | BD8: CBC000000000000846 | BE8: CBC000000000004429 | BF8: CBC000000000004997 | BG8: CBC000000000005525 | BH8: CBC000000000003185 | BI8: CBC000000000004387 | BJ8: CBC000000000004485 | BK8: CBC000000000005371 | BL8: CBC000000000004884 | BM8: CBC000000000003371 | BN8: CBC000000000003986 | BO8: CBC000000000003542 | BP8: CBC000000000000445 | BQ8: CBC000000000002338 | BR8: CBC000000000004461 | BS8: CBC000000000004736 | BT8: CBC000000000002928 | BU8: CBC000000000002382 | BV8: CBC000000000001409 | BW8: CBC000000000002861 | BX8: CBC000000000002272 | BY8: CBC000000000002550 | BZ8: CBC000000000003837 | CA8: CBC000000000000738 | CB8: CBC000000000004523 | CC8: CBC000000000002318 | CD8: CBC000000000004141 | CE8: CBC000000000002159 | CF8: CBC000000000002496 | CG8: CBC000000000000968 | CH8: CBC000000000000772
A9: CBC000000000003469 | B9: CBC000000000001182 | C9: CBC000000000004088 | D9: CBC000000000001406 | E9: CBC000000000004894 | F9: CBC000000000001536 | G9: CBC000000000004935 | H9: CBC000000000004434 | I9: CBC000000000003140 | J9: CBC000000000001899 | K9: CBC000000000004677 | L9: CBC000000000001562 | M9: CBC000000000003146 | N9: CBC000000000005193 | O9: CBC000000000002592 | P9: CBC000000000003787 | Q9: CBC000000000002066 | R9: CBC000000000001320 | S9: CBC000000000000936 | T9: CBC000000000001478 | U9: CBC000000000003674 | V9: CBC000000000001359 | W9: CBC000000000004966 | X9: CBC000000000005389 | Z9: CBC000000000002206 | AA9: CBC000000000002163 | AB9: CBC000000000002226 | AC9: CBC000000000004040 | AD9: CBC000000000002824 | AE9: CBC000000000002729 | AF9: CBC000000000003025 | AG9: CBC000000000000585 | AH9: CBC000000000002938 | AJ9: CBC000000000005158 | AK9: CBC000000000000102 | AL9: CBC000000000005487 | AM9: CBC000000000005088 | AN9: CBC000000000001930 | AO9: CBC000000000002279 | AP9: CBC000000000000172 | AQ9: CBC000000000004179 | AR9: CBC000000000001162 | AS9: CBC000000000003648 | AT9: CBC000000000003798 | AU9: CBC000000000003920 | AV9: CBC000000000004697 | AW9: CBC000000000001853 | AX9: CBC000000000002191 | AY9: CBC000000000001214 | AZ9: CBC000000000002862 | BA9: CBC000000000001576 | BB9: CBC000000000002878 | BC9: CBC000000000000273 | BD9: CBC000000000002713 | BE9: CBC000000000003657 | BF9: CBC000000000003229 | BG9: CBC000000000003612 | BH9: CBC000000000004854 | BI9: CBC000000000000582 | BJ9: CBC000000000004491 | BK9: CBC000000000004741 | BL9: CBC000000000004584 | BM9: CBC000000000003232 | BN9: CBC000000000000077 | BO9: CBC000000000003073 | BP9: CBC000000000001981 | BQ9: CBC000000000002372 | BR9: CBC000000000005225 | BS9: CBC000000000004740 | BT9: CBC000000000003102 | BU9: CBC000000000000632 | BV9: CBC000000000001903 | BW9: CBC000000000002864 | BX9: CBC000000000005293 | BY9: CBC000000000002301 | BZ9: CBC000000000003248 | CA9: CBC000000000003633 | CB9: CBC000000000000717 | CC9: CBC000000000002328 | CD9: CBC000000000004168 | CE9: CBC000000000003528 | CF9: CBC000000000002460 | CG9: CBC000000000000524 | CH9: CBC000000000000325
A10: CBC000000000004129 | B10: CBC000000000003245 | C10: CBC000000000004797 | D10: CBC000000000001335 | E10: CBC000000000004773 | F10: CBC000000000001540 | G10: CBC000000000004938 | H10: CBC000000000004165 | I10: CBC000000000003160 | J10: CBC000000000000880 | K10: CBC000000000002804 | L10: CBC000000000004197 | M10: CBC000000000003449 | N10: CBC000000000000565 | O10: CBC000000000001801 | P10: CBC000000000003789 | Q10: CBC000000000004617 | R10: CBC000000000001376 | S10: CBC000000000001902 | T10: CBC000000000001523 | U10: CBC000000000003675 | V10: CBC000000000001102 | W10: CBC000000000005303 | X10: CBC000000000005191 | Z10: CBC000000000002865 | AA10: CBC000000000002127 | AB10: CBC000000000002228 | AC10: CBC000000000002083 | AD10: CBC000000000004059 | AE10: CBC000000000002570 | AF10: CBC000000000003028 | AG10: CBC000000000004272 | AH10: CBC000000000003975 | AJ10: CBC000000000005330 | AK10: CBC000000000000103 | AL10: CBC000000000005491 | AM10: CBC000000000004552 | AN10: CBC000000000001798 | AO10: CBC000000000002296 | AP10: CBC000000000000163 | AQ10: CBC000000000004837 | AR10: CBC000000000001278 | AS10: CBC000000000004401 | AT10: CBC000000000003800 | AU10: CBC000000000004730 | AV10: CBC000000000004976 | AW10: CBC000000000000888 | AX10: CBC000000000001004 | AY10: CBC000000000001262 | AZ10: CBC000000000004404 | BA10: CBC000000000001545 | BB10: CBC000000000002467 | BC10: CBC000000000000261 | BD10: CBC000000000002724 | BE10: CBC000000000003807 | BF10: CBC000000000003241 | BG10: CBC000000000005548 | BH10: CBC000000000004616 | BI10: CBC000000000005055 | BJ10: CBC000000000004490 | BK10: CBC000000000004002 | BL10: CBC000000000004587 | BM10: CBC000000000005418 | BN10: CBC000000000000365 | BO10: CBC000000000003414 | BP10: CBC000000000000504 | BQ10: CBC000000000002365 | BR10: CBC000000000004376 | BS10: CBC000000000003940 | BT10: CBC000000000002904 | BU10: CBC000000000000638 | BV10: CBC000000000001426 | BW10: CBC000000000003620 | BX10: CBC000000000005296 | BY10: CBC000000000003318 | BZ10: CBC000000000003830 | CA10: CBC000000000000448 | CB10: CBC000000000000821 | CC10: CBC000000000002310 | CD10: CBC000000000004177 | CE10: CBC000000000003386 | CF10: CBC000000000002481 | CG10: CBC000000000005067 | CH10: CBC000000000000364
A11: CBC000000000000754 | B11: CBC000000000001772 | C11: CBC000000000003262 | D11: CBC000000000001336 | E11: CBC000000000004820 | F11: CBC000000000001543 | G11: CBC000000000004939 | H11: CBC000000000004183 | I11: CBC000000000003165 | J11: CBC000000000001953 | K11: CBC000000000005434 | L11: CBC000000000001589 | M11: CBC000000000003136 | N11: CBC000000000005428 | O11: CBC000000000002572 | P11: CBC000000000003795 | Q11: CBC000000000002530 | R11: CBC000000000001399 | S11: CBC000000000001904 | T11: CBC000000000003784 | U11: CBC000000000002703 | V11: CBC000000000001034 | W11: CBC000000000002690 | X11: CBC000000000005374 | Z11: CBC000000000002544 | AA11: CBC000000000002131 | AB11: CBC000000000002230 | AC11: CBC000000000002093 | AD11: CBC000000000004072 | AE11: CBC000000000002726 | AF11: CBC000000000002096 | AG11: CBC000000000000643 | AH11: CBC000000000003761 | AJ11: CBC000000000004948 | AK11: CBC000000000000108 | AL11: CBC000000000005454 | AM11: CBC000000000005211 | AN11: CBC000000000002633 | AO11: CBC000000000005278 | AP11: CBC000000000000157 | AQ11: CBC000000000004253 | AR11: CBC000000000001604 | AS11: CBC000000000004573 | AT11: CBC000000000003803 | AU11: CBC000000000004213 | AV11: CBC000000000004285 | AW11: CBC000000000003716 | AX11: CBC000000000001024 | AY11: CBC000000000001267 | AZ11: CBC000000000003935 | BA11: CBC000000000001625 | BB11: CBC000000000003505 | BC11: CBC000000000000278 | BD11: CBC000000000002465 | BE11: CBC000000000004821 | BF11: CBC000000000003227 | BG11: CBC000000000004571 | BH11: CBC000000000004648 | BI11: CBC000000000000599 | BJ11: CBC000000000004911 | BK11: CBC000000000004146 | BL11: CBC000000000004618 | BM11: CBC000000000004067 | BN11: CBC000000000003389 | BO11: CBC000000000003515 | BQ11: CBC000000000002341 | BR11: CBC000000000004156 | BS11: CBC000000000002893 | BT11: CBC000000000002906 | BU11: CBC000000000002014 | BV11: CBC000000000001417 | BW11: CBC000000000002867 | BX11: CBC000000000002583 | BY11: CBC000000000002302 | BZ11: CBC000000000003777 | CA11: CBC000000000000665 | CB11: CBC000000000000673 | CC11: CBC000000000005039 | CD11: CBC000000000004174 | CE11: CBC000000000003493 | CF11: CBC000000000002470 | CG11: CBC000000000001270 | CH11: CBC000000000000555
A12: CBC000000000004131 | B12: CBC000000000001769 | C12: CBC000000000003249 | D12: CBC000000000001339 | E12: CBC000000000004868 | G12: CBC000000000004928 | H12: CBC000000000003872 | I12: CBC000000000003167 | J12: CBC000000000001781 | K12: CBC000000000005503 | L12: CBC000000000001564 | N12: CBC000000000001754 | O12: CBC000000000001649 | P12: CBC000000000003813 | Q12: CBC000000000004436 | R12: CBC000000000001407 | S12: CBC000000000001905 | T12: CBC000000000003792 | U12: CBC000000000003677 | V12: CBC000000000001721 | W12: CBC000000000002954 | X12: CBC000000000005306 | Z12: CBC000000000003879 | AA12: CBC000000000002158 | AB12: CBC000000000002231 | AC12: CBC000000000002073 | AD12: CBC000000000004389 | AE12: CBC000000000002655 | AF12: CBC000000000002039 | AG12: CBC000000000001702 | AH12: CBC000000000002926 | AJ12: CBC000000000005336 | AK12: CBC000000000000110 | AL12: CBC000000000000100 | AM12: CBC000000000005063 | AN12: CBC000000000002106 | AO12: CBC000000000005284 | AP12: CBC000000000003189 | AQ12: CBC000000000004958 | AR12: CBC000000000001173 | AS12: CBC000000000004803 | AT12: CBC000000000003419 | AU12: CBC000000000003929 | AV12: CBC000000000004640 | AW12: CBC000000000000896 | AX12: CBC000000000001000 | AY12: CBC000000000001254 | AZ12: CBC000000000003939 | BA12: CBC000000000004598 | BB12: CBC000000000002739 | BC12: CBC000000000000447 | BD12: CBC000000000002167 | BE12: CBC000000000004570 | BF12: CBC000000000002313 | BG12: CBC000000000005546 | BH12: CBC000000000005498 | BI12: CBC000000000001827 | BJ12: CBC000000000004910 | BK12: CBC000000000005245 | BL12: CBC000000000005176 | BM12: CBC000000000002449 | BN12: CBC000000000000312 | BO12: CBC000000000003537 | BQ12: CBC000000000002364 | BR12: CBC000000000005230 | BS12: CBC000000000003026 | BT12: CBC000000000003104 | BU12: CBC000000000000636 | BV12: CBC000000000001906 | BW12: CBC000000000004091 | BX12: CBC000000000003592 | BY12: CBC000000000002444 | BZ12: CBC000000000003781 | CA12: CBC000000000000600 | CB12: CBC000000000001118 | CC12: CBC000000000002505 | CD12: CBC000000000004180 | CE12: CBC000000000003535 | CF12: CBC000000000002473 | CG12: CBC000000000004926 | CH12: CBC000000000001146
A13: CBC000000000000759 | B13: CBC000000000002200 | C13: CBC000000000004775 | D13: CBC000000000001342 | E13: CBC000000000004361 | G13: CBC000000000004940 | H13: CBC000000000004155 | I13: CBC000000000003954 | J13: CBC000000000000921 | K13: CBC000000000005420 | L13: CBC000000000001568 | N13: CBC000000000000039 | O13: CBC000000000002525 | P13: CBC000000000004891 | Q13: CBC000000000002011 | R13: CBC000000000001411 | S13: CBC000000000002425 | T13: CBC000000000001909 | U13: CBC000000000003678 | V13: CBC000000000001301 | W13: CBC000000000005184 | X13: CBC000000000001985 | Z13: CBC000000000005569 | AA13: CBC000000000002130 | AB13: CBC000000000002232 | AC13: CBC000000000002227 | AD13: CBC000000000002826 | AE13: CBC000000000002667 | AF13: CBC000000000004521 | AG13: CBC000000000000608 | AH13: CBC000000000004848 | AJ13: CBC000000000004918 | AK13: CBC000000000000116 | AL13: CBC000000000000130 | AM13: CBC000000000004371 | AN13: CBC000000000002665 | AO13: CBC000000000004119 | AP13: CBC000000000000154 | AQ13: CBC000000000004920 | AR13: CBC000000000001126 | AS13: CBC000000000004799 | AT13: CBC000000000004835 | AU13: CBC000000000004777 | AV13: CBC000000000004315 | AW13: CBC000000000000898 | AX13: CBC000000000001010 | AY13: CBC000000000001204 | AZ13: CBC000000000003910 | BA13: CBC000000000001524 | BB13: CBC000000000003194 | BC13: CBC000000000000457 | BD13: CBC000000000002439 | BE13: CBC000000000003552 | BF13: CBC000000000004995 | BG13: CBC000000000002329 | BH13: CBC000000000003179 | BI13: CBC000000000000578 | BJ13: CBC000000000003666 | BK13: CBC000000000004688 | BL13: CBC000000000004840 | BN13: CBC000000000000082 | BO13: CBC000000000003524 | BQ13: CBC000000000004973 | BR13: CBC000000000004157 | BS13: CBC000000000004021 | BT13: CBC000000000003173 | BU13: CBC000000000002030 | BV13: CBC000000000001435 | BW13: CBC000000000003087 | BX13: CBC000000000003595 | BY13: CBC000000000001964 | BZ13: CBC000000000003786 | CA13: CBC000000000000647 | CB13: CBC000000000005024 | CC13: CBC000000000005099 | CD13: CBC000000000004169 | CE13: CBC000000000003432 | CF13: CBC000000000002469 | CG13: CBC000000000000956 | CH13: CBC000000000000757
A14: CBC000000000000763 | B14: CBC000000000001765 | C14: CBC000000000003433 | D14: CBC000000000001354 | E14: CBC000000000004903 | G14: CBC000000000004927 | H14: CBC000000000004103 | I14: CBC000000000003170 | J14: CBC000000000000885 | K14: CBC000000000002656 | L14: CBC000000000001594 | N14: CBC000000000001923 | O14: CBC000000000002523 | P14: CBC000000000005446 | Q14: CBC000000000002342 | R14: CBC000000000001424 | S14: CBC000000000001384 | T14: CBC000000000001493 | U14: CBC000000000003653 | V14: CBC000000000001125 | W14: CBC000000000002325 | X14: CBC000000000000017 | Z14: CBC000000000005560 | AA14: CBC000000000002140 | AB14: CBC000000000002234 | AC14: CBC000000000002049 | AD14: CBC000000000004024 | AE14: CBC000000000003168 | AF14: CBC000000000002037 | AH14: CBC000000000002768 | AJ14: CBC000000000005101 | AK14: CBC000000000000131 | AL14: CBC000000000000169 | AM14: CBC000000000004017 | AN14: CBC000000000002666 | AO14: CBC000000000004109 | AP14: CBC000000000000151 | AQ14: CBC000000000003621 | AR14: CBC000000000001597 | AS14: CBC000000000004549 | AT14: CBC000000000004836 | AU14: CBC000000000004580 | AV14: CBC000000000004641 | AW14: CBC000000000000745 | AX14: CBC000000000002258 | AY14: CBC000000000001247 | AZ14: CBC000000000002855 | BA14: CBC000000000001695 | BB14: CBC000000000003373 | BC14: CBC000000000000455 | BD14: CBC000000000003858 | BE14: CBC000000000004298 | BF14: CBC000000000002312 | BG14: CBC000000000003390 | BH14: CBC000000000002430 | BI14: CBC000000000000593 | BJ14: CBC000000000004486 | BK14: CBC000000000004608 | BL14: CBC000000000004588 | BN14: CBC000000000000084 | BO14: CBC000000000003741 | BQ14: CBC000000000003893 | BR14: CBC000000000005217 | BS14: CBC000000000004993 | BT14: CBC000000000003103 | BU14: CBC000000000000024 | BV14: CBC000000000000965 | BW14: CBC000000000002852 | BX14: CBC000000000002211 | BY14: CBC000000000002006 | BZ14: CBC000000000003874 | CA14: CBC000000000000637 | CB14: CBC000000000001541 | CC14: CBC000000000002427 | CD14: CBC000000000004171 | CE14: CBC000000000003412 | CF14: CBC000000000002463 | CG14: CBC000000000001253 | CH14: CBC000000000000768
A15: CBC000000000000764 | B15: CBC000000000001763 | C15: CBC000000000003895 | D15: CBC000000000001174 | E15: CBC000000000004901 | G15: CBC000000000004941 | H15: CBC000000000004151 | I15: CBC000000000002688 | J15: CBC000000000000874 | K15: CBC000000000005366 | L15: CBC000000000001591 | N15: CBC000000000001018 | O15: CBC000000000001716 | P15: CBC000000000003971 | Q15: CBC000000000003101 | R15: CBC000000000001331 | S15: CBC000000000000867 | T15: CBC000000000002393 | U15: CBC000000000005023 | V15: CBC000000000001774 | W15: CBC000000000003998 | X15: CBC000000000002494 | Z15: CBC000000000002007 | AA15: CBC000000000002161 | AB15: CBC000000000002235 | AC15: CBC000000000004192 | AD15: CBC000000000003238 | AE15: CBC000000000003169 | AF15: CBC000000000005410 | AH15: CBC000000000002747 | AJ15: CBC000000000000938 | AK15: CBC000000000000132 | AL15: CBC000000000000251 | AM15: CBC000000000004596 | AN15: CBC000000000000546 | AO15: CBC000000000004122 | AP15: CBC000000000000148 | AQ15: CBC000000000003629 | AR15: CBC000000000002741 | AS15: CBC000000000004565 | AT15: CBC000000000004308 | AU15: CBC000000000004878 | AV15: CBC000000000004642 | AW15: CBC000000000000747 | AX15: CBC000000000002410 | AY15: CBC000000000001276 | AZ15: CBC000000000003915 | BA15: CBC000000000002514 | BB15: CBC000000000003308 | BC15: CBC000000000002143 | BD15: CBC000000000002720 | BE15: CBC000000000004048 | BF15: CBC000000000002322 | BG15: CBC000000000005163 | BH15: CBC000000000005566 | BI15: CBC000000000000559 | BJ15: CBC000000000005504 | BK15: CBC000000000004424 | BL15: CBC000000000005390 | BN15: CBC000000000003398 | BO15: CBC000000000004428 | BQ15: CBC000000000002347 | BR15: CBC000000000005215 | BS15: CBC000000000005005 | BT15: CBC000000000002909 | BU15: CBC000000000000628 | BV15: CBC000000000000752 | BW15: CBC000000000002660 | BX15: CBC000000000002002 | BY15: CBC000000000002969 | BZ15: CBC000000000003823 | CA15: CBC000000000000564 | CB15: CBC000000000000676 | CC15: CBC000000000002101 | CD15: CBC000000000004153 | CE15: CBC000000000003396 | CF15: CBC000000000002482 | CG15: CBC000000000001207 | CH15: CBC000000000003184
A16: CBC000000000000769 | B16: CBC000000000001755 | C16: CBC000000000003436 | D16: CBC000000000001410 | E16: CBC000000000004936 | G16: CBC000000000004942 | H16: CBC000000000004134 | I16: CBC000000000003135 | J16: CBC000000000005331 | K16: CBC000000000004536 | L16: CBC000000000003655 | N16: CBC000000000005447 | O16: CBC000000000001713 | P16: CBC000000000005444 | Q16: CBC000000000002061 | R16: CBC000000000001364 | S16: CBC000000000001661 | T16: CBC000000000001911 | U16: CBC000000000005295 | V16: CBC000000000005307 | W16: CBC000000000003977 | X16: CBC000000000002546 | Z16: CBC000000000002654 | AA16: CBC000000000002129 | AB16: CBC000000000002236 | AC16: CBC000000000004996 | AD16: CBC000000000002220 | AE16: CBC000000000002653 | AF16: CBC000000000003461 | AH16: CBC000000000003072 | AJ16: CBC000000000005333 | AK16: CBC000000000000134 | AL16: CBC000000000005391 | AM16: CBC000000000002661 | AN16: CBC000000000002639 | AO16: CBC000000000004084 | AP16: CBC000000000003315 | AQ16: CBC000000000003635 | AR16: CBC000000000001513 | AS16: CBC000000000003686 | AT16: CBC000000000004304 | AU16: CBC000000000004077 | AV16: CBC000000000004644 | AW16: CBC000000000000749 | AX16: CBC000000000002409 | AY16: CBC000000000001280 | AZ16: CBC000000000002776 | BA16: CBC000000000001633 | BB16: CBC000000000002589 | BC16: CBC000000000000318 | BD16: CBC000000000002727 | BE16: CBC000000000004050 | BF16: CBC000000000005003 | BG16: CBC000000000004215 | BH16: CBC000000000003290 | BI16: CBC000000000000528 | BJ16: CBC000000000004452 | BK16: CBC000000000004734 | BL16: CBC000000000005383 | BN16: CBC000000000003417 | BO16: CBC000000000003525 | BQ16: CBC000000000002374 | BR16: CBC000000000005203 | BS16: CBC000000000004018 | BT16: CBC000000000002915 | BU16: CBC000000000004746 | BV16: CBC000000000000727 | BW16: CBC000000000004330 | BX16: CBC000000000003593 | BY16: CBC000000000003540 | BZ16: CBC000000000003828 | CA16: CBC000000000001273 | CB16: CBC000000000000615 | CC16: CBC000000000002869 | CD16: CBC000000000004167 | CE16: CBC000000000003399 | CF16: CBC000000000002485 | CG16: CBC000000000000406
A17: CBC000000000000774 | B17: CBC000000000000951 | C17: CBC000000000003252 | D17: CBC000000000001431 | E17: CBC000000000004937 | G17: CBC000000000004372 | I17: CBC000000000002757 | J17: CBC000000000001737 | K17: CBC000000000005436 | L17: CBC000000000001566 | N17: CBC000000000005445 | O17: CBC000000000001714 | P17: CBC000000000005464 | Q17: CBC000000000002340 | R17: CBC000000000001879 | S17: CBC000000000001584 | T17: CBC000000000001619 | U17: CBC000000000003423 | V17: CBC000000000001079 | W17: CBC000000000004319 | X17: CBC000000000002548 | Z17: CBC000000000003884 | AB17: CBC000000000002237 | AC17: CBC000000000002555 | AD17: CBC000000000002891 | AF17: CBC000000000003106 | AH17: CBC000000000003980 | AJ17: CBC000000000000901 | AK17: CBC000000000000140 | AL17: CBC000000000000208 | AM17: CBC000000000004070 | AN17: CBC000000000001936 | AO17: CBC000000000005294 | AP17: CBC000000000003196 | AQ17: CBC000000000003632 | AR17: CBC000000000003460 | AS17: CBC000000000003615 | AT17: CBC000000000004313 | AU17: CBC000000000004798 | AV17: CBC000000000004699 | AW17: CBC000000000000775 | AX17: CBC000000000005308 | AY17: CBC000000000001185 | AZ17: CBC000000000002960 | BA17: CBC000000000004735 | BB17: CBC000000000003413 | BC17: CBC000000000000327 | BD17: CBC000000000001838 | BE17: CBC000000000004053 | BF17: CBC000000000002314 | BG17: CBC000000000003475 | BH17: CBC000000000003464 | BI17: CBC000000000005564 | BJ17: CBC000000000004138 | BK17: CBC000000000005154 | BL17: CBC000000000004613 | BN17: CBC000000000000168 | BO17: CBC000000000003507 | BQ17: CBC000000000002373 | BR17: CBC000000000005224 | BS17: CBC000000000003006 | BT17: CBC000000000002917 | BU17: CBC000000000000634 | BV17: CBC000000000001383 | BW17: CBC000000000004043 | BX17: CBC000000000002935 | BY17: CBC000000000002489 | BZ17: CBC000000000003876 | CA17: CBC000000000001294 | CB17: CBC000000000000835 | CC17: CBC000000000005402 | CD17: CBC000000000004166 | CE17: CBC000000000002199 | CF17: CBC000000000002495 | CG17: CBC000000000000289
A18: CBC000000000000780 | B18: CBC000000000000809 | C18: CBC000000000005505 | D18: CBC000000000001390 | E18: CBC000000000004962 | G18: CBC000000000004283 | I18: CBC000000000002682 | K18: CBC000000000003145 | L18: CBC000000000004578 | N18: CBC000000000005090 | O18: CBC000000000001715 | P18: CBC000000000004317 | Q18: CBC000000000003806 | R18: CBC000000000001882 | S18: CBC000000000000765 | T18: CBC000000000001614 | U18: CBC000000000003679 | V18: CBC000000000005329 | W18: CBC000000000003582 | X18: CBC000000000002547 | Z18: CBC000000000002045 | AB18: CBC000000000002238 | AC18: CBC000000000002557 | AD18: CBC000000000004175 | AF18: CBC000000000002036 | AH18: CBC000000000004632 | AJ18: CBC000000000005350 | AK18: CBC000000000000152 | AL18: CBC000000000000260 | AM18: CBC000000000002687 | AN18: CBC000000000001867 | AO18: CBC000000000005300 | AP18: CBC000000000000143 | AQ18: CBC000000000003637 | AR18: CBC000000000001014 | AS18: CBC000000000004778 | AT18: CBC000000000003791 | AU18: CBC000000000004853 | AV18: CBC000000000004977 | AW18: CBC000000000000778 | AX18: CBC000000000001933 | AY18: CBC000000000001238 | AZ18: CBC000000000003907 | BA18: CBC000000000004410 | BB18: CBC000000000005268 | BC18: CBC000000000002148 | BD18: CBC000000000002889 | BE18: CBC000000000004056 | BF18: CBC000000000005398 | BG18: CBC000000000003517 | BH18: CBC000000000004860 | BI18: CBC000000000002771 | BJ18: CBC000000000004492 | BK18: CBC000000000004450 | BL18: CBC000000000005156 | BN18: CBC000000000000086 | BO18: CBC000000000003112 | BQ18: CBC000000000002350 | BR18: CBC000000000005238 | BS18: CBC000000000004202 | BT18: CBC000000000004787 | BU18: CBC000000000000626 | BV18: CBC000000000001124 | BW18: CBC000000000004108 | BX18: CBC000000000002877 | BY18: CBC000000000002498 | BZ18: CBC000000000003833 | CA18: CBC000000000000596 | CB18: CBC000000000000822 | CC18: CBC000000000002483 | CD18: CBC000000000004160 | CE18: CBC000000000003401 | CF18: CBC000000000002490 | CG18: CBC000000000001442
A19: CBC000000000000786 | B19: CBC000000000002048 | C19: CBC000000000003215 | D19: CBC000000000001219 | E19: CBC000000000004902 | G19: CBC000000000004384 | I19: CBC000000000003159 | K19: CBC000000000004643 | L19: CBC000000000004689 | N19: CBC000000000000035 | O19: CBC000000000001802 | P19: CBC000000000002700 | Q19: CBC000000000002794 | R19: CBC000000000001925 | S19: CBC000000000001306 | T19: CBC000000000001472 | U19: CBC000000000004776 | V19: CBC000000000001026 | W19: CBC000000000005282 | X19: CBC000000000002549 | Z19: CBC000000000003388 | AB19: CBC000000000002239 | AC19: CBC000000000002536 | AD19: CBC000000000004547 | AF19: CBC000000000004805 | AH19: CBC000000000003056 | AJ19: CBC000000000000908 | AK19: CBC000000000000142 | AL19: CBC000000000000181 | AM19: CBC000000000005059 | AN19: CBC000000000001955 | AO19: CBC000000000002294 | AP19: CBC000000000004924 | AQ19: CBC000000000003624 | AR19: CBC000000000003712 | AS19: CBC000000000004770 | AT19: CBC000000000004326 | AU19: CBC000000000004035 | AV19: CBC000000000004309 | AW19: CBC000000000000782 | AX19: CBC000000000004530 | AY19: CBC000000000001195 | AZ19: CBC000000000004395 | BA19: CBC000000000004417 | BB19: CBC000000000002192 | BC19: CBC000000000000506 | BD19: CBC000000000003868 | BE19: CBC000000000004065 | BF19: CBC000000000001707 | BG19: CBC000000000002435 | BH19: CBC000000000004767 | BI19: CBC000000000005054 | BJ19: CBC000000000004496 | BK19: CBC000000000004459 | BL19: CBC000000000004888 | BN19: CBC000000000000089 | BO19: CBC000000000005119 | BQ19: CBC000000000002349 | BR19: CBC000000000004063 | BS19: CBC000000000002977 | BT19: CBC000000000003387 | BU19: CBC000000000000625 | BV19: CBC000000000001425 | BW19: CBC000000000004080 | BX19: CBC000000000003482 | BY19: CBC000000000002507 | BZ19: CBC000000000003870 | CA19: CBC000000000000548 | CB19: CBC000000000000539 | CC19: CBC000000000002511 | CD19: CBC000000000004125 | CE19: CBC000000000003382 | CF19: CBC000000000002476 | CG19: CBC000000000003137
A20: CBC000000000000849 | B20: CBC000000000002827 | C20: CBC000000000005507 | D20: CBC000000000002356 | E20: CBC000000000003492 | G20: CBC000000000004341 | I20: CBC000000000003150 | K20: CBC000000000002763 | L20: CBC000000000003656 | N20: CBC000000000005077 | O20: CBC000000000001805 | P20: CBC000000000005463 | Q20: CBC000000000001984 | R20: CBC000000000000871 | S20: CBC000000000001466 | T20: CBC000000000001915 | U20: CBC000000000003465 | V20: CBC000000000002644 | W20: CBC000000000004008 | X20: CBC000000000002551 | Z20: CBC000000000002783 | AB20: CBC000000000002240 | AC20: CBC000000000002415 | AF20: CBC000000000002042 | AH20: CBC000000000002908 | AJ20: CBC000000000000914 | AK20: CBC000000000000136 | AL20: CBC000000000000288 | AM20: CBC000000000002691 | AN20: CBC000000000000532 | AO20: CBC000000000004115 | AP20: CBC000000000003216 | AQ20: CBC000000000003616 | AR20: CBC000000000001362 | AS20: CBC000000000003611 | AT20: CBC000000000003944 | AU20: CBC000000000004228 | AV20: CBC000000000004328 | AW20: CBC000000000000783 | AX20: CBC000000000002177 | AY20: CBC000000000001228 | AZ20: CBC000000000003908 | BA20: CBC000000000004816 | BB20: CBC000000000001990 | BC20: CBC000000000000478 | BD20: CBC000000000003877 | BE20: CBC000000000004073 | BF20: CBC000000000004832 | BG20: CBC000000000004679 | BH20: CBC000000000002303 | BI20: CBC000000000002632 | BJ20: CBC000000000004487 | BK20: CBC000000000004078 | BL20: CBC000000000005352 | BN20: CBC000000000005449 | BO20: CBC000000000004057 | BQ20: CBC000000000002354 | BR20: CBC000000000005237 | BS20: CBC000000000002967 | BT20: CBC000000000005127 | BU20: CBC000000000000630 | BV20: CBC000000000001470 | BW20: CBC000000000003116 | BX20: CBC000000000003079 | BY20: CBC000000000002513 | BZ20: CBC000000000003840 | CA20: CBC000000000001268 | CB20: CBC000000000000702 | CC20: CBC000000000002787 | CE20: CBC000000000003379 | CF20: CBC000000000002486 | CG20: CBC000000000000978
A21: CBC000000000000851 | B21: CBC000000000000589 | C21: CBC000000000004411 | D21: CBC000000000000674 | E21: CBC000000000004819 | G21: CBC000000000004310 | I21: CBC000000000003149 | K21: CBC000000000004960 | L21: CBC000000000003881 | N21: CBC000000000005442 | O21: CBC000000000002617 | P21: CBC000000000005461 | Q21: CBC000000000001999 | R21: CBC000000000000878 | S21: CBC000000000001504 | T21: CBC000000000001617 | U21: CBC000000000004026 | V21: CBC000000000001852 | W21: CBC000000000003967 | X21: CBC000000000002123 | Z21: CBC000000000002422 | AB21: CBC000000000002242 | AC21: CBC000000000002535 | AF21: CBC000000000004527 | AH21: CBC000000000002813 | AJ21: CBC000000000000923 | AK21: CBC000000000000147 | AL21: CBC000000000000294 | AM21: CBC000000000004421 | AN21: CBC000000000002497 | AO21: CBC000000000005288 | AP21: CBC000000000003209 | AQ21: CBC000000000003610 | AR21: CBC000000000003174 | AS21: CBC000000000004585 | AT21: CBC000000000003949 | AU21: CBC000000000004357 | AV21: CBC000000000004322 | AW21: CBC000000000000784 | AX21: CBC000000000003043 | AY21: CBC000000000001153 | AZ21: CBC000000000002759 | BA21: CBC000000000005070 | BB21: CBC000000000001973 | BC21: CBC000000000000480 | BD21: CBC000000000002823 | BE21: CBC000000000004075 | BF21: CBC000000000002326 | BG21: CBC000000000003508 | BH21: CBC000000000002308 | BI21: CBC000000000000520 | BJ21: CBC000000000004495 | BK21: CBC000000000004477 | BL21: CBC000000000004591 | BN21: CBC000000000003410 | BO21: CBC000000000005451 | BQ21: CBC000000000002375 | BR21: CBC000000000004457 | BS21: CBC000000000005098 | BT21: CBC000000000002607 | BU21: CBC000000000000016 | BV21: CBC000000000001530 | BW21: CBC000000000004301 | BX21: CBC000000000002558 | BY21: CBC000000000002283 | BZ21: CBC000000000003841 | CA21: CBC000000000000604 | CB21: CBC000000000000699 | CC21: CBC000000000002219 | CE21: CBC000000000003430 | CF21: CBC000000000002479 | CG21: CBC000000000000349
A22: CBC000000000004241 | B22: CBC000000000000511 | C22: CBC000000000003142 | D22: CBC000000000001358 | E22: CBC000000000004731 | G22: CBC000000000003835 | I22: CBC000000000003156 | K22: CBC000000000005440 | L22: CBC000000000001570 | N22: CBC000000000000541 | O22: CBC000000000002575 | P22: CBC000000000003055 | Q22: CBC000000000002540 | R22: CBC000000000000875 | S22: CBC000000000000656 | T22: CBC000000000005541 | U22: CBC000000000003012 | V22: CBC000000000001344 | W22: CBC000000000005016 | X22: CBC000000000002124 | Z22: CBC000000000002844 | AB22: CBC000000000002243 | AC22: CBC000000000002050 | AF22: CBC000000000004518 | AH22: CBC000000000002916 | AJ22: CBC000000000005348 | AK22: CBC000000000000156 | AL22: CBC000000000000268 | AM22: CBC000000000004560 | AN22: CBC000000000003602 | AO22: CBC000000000005290 | AP22: CBC000000000003316 | AQ22: CBC000000000003658 | AR22: CBC000000000001773 | AS22: CBC000000000004791 | AT22: CBC000000000003950 | AU22: CBC000000000004784 | AV22: CBC000000000004325 | AW22: CBC000000000000788 | AX22: CBC000000000005425 | AY22: CBC000000000001165 | AZ22: CBC000000000004370 | BA22: CBC000000000002641 | BB22: CBC000000000002888 | BC22: CBC000000000000434 | BD22: CBC000000000000890 | BE22: CBC000000000004081 | BF22: CBC000000000000598 | BG22: CBC000000000004866 | BH22: CBC000000000005159 | BI22: CBC000000000001931 | BJ22: CBC000000000004488 | BK22: CBC000000000004458 | BL22: CBC000000000005178 | BN22: CBC000000000000179 | BO22: CBC000000000002675 | BQ22: CBC000000000002366 | BR22: CBC000000000004374 | BS22: CBC000000000002962 | BT22: CBC000000000002346 | BU22: CBC000000000002445 | BV22: CBC000000000001123 | BW22: CBC000000000002499 | BX22: CBC000000000003076 | BY22: CBC000000000002437 | BZ22: CBC000000000003845 | CA22: CBC000000000001910 | CB22: CBC000000000000857 | CC22: CBC000000000005397 | CE22: CBC000000000003483 | CF22: CBC000000000002478 | CG22: CBC000000000000322
A23: CBC000000000000854 | B23: CBC000000000001776 | C23: CBC000000000003244 | D23: CBC000000000001419 | E23: CBC000000000004251 | G23: CBC000000000003448 | I23: CBC000000000002685 | K23: CBC000000000003345 | L23: CBC000000000001573 | N23: CBC000000000005143 | O23: CBC000000000001894 | P23: CBC000000000003061 | Q23: CBC000000000003451 | R23: CBC000000000000675 | S23: CBC000000000001533 | T23: CBC000000000001283 | U23: CBC000000000003015 | V23: CBC000000000001059 | W23: CBC000000000004004 | X23: CBC000000000002125 | Z23: CBC000000000002194 | AB23: CBC000000000002245 | AC23: CBC000000000002256 | AF23: CBC000000000002043 | AH23: CBC000000000002974 | AJ23: CBC000000000005073 | AK23: CBC000000000002930 | AL23: CBC000000000000300 | AM23: CBC000000000002694 | AN23: CBC000000000001638 | AO23: CBC000000000002277 | AP23: CBC000000000000138 | AQ23: CBC000000000004181 | AR23: CBC000000000001599 | AS23: CBC000000000004579 | AT23: CBC000000000003947 | AU23: CBC000000000004280 | AV23: CBC000000000004106 | AW23: CBC000000000000789 | AX23: CBC000000000002185 | AY23: CBC000000000001177 | AZ23: CBC000000000003305 | BA23: CBC000000000004895 | BB23: CBC000000000003214 | BC23: CBC000000000000437 | BD23: CBC000000000003811 | BE23: CBC000000000004085 | BF23: CBC000000000000058 | BG23: CBC000000000004771 | BH23: CBC000000000004772 | BI23: CBC000000000005053 | BK23: CBC000000000004846 | BL23: CBC000000000004592 | BN23: CBC000000000000189 | BO23: CBC000000000003402 | BQ23: CBC000000000002360 | BR23: CBC000000000005226 | BS23: CBC000000000003024 | BT23: CBC000000000002352 | BU23: CBC000000000002009 | BV23: CBC000000000001518 | BW23: CBC000000000002388 | BX23: CBC000000000003258 | BY23: CBC000000000002363 | BZ23: CBC000000000003850 | CA23: CBC000000000000616 | CB23: CBC000000000000742 | CC23: CBC000000000003096 | CE23: CBC000000000003532 | CF23: CBC000000000002474 | CG23: CBC000000000000395
A24: CBC000000000000859 | B24: CBC000000000002098 | C24: CBC000000000004543 | D24: CBC000000000001200 | E24: CBC000000000004877 | G24: CBC000000000003970 | K24: CBC000000000004955 | L24: CBC000000000001581 | N24: CBC000000000000060 | O24: CBC000000000001796 | P24: CBC000000000002755 | Q24: CBC000000000001752 | R24: CBC000000000001392 | S24: CBC000000000001644 | T24: CBC000000000001912 | U24: CBC000000000003680 | V24: CBC000000000005322 | W24: CBC000000000003504 | X24: CBC000000000005115 | Z24: CBC000000000002209 | AB24: CBC000000000002246 | AC24: CBC000000000003668 | AF24: CBC000000000004519 | AH24: CBC000000000003695 | AJ24: CBC000000000000928 | AK24: CBC000000000002939 | AL24: CBC000000000000306 | AM24: CBC000000000002749 | AN24: CBC000000000001777 | AO24: CBC000000000005311 | AP24: CBC000000000003198 | AQ24: CBC000000000004097 | AR24: CBC000000000001261 | AS24: CBC000000000003366 | AT24: CBC000000000003948 | AU24: CBC000000000004795 | AV24: CBC000000000004700 | AW24: CBC000000000000790 | AX24: CBC000000000000816 | AY24: CBC000000000001499 | AZ24: CBC000000000003404 | BA24: CBC000000000001615 | BB24: CBC000000000005249 | BC24: CBC000000000000483 | BD24: CBC000000000003817 | BE24: CBC000000000004093 | BF24: CBC000000000005001 | BG24: CBC000000000004812 | BH24: CBC000000000003638 | BI24: CBC000000000000490 | BK24: CBC000000000005369 | BL24: CBC000000000004445 | BN24: CBC000000000000191 | BO24: CBC000000000005058 | BQ24: CBC000000000002561 | BR24: CBC000000000004481 | BS24: CBC000000000003578 | BT24: CBC000000000002901 | BU24: CBC000000000004744 | BV24: CBC000000000001509 | BW24: CBC000000000002038 | BX24: CBC000000000005287 | BY24: CBC000000000002552 | BZ24: CBC000000000003854 | CA24: CBC000000000001120 | CB24: CBC000000000000830 | CC24: CBC000000000002421 | CE24: CBC000000000003485 | CF24: CBC000000000000370 | CG24: CBC000000000003141
A25: CBC000000000000863 | B25: CBC000000000000750 | C25: CBC000000000003123 | D25: CBC000000000001414 | E25: CBC000000000004912 | G25: CBC000000000003182 | K25: CBC000000000004959 | L25: CBC000000000001577 | N25: CBC000000000005476 | O25: CBC000000000005375 | P25: CBC000000000003045 | Q25: CBC000000000001992 | R25: CBC000000000001528 | S25: CBC000000000001322 | T25: CBC000000000003812 | U25: CBC000000000003681 | V25: CBC000000000001111 | W25: CBC000000000005186 | X25: CBC000000000000703 | Z25: CBC000000000005524 | AB25: CBC000000000002247 | AC25: CBC000000000002672 | AF25: CBC000000000002015 | AH25: CBC000000000002805 | AJ25: CBC000000000005349 | AK25: CBC000000000002943 | AL25: CBC000000000000313 | AM25: CBC000000000002622 | AN25: CBC000000000001705 | AO25: CBC000000000005392 | AP25: CBC000000000003219 | AQ25: CBC000000000004083 | AR25: CBC000000000001181 | AS25: CBC000000000004765 | AT25: CBC000000000003945 | AU25: CBC000000000004786 | AV25: CBC000000000004979 | AW25: CBC000000000000791 | AX25: CBC000000000002940 | AY25: CBC000000000002387 | AZ25: CBC000000000001106 | BA25: CBC000000000001601 | BB25: CBC000000000004250 | BC25: CBC000000000000012 | BD25: CBC000000000001792 | BE25: CBC000000000004126 | BF25: CBC000000000005424 | BG25: CBC000000000002851 | BH25: CBC000000000004863 | BI25: CBC000000000004841 | BL25: CBC000000000004038 | BN25: CBC000000000000193 | BO25: CBC000000000005089 | BQ25: CBC000000000002559 | BR25: CBC000000000004064 | BS25: CBC000000000004006 | BT25: CBC000000000002895 | BU25: CBC000000000000635 | BV25: CBC000000000001547 | BW25: CBC000000000002808 | BX25: CBC000000000003495 | BY25: CBC000000000002457 | BZ25: CBC000000000003861 | CA25: CBC000000000000609 | CB25: CBC000000000000670 | CC25: CBC000000000004922 | CE25: CBC000000000002975 | CF25: CBC000000000000452 | CG25: CBC000000000000336
A26: CBC000000000000868 | B26: CBC000000000000746 | C26: CBC000000000003370 | D26: CBC000000000001093 | E26: CBC000000000004946 | G26: CBC000000000004925 | K26: CBC000000000004792 | L26: CBC000000000001585 | N26: CBC000000000005477 | O26: CBC000000000003275 | P26: CBC000000000003051 | Q26: CBC000000000002964 | R26: CBC000000000001549 | S26: CBC000000000000966 | T26: CBC000000000001913 | U26: CBC000000000003426 | V26: CBC000000000001135 | W26: CBC000000000002989 | X26: CBC000000000000704 | Z26: CBC000000000005526 | AB26: CBC000000000002251 | AC26: CBC000000000005289 | AF26: CBC000000000003124 | AH26: CBC000000000003785 | AJ26: CBC000000000004949 | AK26: CBC000000000003706 | AL26: CBC000000000000321 | AM26: CBC000000000004553 | AN26: CBC000000000004610 | AO26: CBC000000000005286 | AP26: CBC000000000003218 | AQ26: CBC000000000004118 | AR26: CBC000000000001693 | AS26: CBC000000000003951 | AT26: CBC000000000003943 | AU26: CBC000000000004225 | AV26: CBC000000000004274 | AW26: CBC000000000000793 | AX26: CBC000000000003364 | AY26: CBC000000000001377 | AZ26: CBC000000000002779 | BA26: CBC000000000001567 | BB26: CBC000000000002704 | BC26: CBC000000000000530 | BD26: CBC000000000003360 | BE26: CBC000000000004111 | BF26: CBC000000000004545 | BG26: CBC000000000004143 | BH26: CBC000000000005565 | BI26: CBC000000000000458 | BL26: CBC000000000004594 | BN26: CBC000000000000196 | BO26: CBC000000000005533 | BQ26: CBC000000000005536 | BR26: CBC000000000004462 | BS26: CBC000000000004046 | BT26: CBC000000000002912 | BU26: CBC000000000002379 | BV26: CBC000000000001444 | BW26: CBC000000000002669 | BX26: CBC000000000003083 | BY26: CBC000000000002005 | BZ26: CBC000000000003848 | CA26: CBC000000000000655 | CB26: CBC000000000001213 | CC26: CBC000000000002434 | CE26: CBC000000000003060 | CF26: CBC000000000000413 | CG26: CBC000000000000939
A27: CBC000000000000873 | B27: CBC000000000000623 | C27: CBC000000000004687 | D27: CBC000000000001127 | E27: CBC000000000004564 | G27: CBC000000000002289 | K27: CBC000000000005395 | L27: CBC000000000001587 | N27: CBC000000000001945 | O27: CBC000000000001251 | P27: CBC000000000003591 | Q27: CBC000000000002336 | R27: CBC000000000001212 | S27: CBC000000000001452 | T27: CBC000000000002394 | U27: CBC000000000002563 | V27: CBC000000000001103 | W27: CBC000000000003541 | X27: CBC000000000005362 | Z27: CBC000000000002719 | AB27: CBC000000000002249 | AC27: CBC000000000003888 | AF27: CBC000000000002094 | AH27: CBC000000000002835 | AJ27: CBC000000000004041 | AK27: CBC000000000003700 | AL27: CBC000000000000330 | AM27: CBC000000000004406 | AN27: CBC000000000004606 | AO27: CBC000000000005393 | AP27: CBC000000000000135 | AQ27: CBC000000000004968 | AR27: CBC000000000001314 | AS27: CBC000000000003670 | AT27: CBC000000000003946 | AU27: CBC000000000004550 | AV27: CBC000000000004275 | AW27: CBC000000000000795 | AX27: CBC000000000005514 | AY27: CBC000000000001659 | AZ27: CBC000000000001131 | BA27: CBC000000000001640 | BB27: CBC000000000003409 | BC27: CBC000000000000381 | BD27: CBC000000000003361 | BE27: CBC000000000005396 | BF27: CBC000000000004556 | BG27: CBC000000000003434 | BH27: CBC000000000005568 | BI27: CBC000000000000563 | BL27: CBC000000000004886 | BN27: CBC000000000000198 | BO27: CBC000000000005139 | BQ27: CBC000000000004986 | BR27: CBC000000000005239 | BS27: CBC000000000003274 | BT27: CBC000000000002923 | BU27: CBC000000000004747 | BV27: CBC000000000001412 | BW27: CBC000000000003131 | BX27: CBC000000000002879 | BY27: CBC000000000004172 | BZ27: CBC000000000004150 | CA27: CBC000000000001149 | CB27: CBC000000000000671 | CC27: CBC000000000002104 | CE27: CBC000000000002554 | CF27: CBC000000000002515 | CG27: CBC000000000005529
A28: CBC000000000000877 | B28: CBC000000000000472 | D28: CBC000000000001455 | E28: CBC000000000004759 | G28: CBC000000000003247 | K28: CBC000000000003961 | L28: CBC000000000004635 | N28: CBC000000000000034 | O28: CBC000000000005473 | P28: CBC000000000003040 | Q28: CBC000000000002059 | R28: CBC000000000001226 | S28: CBC000000000001623 | T28: CBC000000000001618 | U28: CBC000000000002579 | V28: CBC000000000001144 | W28: CBC000000000003559 | X28: CBC000000000005339 | Z28: CBC000000000002721 | AB28: CBC000000000002252 | AC28: CBC000000000005069 | AF28: CBC000000000002041 | AH28: CBC000000000003311 | AJ28: CBC000000000004554 | AK28: CBC000000000000161 | AL28: CBC000000000000188 | AM28: CBC000000000005506 | AN28: CBC000000000001961 | AO28: CBC000000000002278 | AP28: CBC000000000000133 | AQ28: CBC000000000004796 | AR28: CBC000000000001210 | AS28: CBC000000000003669 | AT28: CBC000000000004349 | AU28: CBC000000000004227 | AV28: CBC000000000004981 | AW28: CBC000000000000797 | AX28: CBC000000000005419 | AY28: CBC000000000001635 | AZ28: CBC000000000003909 | BA28: CBC000000000001621 | BB28: CBC000000000003005 | BC28: CBC000000000000510 | BD28: CBC000000000003869 | BE28: CBC000000000005408 | BF28: CBC000000000002307 | BG28: CBC000000000002401 | BH28: CBC000000000005144 | BI28: CBC000000000000476 | BL28: CBC000000000005368 | BN28: CBC000000000000201 | BO28: CBC000000000003516 | BQ28: CBC000000000004980 | BR28: CBC000000000005204 | BS28: CBC000000000005011 | BT28: CBC000000000002924 | BU28: CBC000000000001920 | BV28: CBC000000000001477 | BW28: CBC000000000002677 | BX28: CBC000000000002866 | BY28: CBC000000000002442 | BZ28: CBC000000000003856 | CA28: CBC000000000000590 | CB28: CBC000000000000669 | CC28: CBC000000000002105 | CE28: CBC000000000003405 | CF28: CBC000000000003743 | CG28: CBC000000000003143
A29: CBC000000000000879 | B29: CBC000000000001779 | D29: CBC000000000001250 | E29: CBC000000000004762 | G29: CBC000000000004261 | K29: CBC000000000003107 | L29: CBC000000000003661 | N29: CBC000000000005441 | O29: CBC000000000005413 | P29: CBC000000000005465 | Q29: CBC000000000002317 | R29: CBC000000000001141 | S29: CBC000000000000999 | T29: CBC000000000001483 | U29: CBC000000000003037 | V29: CBC000000000001571 | W29: CBC000000000003062 | X29: CBC000000000001767 | Z29: CBC000000000003425 | AB29: CBC000000000002254 | AC29: CBC000000000003708 | AF29: CBC000000000002616 | AH29: CBC000000000003428 | AJ29: CBC000000000005195 | AK29: CBC000000000000166 | AL29: CBC000000000005479 | AM29: CBC000000000004600 | AN29: CBC000000000001959 | AO29: CBC000000000002280 | AP29: CBC000000000003205 | AQ29: CBC000000000005280 | AR29: CBC000000000000919 | AS29: CBC000000000004544 | AT29: CBC000000000003756 | AU29: CBC000000000004766 | AV29: CBC000000000004647 | AW29: CBC000000000000800 | AX29: CBC000000000003362 | AY29: CBC000000000001510 | AZ29: CBC000000000004170 | BA29: CBC000000000002170 | BB29: CBC000000000002881 | BC29: CBC000000000000004 | BD29: CBC000000000003119 | BE29: CBC000000000004121 | BF29: CBC000000000005309 | BG29: CBC000000000005313 | BH29: CBC000000000003705 | BI29: CBC000000000000509 | BL29: CBC000000000005179 | BN29: CBC000000000000203 | BO29: CBC000000000002746 | BQ29: CBC000000000004974 | BR29: CBC000000000005205 | BS29: CBC000000000004020 | BU29: CBC000000000002385 | BV29: CBC000000000001494 | BW29: CBC000000000002925 | BX29: CBC000000000003642 | BY29: CBC000000000002521 | BZ29: CBC000000000003864 | CA29: CBC000000000000659 | CB29: CBC000000000000740 | CC29: CBC000000000004921 | CE29: CBC000000000002332 | CF29: CBC000000000005513 | CG29: CBC000000000005351
A30: CBC000000000004173 | B30: CBC000000000001758 | D30: CBC000000000003690 | E30: CBC000000000004764 | K30: CBC000000000003381 | L30: CBC000000000004623 | N30: CBC000000000003285 | O30: CBC000000000003201 | P30: CBC000000000002994 | Q30: CBC000000000002624 | R30: CBC000000000000979 | S30: CBC000000000001325 | T30: CBC000000000001914 | U30: CBC000000000002748 | V30: CBC000000000001574 | W30: CBC000000000003510 | X30: CBC000000000000705 | Z30: CBC000000000002648 | AB30: CBC000000000002253 | AC30: CBC000000000002081 | AF30: CBC000000000002022 | AH30: CBC000000000005141 | AJ30: CBC000000000000942 | AK30: CBC000000000000170 | AL30: CBC000000000000257 | AM30: CBC000000000004620 | AN30: CBC000000000000776 | AO30: CBC000000000002281 | AP30: CBC000000000003221 | AQ30: CBC000000000004186 | AR30: CBC000000000000785 | AS30: CBC000000000004825 | AT30: CBC000000000005508 | AU30: CBC000000000004872 | AV30: CBC000000000004316 | AW30: CBC000000000000801 | AX30: CBC000000000002404 | AY30: CBC000000000001657 | AZ30: CBC000000000001140 | BA30: CBC000000000001692 | BB30: CBC000000000002886 | BC30: CBC000000000000005 | BD30: CBC000000000003120 | BE30: CBC000000000004127 | BF30: CBC000000000004537 | BG30: CBC000000000005522 | BH30: CBC000000000005466 | BI30: CBC000000000000460 | BL30: CBC000000000003641 | BN30: CBC000000000000205 | BO30: CBC000000000005102 | BQ30: CBC000000000002376 | BR30: CBC000000000004033 | BS30: CBC000000000002982 | BU30: CBC000000000002450 | BV30: CBC000000000001538 | BW30: CBC000000000002056 | BX30: CBC000000000003640 | BY30: CBC000000000002003 | CA30: CBC000000000000440 | CB30: CBC000000000001546 | CC30: CBC000000000003630 | CE30: CBC000000000003158 | CF30: CBC000000000000347 | CG30: CBC000000000002198
A31: CBC000000000000887 | B31: CBC000000000004972 | D31: CBC000000000001129 | E31: CBC000000000003990 | K31: CBC000000000002890 | L31: CBC000000000001593 | N31: CBC000000000005194 | O31: CBC000000000004497 | P31: CBC000000000003180 | Q31: CBC000000000002643 | R31: CBC000000000001198 | S31: CBC000000000001405 | T31: CBC000000000001916 | U31: CBC000000000003682 | V31: CBC000000000001579 | W31: CBC000000000003574 | X31: CBC000000000000052 | Z31: CBC000000000005561 | AB31: CBC000000000002872 | AC31: CBC000000000002701 | AF31: CBC000000000002097 | AH31: CBC000000000003981 | AJ31: CBC000000000005092 | AK31: CBC000000000000190 | AL31: CBC000000000002033 | AM31: CBC000000000003071 | AN31: CBC000000000001694 | AO31: CBC000000000005301 | AP31: CBC000000000003317 | AQ31: CBC000000000004185 | AR31: CBC000000000002389 | AS31: CBC000000000004785 | AT31: CBC000000000003793 | AU31: CBC000000000004216 | AV31: CBC000000000004351 | AW31: CBC000000000000804 | AX31: CBC000000000001244 | AY31: CBC000000000001677 | AZ31: CBC000000000001161 | BA31: CBC000000000002190 | BB31: CBC000000000002884 | BC31: CBC000000000000368 | BD31: CBC000000000003121 | BE31: CBC000000000004337 | BF31: CBC000000000004971 | BH31: CBC000000000005567 | BI31: CBC000000000000591 | BL31: CBC000000000004593 | BN31: CBC000000000000206 | BO31: CBC000000000003134 | BQ31: CBC000000000002371 | BR31: CBC000000000004479 | BS31: CBC000000000002971 | BU31: CBC000000000004738 | BV31: CBC000000000001456 | BW31: CBC000000000003138 | BX31: CBC000000000002856 | CA31: CBC000000000000597 | CB31: CBC000000000000605 | CC31: CBC000000000002110 | CE31: CBC000000000003533 | CF31: CBC000000000004873 | CG31: CBC000000000003545
A32: CBC000000000000889 | B32: CBC000000000000667 | D32: CBC000000000001115 | E32: CBC000000000004745 | K32: CBC000000000005273 | L32: CBC000000000004680 | N32: CBC000000000005068 | O32: CBC000000000002758 | P32: CBC000000000004189 | Q32: CBC000000000002060 | R32: CBC000000000000729 | S32: CBC000000000001048 | T32: CBC000000000001622 | U32: CBC000000000002992 | V32: CBC000000000001580 | W32: CBC000000000005275 | X32: CBC000000000000650 | Z32: CBC000000000002848 | AB32: CBC000000000002876 | AC32: CBC000000000002082 | AF32: CBC000000000002099 | AH32: CBC000000000005259 | AK32: CBC000000000000068 | AL32: CBC000000000000085 | AM32: CBC000000000005160 | AN32: CBC000000000000576 | AO32: CBC000000000002300 | AP32: CBC000000000003207 | AQ32: CBC000000000004100 | AR32: CBC000000000001218 | AS32: CBC000000000003606 | AT32: CBC000000000004505 | AU32: CBC000000000003916 | AV32: CBC000000000004344 | AW32: CBC000000000000806 | AX32: CBC000000000005416 | AY32: CBC000000000001682 | AZ32: CBC000000000003643 | BA32: CBC000000000003614 | BB32: CBC000000000004418 | BC32: CBC000000000000376 | BD32: CBC000000000002358 | BE32: CBC000000000004347 | BF32: CBC000000000001749 | BH32: CBC000000000005384 | BI32: CBC000000000000587 | BL32: CBC000000000005180 | BN32: CBC000000000000209 | BO32: CBC000000000002664 | BQ32: CBC000000000005538 | BR32: CBC000000000004069 | BS32: CBC000000000002988 | BU32: CBC000000000002031 | BV32: CBC000000000001486 | BW32: CBC000000000003304 | BX32: CBC000000000003242 | CA32: CBC000000000005128 | CC32: CBC000000000002112 | CE32: CBC000000000003407 | CF32: CBC000000000005406 | CG32: CBC000000000000314
A33: CBC000000000000893 | B33: CBC000000000000777 | D33: CBC000000000001191 | E33: CBC000000000004743 | K33: CBC000000000005279 | L33: CBC000000000002274 | N33: CBC000000000000618 | O33: CBC000000000002621 | P33: CBC000000000005450 | Q33: CBC000000000002531 | R33: CBC000000000000805 | S33: CBC000000000001361 | T33: CBC000000000001613 | U33: CBC000000000003965 | V33: CBC000000000001583 | W33: CBC000000000005276 | X33: CBC000000000000642 | Z33: CBC000000000003627 | AB33: CBC000000000004193 | AC33: CBC000000000002250 | AF33: CBC000000000004834 | AH33: CBC000000000002905 | AK33: CBC000000000000072 | AL33: CBC000000000000254 | AM33: CBC000000000003894 | AN33: CBC000000000000645 | AO33: CBC000000000002305 | AP33: CBC000000000003319 | AQ33: CBC000000000004124 | AR33: CBC000000000002390 | AS33: CBC000000000004789 | AT33: CBC000000000003901 | AU33: CBC000000000004582 | AV33: CBC000000000004346 | AW33: CBC000000000000807 | AX33: CBC000000000002257 | AY33: CBC000000000001099 | AZ33: CBC000000000003932 | BA33: CBC000000000005528 | BB33: CBC000000000001998 | BC33: CBC000000000001328 | BD33: CBC000000000003824 | BE33: CBC000000000004354 | BF33: CBC000000000004540 | BH33: CBC000000000003704 | BI33: CBC000000000000493 | BL33: CBC000000000005181 | BN33: CBC000000000000211 | BO33: CBC000000000002446 | BQ33: CBC000000000005540 | BR33: CBC000000000004463 | BS33: CBC000000000004022 | BU33: CBC000000000002441 | BV33: CBC000000000001552 | BW33: CBC000000000002831 | BX33: CBC000000000003596 | CA33: CBC000000000000606 | CE33: CBC000000000003372 | CF33: CBC000000000004431 | CG33: CBC000000000000900
A34: CBC000000000004133 | B34: CBC000000000002103 | D34: CBC000000000001083 | E34: CBC000000000004828 | K34: CBC000000000002833 | L34: CBC000000000002270 | N34: CBC000000000001756 | O34: CBC000000000002565 | P34: CBC000000000005455 | Q34: CBC000000000003128 | R34: CBC000000000000990 | S34: CBC000000000001323 | T34: CBC000000000001519 | U34: CBC000000000002754 | V34: CBC000000000001133 | W34: CBC000000000005318 | X34: CBC000000000000646 | Z34: CBC000000000002566 | AB34: CBC000000000002293 | AC34: CBC000000000002244 | AF34: CBC000000000005542 | AH34: CBC000000000003455 | AK34: CBC000000000000075 | AL34: CBC000000000002018 | AM34: CBC000000000005065 | AN34: CBC000000000001963 | AO34: CBC000000000002287 | AP34: CBC000000000003320 | AQ34: CBC000000000005265 | AR34: CBC000000000001009 | AS34: CBC000000000003739 | AT34: CBC000000000004379 | AU34: CBC000000000004881 | AV34: CBC000000000004291 | AW34: CBC000000000000810 | AX34: CBC000000000002403 | AY34: CBC000000000001408 | AZ34: CBC000000000002773 | BA34: CBC000000000002475 | BB34: CBC000000000002142 | BC34: CBC000000000004913 | BD34: CBC000000000000860 | BE34: CBC000000000004359 | BF34: CBC000000000002319 | BH34: CBC000000000005468 | BI34: CBC000000000000543 | BL34: CBC000000000004961 | BN34: CBC000000000000213 | BO34: CBC000000000002737 | BQ34: CBC000000000002370 | BR34: CBC000000000005198 | BS34: CBC000000000003697 | BU34: CBC000000000000629 | BV34: CBC000000000001462 | BW34: CBC000000000005559 | BX34: CBC000000000003250 | CA34: CBC000000000000403 | CE34: CBC000000000003488 | CF34: CBC000000000005074 | CG34: CBC000000000003148
A35: CBC000000000000899 | B35: CBC000000000000562 | D35: CBC000000000001292 | E35: CBC000000000005012 | K35: CBC000000000005557 | L35: CBC000000000002265 | N35: CBC000000000005439 | O35: CBC000000000003157 | Q35: CBC000000000002065 | R35: CBC000000000001877 | S35: CBC000000000001724 | T35: CBC000000000003818 | U35: CBC000000000002753 | V35: CBC000000000001084 | W35: CBC000000000005353 | X35: CBC000000000000031 | Z35: CBC000000000002118 | AB35: CBC000000000002269 | AF35: CBC000000000002046 | AH35: CBC000000000002267 | AK35: CBC000000000000118 | AL35: CBC000000000003164 | AM35: CBC000000000002697 | AN35: CBC000000000001556 | AO35: CBC000000000004104 | AP35: CBC000000000003321 | AQ35: CBC000000000004845 | AR35: CBC000000000001257 | AS35: CBC000000000004817 | AT35: CBC000000000003801 | AU35: CBC000000000004219 | AV35: CBC000000000004302 | AW35: CBC000000000000812 | AX35: CBC000000000002407 | AY35: CBC000000000001678 | AZ35: CBC000000000003924 | BA35: CBC000000000005258 | BB35: CBC000000000002817 | BC35: CBC000000000000433 | BD35: CBC000000000003855 | BE35: CBC000000000004365 | BF35: CBC000000000003213 | BH35: CBC000000000005376 | BI35: CBC000000000001812 | BL35: CBC000000000004595 | BN35: CBC000000000000216 | BO35: CBC000000000003586 | BQ35: CBC000000000002369 | BR35: CBC000000000004464 | BS35: CBC000000000005030 | BU35: CBC000000000002447 | BV35: CBC000000000001688 | BW35: CBC000000000003038 | BX35: CBC000000000003246 | CA35: CBC000000000002255 | CF35: CBC000000000005021 | CG35: CBC000000000000407
B36: CBC000000000002102 | D36: CBC000000000001227 | E36: CBC000000000004915 | K36: CBC000000000005555 | L36: CBC000000000001596 | N36: CBC000000000005188 | O36: CBC000000000002577 | Q36: CBC000000000002538 | R36: CBC000000000000989 | S36: CBC000000000000937 | T36: CBC000000000001917 | U36: CBC000000000003683 | V36: CBC000000000001186 | W36: CBC000000000005317 | X36: CBC000000000001086 | Z36: CBC000000000003987 | AB36: CBC000000000002333 | AF36: CBC000000000004525 | AH36: CBC000000000005140 | AK36: CBC000000000000222 | AL36: CBC000000000000335 | AM36: CBC000000000002698 | AN36: CBC000000000002626 | AP36: CBC000000000003199 | AQ36: CBC000000000003259 | AR36: CBC000000000002084 | AS36: CBC000000000004757 | AT36: CBC000000000003757 | AU36: CBC000000000004231 | AV36: CBC000000000004327 | AW36: CBC000000000000817 | AX36: CBC000000000001976 | AY36: CBC000000000001491 | AZ36: CBC000000000003925 | BA36: CBC000000000003472 | BB36: CBC000000000003009 | BC36: CBC000000000002138 | BD36: CBC000000000003857 | BE36: CBC000000000004042 | BF36: CBC000000000002028 | BH36: CBC000000000005379 | BI36: CBC000000000000473 | BL36: CBC000000000004405 | BN36: CBC000000000000218 | BO36: CBC000000000003564 | BQ36: CBC000000000002353 | BR36: CBC000000000004158 | BS36: CBC000000000003279 | BU36: CBC000000000002021 | BV36: CBC000000000001704 | BW36: CBC000000000002233 | BX36: CBC000000000002196 | CA36: CBC000000000001155 | CF36: CBC000000000003694 | CG36: CBC000000000000503
B37: CBC000000000000574 | D37: CBC000000000001175 | K37: CBC000000000005556 | L37: CBC000000000002260 | N37: CBC000000000000055 | O37: CBC000000000001269 | Q37: CBC000000000003462 | R37: CBC000000000001112 | S37: CBC000000000000944 | T37: CBC000000000001454 | U37: CBC000000000003445 | V37: CBC000000000001744 | W37: CBC000000000003994 | X37: CBC000000000001983 | Z37: CBC000000000002564 | AB37: CBC000000000002344 | AF37: CBC000000000002782 | AH37: CBC000000000002122 | AK37: CBC000000000000223 | AL37: CBC000000000000194 | AM37: CBC000000000005453 | AN37: CBC000000000002627 | AP37: CBC000000000003211 | AQ37: CBC000000000004161 | AR37: CBC000000000001053 | AS37: CBC000000000003625 | AT37: CBC000000000004364 | AU37: CBC000000000004898 | AV37: CBC000000000004278 | AW37: CBC000000000000819 | AX37: CBC000000000003053 | AY37: CBC000000000001667 | AZ37: CBC000000000003926 | BA37: CBC000000000002137 | BB37: CBC000000000000852 | BC37: CBC000000000002151 | BD37: CBC000000000001759 | BE37: CBC000000000005404 | BF37: CBC000000000005006 | BH37: CBC000000000005380 | BL37: CBC000000000004838 | BN37: CBC000000000000219 | BO37: CBC000000000005138 | BQ37: CBC000000000002362 | BR37: CBC000000000004066 | BS37: CBC000000000003171 | BU37: CBC000000000002016 | BV37: CBC000000000001603 | BW37: CBC000000000002357 | BX37: CBC000000000003234 | CA37: CBC000000000000463 | CF37: CBC000000000004678 | CG37: CBC000000000000545
B38: CBC000000000001450 | D38: CBC000000000001349 | K38: CBC000000000002931 | L38: CBC000000000002261 | N38: CBC000000000000030 | O38: CBC000000000002638 | Q38: CBC000000000002063 | R38: CBC000000000001143 | S38: CBC000000000001624 | T38: CBC000000000001471 | U38: CBC000000000003684 | V38: CBC000000000001790 | W38: CBC000000000003991 | X38: CBC000000000005342 | Z38: CBC000000000002461 | AB38: CBC000000000001928 | AF38: CBC000000000004802 | AH38: CBC000000000002121 | AK38: CBC000000000000228 | AL38: CBC000000000000158 | AM38: CBC000000000003982 | AN38: CBC000000000001710 | AP38: CBC000000000003176 | AQ38: CBC000000000004426 | AR38: CBC000000000001551 | AS38: CBC000000000003626 | AT38: CBC000000000003722 | AU38: CBC000000000004864 | AV38: CBC000000000004345 | AW38: CBC000000000000820 | AX38: CBC000000000002413 | AY38: CBC000000000002709 | AZ38: CBC000000000003928 | BB38: CBC000000000005271 | BC38: CBC000000000000332 | BD38: CBC000000000001900 | BE38: CBC000000000005400 | BF38: CBC000000000002297 | BH38: CBC000000000004865 | BL38: CBC000000000005182 | BN38: CBC000000000000221 | BO38: CBC000000000005078 | BQ38: CBC000000000002386 | BR38: CBC000000000004466 | BS38: CBC000000000004000 | BU38: CBC000000000002440 | BV38: CBC000000000001628 | BW38: CBC000000000002913 | BX38: CBC000000000003292 | CA38: CBC000000000002471 | CF38: CBC000000000000430 | CG38: CBC000000000000932
B39: CBC000000000004978 | D39: CBC000000000005544 | K39: CBC000000000005411 | L39: CBC000000000002263 | N39: CBC000000000005168 | O39: CBC000000000002578 | Q39: CBC000000000002064 | R39: CBC000000000001171 | S39: CBC000000000001629 | T39: CBC000000000001918 | U39: CBC000000000002640 | V39: CBC000000000001795 | W39: CBC000000000003992 | X39: CBC000000000000706 | Z39: CBC000000000002468 | AB39: CBC000000000001942 | AF39: CBC000000000003105 | AH39: CBC000000000003805 | AK39: CBC000000000000245 | AL39: CBC000000000000220 | AM39: CBC000000000002695 | AN39: CBC000000000000468 | AP39: CBC000000000004944 | AQ39: CBC000000000002172 | AR39: CBC000000000000916 | AS39: CBC000000000004589 | AT39: CBC000000000004362 | AU39: CBC000000000004575 | AV39: CBC000000000004320 | AW39: CBC000000000000825 | AX39: CBC000000000002186 | AY39: CBC000000000003463 | AZ39: CBC000000000002978 | BB39: CBC000000000003237 | BC39: CBC000000000002139 | BD39: CBC000000000003878 | BE39: CBC000000000005401 | BF39: CBC000000000000286 | BH39: CBC000000000002674 | BL39: CBC000000000003718 | BN39: CBC000000000000224 | BO39: CBC000000000005423 | BQ39: CBC000000000004154 | BR39: CBC000000000005241 | BS39: CBC000000000004413 | BV39: CBC000000000001071 | BW39: CBC000000000003094 | BX39: CBC000000000002443 | CA39: CBC000000000000577 | CF39: CBC000000000000342 | CG39: CBC000000000003744
B40: CBC000000000000639 | D40: CBC000000000001422 | L40: CBC000000000004650 | N40: CBC000000000005152 | O40: CBC000000000001806 | Q40: CBC000000000004947 | R40: CBC000000000000959 | S40: CBC000000000001092 | T40: CBC000000000002397 | U40: CBC000000000002707 | V40: CBC000000000001069 | W40: CBC000000000005185 | X40: CBC000000000003027 | Z40: CBC000000000002207 | AB40: CBC000000000002875 | AF40: CBC000000000002044 | AH40: CBC000000000002055 | AK40: CBC000000000000247 | AL40: CBC000000000000097 | AM40: CBC000000000003283 | AN40: CBC000000000005266 | AP40: CBC000000000000184 | AQ40: CBC000000000005057 | AR40: CBC000000000001223 | AS40: CBC000000000004811 | AT40: CBC000000000005255 | AU40: CBC000000000004763 | AV40: CBC000000000004314 | AW40: CBC000000000000829 | AX40: CBC000000000002405 | AY40: CBC000000000001517 | AZ40: CBC000000000003917 | BB40: CBC000000000002169 | BC40: CBC000000000000527 | BD40: CBC000000000003834 | BE40: CBC000000000005405 | BH40: CBC000000000004869 | BL40: CBC000000000004597 | BN40: CBC000000000000227 | BO40: CBC000000000005314 | BQ40: CBC000000000002377 | BR40: CBC000000000004159 | BS40: CBC000000000004019 | BV40: CBC000000000001062 | BW40: CBC000000000003093 | BX40: CBC000000000002882 | CA40: CBC000000000002545 | CF40: CBC000000000000385 | CG40: CBC000000000003745
B41: CBC000000000000594 | D41: CBC000000000002649 | L41: CBC000000000003662 | N41: CBC000000000005170 | O41: CBC000000000005378 | Q41: CBC000000000002790 | R41: CBC000000000001015 | S41: CBC000000000000917 | T41: CBC000000000004824 | U41: CBC000000000003049 | V41: CBC000000000001039 | W41: CBC000000000003514 | X41: CBC000000000002026 | Z41: CBC000000000002762 | AB41: CBC000000000003480 | AF41: CBC000000000002047 | AH41: CBC000000000003676 | AK41: CBC000000000000248 | AL41: CBC000000000000264 | AM41: CBC000000000003289 | AN41: CBC000000000003023 | AP41: CBC000000000000111 | AQ41: CBC000000000003746 | AR41: CBC000000000002480 | AS41: CBC000000000004807 | AT41: CBC000000000004504 | AU41: CBC000000000004856 | AV41: CBC000000000004323 | AW41: CBC000000000000831 | AX41: CBC000000000002791 | AY41: CBC000000000001642 | AZ41: CBC000000000002822 | BB41: CBC000000000003178 | BC41: CBC000000000000003 | BD41: CBC000000000002712 | BE41: CBC000000000004373 | BH41: CBC000000000005002 | BN41: CBC000000000000229 | BO41: CBC000000000004055 | BQ41: CBC000000000002383 | BR41: CBC000000000005240 | BS41: CBC000000000003004 | BV41: CBC000000000001117 | BW41: CBC000000000002367 | BX41: CBC000000000003233 | CA41: CBC000000000002539 | CF41: CBC000000000004882 | CG41: CBC000000000000912
B42: CBC000000000000581 | D42: CBC000000000001078 | L42: CBC000000000001598 | N42: CBC000000000000043 | O42: CBC000000000002571 | Q42: CBC000000000002929 | R42: CBC000000000000926 | S42: CBC000000000000666 | T42: CBC000000000001501 | U42: CBC000000000003685 | V42: CBC000000000001081 | W42: CBC000000000003973 | X42: CBC000000000000707 | Z42: CBC000000000002025 | AB42: CBC000000000003476 | AF42: CBC000000000002012 | AH42: CBC000000000004831 | AK42: CBC000000000000252 | AL42: CBC000000000000230 | AM42: CBC000000000004532 | AN42: CBC000000000001188 | AP42: CBC000000000000129 | AQ42: CBC000000000003031 | AR42: CBC000000000002488 | AS42: CBC000000000004546 | AT42: CBC000000000004499 | AU42: CBC000000000004899 | AV42: CBC000000000004289 | AW42: CBC000000000000834 | AX42: CBC000000000004760 | AY42: CBC000000000001492 | AZ42: CBC000000000003082 | BB42: CBC000000000002520 | BC42: CBC000000000003394 | BD42: CBC000000000003842 | BE42: CBC000000000004377 | BH42: CBC000000000005421 | BN42: CBC000000000000231 | BO42: CBC000000000003636 | BQ42: CBC000000000005537 | BR42: CBC000000000005216 | BS42: CBC000000000005022 | BV42: CBC000000000001814 | BW42: CBC000000000003067 | BX42: CBC000000000003631 | CA42: CBC000000000001070 | CF42: CBC000000000005399 | CG42: CBC000000000005381
B43: CBC000000000001005 | D43: CBC000000000001502 | L43: CBC000000000002343 | N43: CBC000000000005435 | O43: CBC000000000001786 | Q43: CBC000000000002453 | R43: CBC000000000000856 | S43: CBC000000000000756 | T43: CBC000000000003816 | U43: CBC000000000003693 | V43: CBC000000000001138 | W43: CBC000000000003985 | X43: CBC000000000002183 | Z43: CBC000000000002027 | AB43: CBC000000000003522 | AH43: CBC000000000003762 | AK43: CBC000000000003707 | AL43: CBC000000000000124 | AM43: CBC000000000005061 | AN43: CBC000000000003569 | AP43: CBC000000000003322 | AQ43: CBC000000000003553 | AR43: CBC000000000000994 | AT43: CBC000000000004880 | AU43: CBC000000000004567 | AV43: CBC000000000004288 | AW43: CBC000000000000836 | AX43: CBC000000000005167 | AY43: CBC000000000001646 | AZ43: CBC000000000003936 | BB43: CBC000000000003963 | BC43: CBC000000000000517 | BD43: CBC000000000001216 | BE43: CBC000000000005407 | BH43: CBC000000000003186 | BN43: CBC000000000000232 | BO43: CBC000000000003369 | BQ43: CBC000000000005547 | BR43: CBC000000000004162 | BS43: CBC000000000003000 | BV43: CBC000000000000826 | BW43: CBC000000000002811 | BX43: CBC000000000002843 | CA43: CBC000000000001139 | CF43: CBC000000000000408 | CG43: CBC000000000005202
B44: CBC000000000005050 | D44: CBC000000000001197 | L44: CBC000000000003664 | N44: CBC000000000005484 | O44: CBC000000000001809 | Q44: CBC000000000001932 | R44: CBC000000000000975 | S44: CBC000000000001303 | T44: CBC000000000001532 | U44: CBC000000000003810 | V44: CBC000000000001121 | W44: CBC000000000003563 | X44: CBC000000000001901 | Z44: CBC000000000003709 | AB44: CBC000000000001954 | AH44: CBC000000000003748 | AK44: CBC000000000000182 | AL44: CBC000000000000137 | AM44: CBC000000000005096 | AN44: CBC000000000001822 | AP44: CBC000000000003195 | AQ44: CBC000000000003352 | AR44: CBC000000000003161 | AT44: CBC000000000004517 | AU44: CBC000000000004268 | AV44: CBC000000000004281 | AW44: CBC000000000000838 | AX44: CBC000000000005190 | AY44: CBC000000000001436 | AZ44: CBC000000000002812 | BB44: CBC000000000003309 | BC44: CBC000000000001365 | BD44: CBC000000000001232 | BE44: CBC000000000004238 | BH44: CBC000000000005426 | BN44: CBC000000000000234 | BO44: CBC000000000003397 | BQ44: CBC000000000005549 | BR44: CBC000000000004383 | BS44: CBC000000000002997 | BV44: CBC000000000001373 | BW44: CBC000000000002922 | BX44: CBC000000000003222 | CA44: CBC000000000003617 | CF44: CBC000000000000621 | CG44: CBC000000000002316
B45: CBC000000000000583 | D45: CBC000000000001088 | L45: CBC000000000002262 | N45: CBC000000000003300 | O45: CBC000000000001813 | Q45: CBC000000000003453 | R45: CBC000000000000952 | S45: CBC000000000001279 | T45: CBC000000000001919 | U45: CBC000000000005015 | V45: CBC000000000001097 | W45: CBC000000000002288 | X45: CBC000000000004963 | Z45: CBC000000000002001 | AB45: CBC000000000003491 | AH45: CBC000000000003452 | AK45: CBC000000000000183 | AL45: CBC000000000000202 | AM45: CBC000000000005135 | AN45: CBC000000000002114 | AP45: CBC000000000003323 | AQ45: CBC000000000004191 | AT45: CBC000000000003766 | AU45: CBC000000000004733 | AV45: CBC000000000004329 | AW45: CBC000000000000839 | AX45: CBC000000000003711 | AY45: CBC000000000001065 | AZ45: CBC000000000003922 | BB45: CBC000000000000002 | BC45: CBC000000000000523 | BD45: CBC000000000002179 | BE45: CBC000000000004385 | BH45: CBC000000000004621 | BN45: CBC000000000000235 | BO45: CBC000000000003418 | BQ45: CBC000000000005550 | BR45: CBC000000000005236 | BS45: CBC000000000004049 | BV45: CBC000000000001697 | BW45: CBC000000000003347 | BX45: CBC000000000004551 | CF45: CBC000000000005430 | CG45: CBC000000000000485
B46: CBC000000000000981 | D46: CBC000000000001434 | L46: CBC000000000003667 | N46: CBC000000000003301 | O46: CBC000000000001178 | Q46: CBC000000000001979 | R46: CBC000000000000864 | S46: CBC000000000001108 | T46: CBC000000000003819 | U46: CBC000000000004783 | V46: CBC000000000000949 | W46: CBC000000000004769 | X46: CBC000000000003754 | Z46: CBC000000000002212 | AB46: CBC000000000003077 | AH46: CBC000000000002528 | AK46: CBC000000000000186 | AL46: CBC000000000000081 | AM46: CBC000000000002736 | AN46: CBC000000000004604 | AP46: CBC000000000003190 | AQ46: CBC000000000003187 | AT46: CBC000000000003256 | AU46: CBC000000000004260 | AV46: CBC000000000004342 | AW46: CBC000000000000853 | AX46: CBC000000000001016 | AY46: CBC000000000001588 | AZ46: CBC000000000003933 | BB46: CBC000000000002885 | BC46: CBC000000000000475 | BD46: CBC000000000002717 | BE46: CBC000000000004390 | BH46: CBC000000000005386 | BN46: CBC000000000000236 | BO46: CBC000000000003114 | BQ46: CBC000000000005551 | BR46: CBC000000000004467 | BS46: CBC000000000002986 | BV46: CBC000000000001080 | BW46: CBC000000000005344 | BX46: CBC000000000002569 | CF46: CBC000000000005009 | CG46: CBC000000000004535
B47: CBC000000000000592 | D47: CBC000000000001266 | N47: CBC000000000003287 | O47: CBC000000000001817 | Q47: CBC000000000002932 | R47: CBC000000000000798 | S47: CBC000000000000974 | T47: CBC000000000001550 | U47: CBC000000000004919 | V47: CBC000000000001057 | W47: CBC000000000002334 | X47: CBC000000000005501 | Z47: CBC000000000003324 | AB47: CBC000000000002880 | AH47: CBC000000000002955 | AK47: CBC000000000000192 | AL47: CBC000000000000145 | AM47: CBC000000000003999 | AN47: CBC000000000001757 | AP47: CBC000000000003325 | AQ47: CBC000000000003899 | AT47: CBC000000000004152 | AU47: CBC000000000004619 | AV47: CBC000000000004353 | AW47: CBC000000000000823 | AX47: CBC000000000002259 | AY47: CBC000000000001645 | AZ47: CBC000000000003921 | BB47: CBC000000000002522 | BC47: CBC000000000002153 | BD47: CBC000000000002728 | BE47: CBC000000000003059 | BH47: CBC000000000005149 | BN47: CBC000000000000238 | BO47: CBC000000000002744 | BQ47: CBC000000000005552 | BR47: CBC000000000005201 | BS47: CBC000000000003261 | BV47: CBC000000000000767 | BW47: CBC000000000003204 | BX47: CBC000000000003240 | CF47: CBC000000000005132 | CG47: CBC000000000005530
B48: CBC000000000000678 | D48: CBC000000000001378 | N48: CBC000000000000436 | O48: CBC000000000002584 | Q48: CBC000000000002537 | R48: CBC000000000000794 | S48: CBC000000000001481 | T48: CBC000000000002392 | U48: CBC000000000002681 | V48: CBC000000000001275 | W48: CBC000000000004014 | X48: CBC000000000005277 | Z48: CBC000000000002492 | AB48: CBC000000000003500 | AH48: CBC000000000003753 | AK48: CBC000000000000174 | AL48: CBC000000000000105 | AM48: CBC000000000004061 | AN48: CBC000000000002431 | AP48: CBC000000000003231 | AQ48: CBC000000000004867 | AT48: CBC000000000004808 | AU48: CBC000000000004726 | AV48: CBC000000000004339 | AW48: CBC000000000001193 | AX48: CBC000000000001974 | AY48: CBC000000000001675 | AZ48: CBC000000000002983 | BB48: CBC000000000002518 | BC48: CBC000000000002155 | BD48: CBC000000000003852 | BE48: CBC000000000003477 | BH48: CBC000000000002702 | BN48: CBC000000000000240 | BO48: CBC000000000002581 | BQ48: CBC000000000005553 | BR48: CBC000000000004468 | BS48: CBC000000000004011 | BV48: CBC000000000005029 | BW48: CBC000000000003030 | BX48: CBC000000000005291 | CF48: CBC000000000000985 | CG48: CBC000000000000354
B49: CBC000000000001087 | D49: CBC000000000001239 | N49: CBC000000000005091 | O49: CBC000000000002738 | Q49: CBC000000000002870 | R49: CBC000000000001072 | S49: CBC000000000001475 | T49: CBC000000000002519 | U49: CBC000000000003651 | V49: CBC000000000001372 | W49: CBC000000000003983 | X49: CBC000000000005252 | Z49: CBC000000000002487 | AB49: CBC000000000002899 | AH49: CBC000000000003768 | AK49: CBC000000000000178 | AL49: CBC000000000005274 | AM49: CBC000000000005028 | AN49: CBC000000000002107 | AP49: CBC000000000000120 | AQ49: CBC000000000003898 | AT49: CBC000000000004140 | AU49: CBC000000000004622 | AV49: CBC000000000004352 | AW49: CBC000000000000904 | AX49: CBC000000000003365 | AY49: CBC000000000001497 | AZ49: CBC000000000003906 | BB49: CBC000000000002593 | BC49: CBC000000000000009 | BD49: CBC000000000000796 | BE49: CBC000000000003489 | BH49: CBC000000000004857 | BN49: CBC000000000000241 | BO49: CBC000000000002588 | BQ49: CBC000000000002556 | BR49: CBC000000000004163 | BS49: CBC000000000003013 | BV49: CBC000000000001019 | BW49: CBC000000000002786 | BX49: CBC000000000002323 | CF49: CBC000000000002781 | CG49: CBC000000000000339
B50: CBC000000000001317 | D50: CBC000000000001007 | N50: CBC000000000001969 | O50: CBC000000000001648 | Q50: CBC000000000002339 | S50: CBC000000000000954 | T50: CBC000000000003821 | U50: CBC000000000005014 | V50: CBC000000000001130 | W50: CBC000000000002285 | X50: CBC000000000003863 | Z50: CBC000000000005305 | AB50: CBC000000000002466 | AH50: CBC000000000002802 | AK50: CBC000000000000195 | AL50: CBC000000000000215 | AM50: CBC000000000002610 | AN50: CBC000000000001711 | AP50: CBC000000000003326 | AQ50: CBC000000000003900 | AT50: CBC000000000003438 | AU50: CBC000000000004599 | AV50: CBC000000000004297 | AW50: CBC000000000000905 | AX50: CBC000000000001978 | AY50: CBC000000000001056 | AZ50: CBC000000000003078 | BB50: CBC000000000003429 | BC50: CBC000000000001337 | BD50: CBC000000000002642 | BE50: CBC000000000004217 | BH50: CBC000000000005499 | BN50: CBC000000000000242 | BO50: CBC000000000005110 | BQ50: CBC000000000005535 | BR50: CBC000000000005227 | BS50: CBC000000000004196 | BV50: CBC000000000001726 | BW50: CBC000000000003069 | BX50: CBC000000000002863 | CF50: CBC000000000000397 | CG50: CBC000000000000345
B51: CBC000000000002241 | D51: CBC000000000001215 | N51: CBC000000000005197 | O51: CBC000000000005494 | Q51: CBC000000000005486 | S51: CBC000000000000770 | T51: CBC000000000003822 | U51: CBC000000000002734 | V51: CBC000000000001095 | W51: CBC000000000002290 | X51: CBC000000000004397 | AB51: CBC000000000003192 | AH51: CBC000000000002108 | AK51: CBC000000000000204 | AL51: CBC000000000000199 | AM51: CBC000000000004782 | AN51: CBC000000000005270 | AP51: CBC000000000003327 | AQ51: CBC000000000004090 | AT51: CBC000000000003133 | AU51: CBC000000000004605 | AV51: CBC000000000004331 | AW51: CBC000000000000918 | AX51: CBC000000000005558 | AY51: CBC000000000001044 | AZ51: CBC000000000001245 | BB51: CBC000000000002000 | BC51: CBC000000000002145 | BD51: CBC000000000002860 | BE51: CBC000000000004218 | BH51: CBC000000000002984 | BN51: CBC000000000000243 | BO51: CBC000000000005020 | BQ51: CBC000000000002351 | BR51: CBC000000000004923 | BS51: CBC000000000003002 | BV51: CBC000000000000735 | BW51: CBC000000000004340 | BX51: CBC000000000005292 | CF51: CBC000000000004212 | CG51: CBC000000000000405
B52: CBC000000000001110 | D52: CBC000000000001308 | N52: CBC000000000000414 | O52: CBC000000000001891 | Q52: CBC000000000003458 | S52: CBC000000000001230 | T52: CBC000000000004822 | U52: CBC000000000005017 | V52: CBC000000000001722 | W52: CBC000000000002284 | X52: CBC000000000002501 | AB52: CBC000000000002221 | AH52: CBC000000000003796 | AK52: CBC000000000000207 | AL52: CBC000000000000187 | AM52: CBC000000000003277 | AN52: CBC000000000001952 | AP52: CBC000000000003328 | AQ52: CBC000000000004270 | AT52: CBC000000000003132 | AU52: CBC000000000004780 | AV52: CBC000000000004350 | AW52: CBC000000000000907 | AX52: CBC000000000005171 | AY52: CBC000000000001665 | AZ52: CBC000000000003934 | BB52: CBC000000000001996 | BC52: CBC000000000000350 | BD52: CBC000000000000903 | BE52: CBC000000000003554 | BH52: CBC000000000005500 | BN52: CBC000000000000244 | BO52: CBC000000000004548 | BQ52: CBC000000000004983 | BR52: CBC000000000004469 | BS52: CBC000000000004016 | BV52: CBC000000000000595 | BW52: CBC000000000002361 | BX52: CBC000000000003644 | CG52: CBC000000000002195
B53: CBC000000000001265 | D53: CBC000000000000787 | N53: CBC000000000005474 | O53: CBC000000000003217 | Q53: CBC000000000003457 | S53: CBC000000000001415 | T53: CBC000000000004810 | U53: CBC000000000003652 | V53: CBC000000000000771 | W53: CBC000000000003546 | X53: CBC000000000003832 | AB53: CBC000000000002348 | AH53: CBC000000000005267 | AK53: CBC000000000000212 | AL53: CBC000000000000076 | AM53: CBC000000000003284 | AN53: CBC000000000001965 | AP53: CBC000000000003329 | AT53: CBC000000000003809 | AU53: CBC000000000004224 | AV53: CBC000000000004334 | AW53: CBC000000000000915 | AX53: CBC000000000005429 | AY53: CBC000000000001674 | AZ53: CBC000000000003938 | BB53: CBC000000000002149 | BC53: CBC000000000000910 | BD53: CBC000000000003871 | BE53: CBC000000000004229 | BH53: CBC000000000005261 | BN53: CBC000000000000246 | BO53: CBC000000000002663 | BR53: CBC000000000005200 | BS53: CBC000000000002999 | BV53: CBC000000000001602 | BW53: CBC000000000002076 | BX53: CBC000000000003269 | CG53: CBC000000000001680
B54: CBC000000000001416 | D54: CBC000000000000909 | N54: CBC000000000005475 | O54: CBC000000000001887 | Q54: CBC000000000004324 | S54: CBC000000000001612 | T54: CBC000000000001535 | U54: CBC000000000003440 | V54: CBC000000000001474 | W54: CBC000000000004859 | X54: CBC000000000005183 | AB54: CBC000000000003200 | AH54: CBC000000000005145 | AK54: CBC000000000000233 | AL54: CBC000000000000173 | AM54: CBC000000000004400 | AN54: CBC000000000004465 | AP54: CBC000000000003330 | AT54: CBC000000000004369 | AU54: CBC000000000004562 | AV54: CBC000000000004318 | AW54: CBC000000000001025 | AX54: CBC000000000002184 | AY54: CBC000000000001421 | AZ54: CBC000000000002857 | BB54: CBC000000000005269 | BC54: CBC000000000001340 | BD54: CBC000000000000862 | BE54: CBC000000000003737 | BH54: CBC000000000004631 | BN54: CBC000000000000249 | BO54: CBC000000000005052 | BR54: CBC000000000005234 | BS54: CBC000000000003007 | BV54: CBC000000000001881 | BW54: CBC000000000002512 | CG54: CBC000000000000360
B55: CBC000000000001100 | D55: CBC000000000001437 | N55: CBC000000000000525 | O55: CBC000000000002568 | Q55: CBC000000000001949 | S55: CBC000000000001971 | T55: CBC000000000001921 | V55: CBC000000000001487 | X55: CBC000000000001987 | AB55: CBC000000000003502 | AH55: CBC000000000002809 | AK55: CBC000000000000237 | AL55: CBC000000000000092 | AM55: CBC000000000004559 | AN55: CBC000000000001639 | AP55: CBC000000000003331 | AT55: CBC000000000004392 | AU55: CBC000000000004207 | AV55: CBC000000000004282 | AW55: CBC000000000005302 | AX55: CBC000000000003501 | AY55: CBC000000000001054 | AZ55: CBC000000000003903 | BB55: CBC000000000002391 | BC55: CBC000000000000443 | BD55: CBC000000000004147 | BE55: CBC000000000003731 | BH55: CBC000000000005532 | BN55: CBC000000000000250 | BO55: CBC000000000005448 | BR55: CBC000000000005189 | BS55: CBC000000000004023 | BV55: CBC000000000000661 | BW55: CBC000000000003064 | CG55: CBC000000000002335
B56: CBC000000000001233 | D56: CBC000000000001451 | N56: CBC000000000003267 | O56: CBC000000000001353 | Q56: CBC000000000002936 | S56: CBC000000000001720 | T56: CBC000000000002395 | V56: CBC000000000001465 | X56: CBC000000000001934 | AH56: CBC000000000003765 | AK56: CBC000000000000239 | AL56: CBC000000000005490 | AM56: CBC000000000002693 | AN56: CBC000000000001970 | AP56: CBC000000000003197 | AT56: CBC000000000005563 | AU56: CBC000000000004273 | AV56: CBC000000000004279 | AW56: CBC000000000000924 | AX56: CBC000000000003363 | AY56: CBC000000000001473 | AZ56: CBC000000000003080 | BB56: CBC000000000002586 | BC56: CBC000000000001346 | BD56: CBC000000000003846 | BE56: CBC000000000004407 | BH56: CBC000000000005321 | BN56: CBC000000000005516 | BO56: CBC000000000005443 | BR56: CBC000000000004246 | BS56: CBC000000000004051 | BV56: CBC000000000000664 | BW56: CBC000000000002309 | CG56: CBC000000000000366
B57: CBC000000000001256 | D57: CBC000000000001428 | N57: CBC000000000000059 | O57: CBC000000000001818 | Q57: CBC000000000003130 | S57: CBC000000000001205 | T57: CBC000000000001489 | X57: CBC000000000002210 | AH57: CBC000000000003984 | AL57: CBC000000000000343 | AM57: CBC000000000002658 | AN57: CBC000000000005458 | AP57: CBC000000000003225 | AT57: CBC000000000004355 | AU57: CBC000000000004758 | AV57: CBC000000000004321 | AW57: CBC000000000000751 | AX57: CBC000000000005470 | AY57: CBC000000000001511 | AZ57: CBC000000000003307 | BB57: CBC000000000000001 | BC57: CBC000000000001398 | BD57: CBC000000000002907 | BE57: CBC000000000004414 | BH57: CBC000000000004719 | BN57: CBC000000000000091 | BO57: CBC000000000002952 | BR57: CBC000000000004248 | BS57: CBC000000000003942 | BV57: CBC000000000000658 | BW57: CBC000000000002918 | CG57: CBC000000000002509
B58: CBC000000000001297 | D58: CBC000000000001355 | N58: CBC000000000003263 | O58: CBC000000000002631 | Q58: CBC000000000002651 | S58: CBC000000000001620 | T58: CBC000000000001922 | X58: CBC000000000001993 | AH58: CBC000000000003033 | AL58: CBC000000000000185 | AM58: CBC000000000002696 | AN58: CBC000000000001554 | AP58: CBC000000000003224 | AT58: CBC000000000003763 | AU58: CBC000000000004234 | AV58: CBC000000000004336 | AW58: CBC000000000000828 | AX58: CBC000000000001520 | AY58: CBC000000000001506 | AZ58: CBC000000000002965 | BB58: CBC000000000003660 | BC58: CBC000000000000010 | BD58: CBC000000000002462 | BE58: CBC000000000004416 | BH58: CBC000000000005032 | BN58: CBC000000000000369 | BO58: CBC000000000004060 | BR58: CBC000000000005222 | BS58: CBC000000000003041 | BV58: CBC000000000000657 | BW58: CBC000000000003058 | CG58: CBC000000000001159
B59: CBC000000000004967 | D59: CBC000000000001363 | N59: CBC000000000005173 | O59: CBC000000000001610 | Q59: CBC000000000002062 | S59: CBC000000000001258 | T59: CBC000000000004823 | X59: CBC000000000004419 | AH59: CBC000000000003802 | AM59: CBC000000000004068 | AN59: CBC000000000000660 | AP59: CBC000000000003223 | AT59: CBC000000000003913 | AU59: CBC000000000004793 | AV59: CBC000000000004299 | AW59: CBC000000000000870 | AX59: CBC000000000002187 | AY59: CBC000000000001345 | AZ59: CBC000000000004388 | BB59: CBC000000000003155 | BC59: CBC000000000000006 | BD59: CBC000000000003851 | BE59: CBC000000000003468 | BH59: CBC000000000005519 | BN59: CBC000000000000256 | BO59: CBC000000000005114 | BR59: CBC000000000004380 | BS59: CBC000000000004985 | BV59: CBC000000000001396 | BW59: CBC000000000004657 | CG59: CBC000000000001221
B60: CBC000000000000522 | D60: CBC000000000001305 | N60: CBC000000000005123 | O60: CBC000000000002585 | Q60: CBC000000000002949 | S60: CBC000000000001439 | T60: CBC000000000001527 | X60: CBC000000000005534 | AH60: CBC000000000002934 | AM60: CBC000000000003719 | AN60: CBC000000000000461 | AP60: CBC000000000003226 | AT60: CBC000000000005187 | AU60: CBC000000000004718 | AV60: CBC000000000004303 | AW60: CBC000000000001196 | AX60: CBC000000000001248 | AY60: CBC000000000001298 | AZ60: CBC000000000003902 | BB60: CBC000000000003918 | BC60: CBC000000000000502 | BD60: CBC000000000004539 | BE60: CBC000000000004420 | BH60: CBC000000000004874 | BN60: CBC000000000000259 | BO60: CBC000000000002276 | BR60: CBC000000000004381 | BS60: CBC000000000003471 | BV60: CBC000000000000730 | BW60: CBC000000000002789 | CG60: CBC000000000001122
B61: CBC000000000000489 | D61: CBC000000000001311 | N61: CBC000000000000610 | O61: CBC000000000001006 | Q61: CBC000000000001926 | S61: CBC000000000000732 | T61: CBC000000000001498 | X61: CBC000000000001875 | AH61: CBC000000000002816 | AM61: CBC000000000002692 | AN61: CBC000000000001982 | AP61: CBC000000000003212 | AT61: CBC000000000005256 | AU61: CBC000000000004875 | AV61: CBC000000000004311 | AW61: CBC000000000000925 | AX61: CBC000000000002004 | AY61: CBC000000000001467 | AZ61: CBC000000000002981 | BB61: CBC000000000003147 | BC61: CBC000000000001385 | BD61: CBC000000000002834 | BE61: CBC000000000004435 | BH61: CBC000000000002424 | BN61: CBC000000000000263 | BO61: CBC000000000004454 | BR61: CBC000000000005214 | BS61: CBC000000000002636 | BV61: CBC000000000005117 | BW61: CBC000000000002796 | CG61: CBC000000000004148
B62: CBC000000000000514 | D62: CBC000000000001565 | N62: CBC000000000000498 | O62: CBC000000000001823 | Q62: CBC000000000002600 | S62: CBC000000000000734 | X62: CBC000000000002668 | AH62: CBC000000000003760 | AM62: CBC000000000005129 | AN62: CBC000000000004732 | AP62: CBC000000000003332 | AT62: CBC000000000003755 | AU62: CBC000000000004609 | AV62: CBC000000000004332 | AW62: CBC000000000001201 | AX62: CBC000000000001555 | AY62: CBC000000000001464 | AZ62: CBC000000000003306 | BB62: CBC000000000005264 | BC62: CBC000000000000008 | BD62: CBC000000000002418 | BE62: CBC000000000004444 | BH62: CBC000000000002197 | BN62: CBC000000000000266 | BO62: CBC000000000003590 | BR62: CBC000000000005206 | BS62: CBC000000000003172 | BV62: CBC000000000001631 | BW62: CBC000000000005523 | CG62: CBC000000000005071
B63: CBC000000000001578 | D63: CBC000000000001156 | N63: CBC000000000003299 | O63: CBC000000000002587 | Q63: CBC000000000003098 | S63: CBC000000000000971 | X63: CBC000000000002017 | AH63: CBC000000000002945 | AM63: CBC000000000003688 | AN63: CBC000000000004847 | AP63: CBC000000000003333 | AT63: CBC000000000003594 | AU63: CBC000000000004590 | AV63: CBC000000000004982 | AW63: CBC000000000000845 | AX63: CBC000000000003450 | AY63: CBC000000000001647 | AZ63: CBC000000000002807 | BB63: CBC000000000002706 | BC63: CBC000000000002120 | BD63: CBC000000000002178 | BE63: CBC000000000004449 | BH63: CBC000000000002532 | BN63: CBC000000000000094 | BO63: CBC000000000002292 | BR63: CBC000000000005218 | BS63: CBC000000000002733 | BV63: CBC000000000001479 | BW63: CBC000000000003303 | CG63: CBC000000000000340
B64: CBC000000000000579 | D64: CBC000000000003691 | N64: CBC000000000002324 | O64: CBC000000000001263 | Q64: CBC000000000002645 | S64: CBC000000000000869 | X64: CBC000000000002115 | AH64: CBC000000000002914 | AM64: CBC000000000005356 | AN64: CBC000000000003608 | AP64: CBC000000000005076 | AT64: CBC000000000004343 | AU64: CBC000000000004586 | AV64: CBC000000000004701 | AW64: CBC000000000000808 | AX64: CBC000000000003431 | AY64: CBC000000000001445 | AZ64: CBC000000000002806 | BB64: CBC000000000002165 | BC64: CBC000000000002141 | BD64: CBC000000000003618 | BE64: CBC000000000003529 | BH64: CBC000000000003183 | BN64: CBC000000000000293 | BO64: CBC000000000005116 | BR64: CBC000000000005242 | BS64: CBC000000000002092 | BV64: CBC000000000000641 | BW64: CBC000000000002892 | CG64: CBC000000000000963
D65: CBC000000000001160 | N65: CBC000000000000047 | O65: CBC000000000002590 | Q65: CBC000000000004178 | S65: CBC000000000000711 | X65: CBC000000000002116 | AH65: CBC000000000003797 | AM65: CBC000000000003288 | AN65: CBC000000000003035 | AP65: CBC000000000005324 | AT65: CBC000000000003927 | AU65: CBC000000000004905 | AV65: CBC000000000004107 | AW65: CBC000000000000858 | AX65: CBC000000000002411 | AY65: CBC000000000001463 | AZ65: CBC000000000002976 | BB65: CBC000000000002708 | BC65: CBC000000000002156 | BD65: CBC000000000002180 | BE65: CBC000000000003376 | BH65: CBC000000000004756 | BN65: CBC000000000000297 | BO65: CBC000000000002743 | BR65: CBC000000000005223 | BS65: CBC000000000004849 | BV65: CBC000000000000601 | BW65: CBC000000000002074 | CG65: CBC000000000000396
D66: CBC000000000001158 | N66: CBC000000000003296 | O66: CBC000000000002630 | Q66: CBC000000000002069 | S66: CBC000000000001001 | X66: CBC000000000001075 | AH66: CBC000000000003978 | AM66: CBC000000000003703 | AN66: CBC000000000001988 | AP66: CBC000000000003203 | AT66: CBC000000000003776 | AV66: CBC000000000004988 | AW66: CBC000000000000866 | AX66: CBC000000000004809 | AY66: CBC000000000001105 | AZ66: CBC000000000003605 | BB66: CBC000000000003286 | BC66: CBC000000000002152 | BD66: CBC000000000003603 | BE66: CBC000000000003735 | BH66: CBC000000000004851 | BN66: CBC000000000000309 | BO66: CBC000000000002956 | BR66: CBC000000000004470 | BS66: CBC000000000003673 | BV66: CBC000000000000586 | BW66: CBC000000000002772 | CG66: CBC000000000001145
D67: CBC000000000001211 | N67: CBC000000000000534 | O67: CBC000000000001366 | Q67: CBC000000000002944 | S67: CBC000000000001609 | X67: CBC000000000002010 | AH67: CBC000000000005072 | AM67: CBC000000000004478 | AN67: CBC000000000002689 | AP67: CBC000000000003334 | AT67: CBC000000000004781 | AV67: CBC000000000004989 | AW67: CBC000000000000803 | AX67: CBC000000000005517 | AY67: CBC000000000001742 | AZ67: CBC000000000002795 | BB67: CBC000000000005111 | BC67: CBC000000000000876 | BD67: CBC000000000003838 | BE67: CBC000000000003520 | BH67: CBC000000000004638 | BN67: CBC000000000000095 | BO67: CBC000000000002957 | BR67: CBC000000000005219 | BS67: CBC000000000003953 | BV67: CBC000000000000972 | BW67: CBC000000000003092 | CG67: CBC000000000000358
D68: CBC000000000001418 | N68: CBC000000000005087 | O68: CBC000000000001343 | Q68: CBC000000000003127 | S68: CBC000000000001600 | X68: CBC000000000005142 | AH68: CBC000000000003767 | AM68: CBC000000000004375 | AN68: CBC000000000005008 | AP68: CBC000000000003335 | AT68: CBC000000000003095 | AV68: CBC000000000004307 | AW68: CBC000000000000827 | AX68: CBC000000000003960 | AY68: CBC000000000001650 | AZ68: CBC000000000002987 | BB68: CBC000000000003740 | BC68: CBC000000000000007 | BD68: CBC000000000003853 | BE68: CBC000000000003734 | BH68: CBC000000000005010 | BN68: CBC000000000000098 | BO68: CBC000000000002291 | BR68: CBC000000000005232 | BS68: CBC000000000003692 | BV68: CBC000000000005104 | BW68: CBC000000000004612 | CG68: CBC000000000000603
D69: CBC000000000001148 | N69: CBC000000000005437 | O69: CBC000000000002611 | Q69: CBC000000000002070 | S69: CBC000000000001166 | X69: CBC000000000001940 | AH69: CBC000000000002948 | AM69: CBC000000000002596 | AN69: CBC000000000000547 | AP69: CBC000000000003336 | AT69: CBC000000000003539 | AV69: CBC000000000004990 | AW69: CBC000000000000929 | AX69: CBC000000000005427 | AY69: CBC000000000001651 | AZ69: CBC000000000002840 | BB69: CBC000000000003210 | BC69: CBC000000000000011 | BD69: CBC000000000004520 | BE69: CBC000000000003443 | BH69: CBC000000000005485 | BN69: CBC000000000000099 | BO69: CBC000000000003109 | BR69: CBC000000000005233 | BS69: CBC000000000003257 | BV69: CBC000000000000731 | BW69: CBC000000000002035 | CG69: CBC000000000000984
D70: CBC000000000001147 | N70: CBC000000000005438 | O70: CBC000000000001889 | Q70: CBC000000000002264 | S70: CBC000000000001977 | X70: CBC000000000001941 | AH70: CBC000000000002438 | AM70: CBC000000000004233 | AN70: CBC000000000002921 | AP70: CBC000000000003337 | AT70: CBC000000000004900 | AV70: CBC000000000004652 | AW70: CBC000000000001313 | AX70: CBC000000000005164 | AY70: CBC000000000001671 | AZ70: CBC000000000003914 | BB70: CBC000000000002146 | BC70: CBC000000000002147 | BD70: CBC000000000003110 | BE70: CBC000000000003521 | BH70: CBC000000000003509 | BN70: CBC000000000000101 | BO70: CBC000000000005106 | BR70: CBC000000000005213 | BS70: CBC000000000003255 | BV70: CBC000000000005113 | BW70: CBC000000000002784 | CG70: CBC000000000003251
D71: CBC000000000001240 | N71: CBC000000000005097 | O71: CBC000000000002595 | Q71: CBC000000000003097 | S71: CBC000000000001002 | X71: CBC000000000001943 | AH71: CBC000000000002946 | AM71: CBC000000000004149 | AN71: CBC000000000002619 | AP71: CBC000000000003338 | AT71: CBC000000000004887 | AV71: CBC000000000004113 | AW71: CBC000000000001206 | AX71: CBC000000000005162 | AY71: CBC000000000001669 | AZ71: CBC000000000003919 | BB71: CBC000000000002144 | BC71: CBC000000000000902 | BD71: CBC000000000002602 | BE71: CBC000000000003526 | BH71: CBC000000000003601 | BN71: CBC000000000003420 | BO71: CBC000000000002304 | BR71: CBC000000000004627 | BS71: CBC000000000004534 | BV71: CBC000000000005120 | CG71: CBC000000000001151
D72: CBC000000000001176 | N72: CBC000000000005172 | O72: CBC000000000001821 | Q72: CBC000000000002331 | S72: CBC000000000001605 | X72: CBC000000000004541 | AH72: CBC000000000002119 | AM72: CBC000000000002432 | AN72: CBC000000000001782 | AP72: CBC000000000000115 | AT72: CBC000000000004889 | AV72: CBC000000000004702 | AW72: CBC000000000000930 | AX72: CBC000000000005509 | AY72: CBC000000000001685 | AZ72: CBC000000000003084 | BB72: CBC000000000005247 | BC72: CBC000000000004698 | BD72: CBC000000000002173 | BE72: CBC000000000003511 | BH72: CBC000000000003604 | BN72: CBC000000000000304 | BO72: CBC000000000004576 | BR72: CBC000000000004611 | BS72: CBC000000000003298 | BV72: CBC000000000001485 | CG72: CBC000000000001243
D73: CBC000000000003689 | N73: CBC000000000000046 | O73: CBC000000000002635 | Q73: CBC000000000001929 | S73: CBC000000000001944 | X73: CBC000000000004409 | AH73: CBC000000000003782 | AM73: CBC000000000002634 | AN73: CBC000000000002911 | AP73: CBC000000000000114 | AT73: CBC000000000003758 | AV73: CBC000000000004653 | AW73: CBC000000000000934 | AX73: CBC000000000005488 | AY73: CBC000000000001503 | AZ73: CBC000000000002800 | BB73: CBC000000000004794 | BC73: CBC000000000000441 | BD73: CBC000000000002174 | BE73: CBC000000000003727 | BH73: CBC000000000003738 | BN73: CBC000000000000307 | BO73: CBC000000000002433 | BR73: CBC000000000005231 | BS73: CBC000000000004028 | BV73: CBC000000000005045 | CG73: CBC000000000002090
D74: CBC000000000001315 | N74: CBC000000000000022 | O74: CBC000000000001296 | Q74: CBC000000000002541 | S74: CBC000000000000945 | X74: CBC000000000001858 | AM74: CBC000000000004200 | AN74: CBC000000000003597 | AP74: CBC000000000003339 | AT74: CBC000000000004503 | AV74: CBC000000000004965 | AW74: CBC000000000001209 | AX74: CBC000000000002412 | AY74: CBC000000000001664 | AZ74: CBC000000000002846 | BB74: CBC000000000002705 | BC74: CBC000000000000431 | BD74: CBC000000000004526 | BE74: CBC000000000003723 | BH74: CBC000000000005422 | BN74: CBC000000000000315 | BO74: CBC000000000002400 | BR74: CBC000000000003995 | BS74: CBC000000000002998 | BV74: CBC000000000001703 | CG74: CBC000000000003151
D75: CBC000000000001187 | N75: CBC000000000001747 | O75: CBC000000000001286 | Q75: CBC000000000002068 | S75: CBC000000000000953 | X75: CBC000000000005345 | AM75: CBC000000000004437 | AN75: CBC000000000003017 | AP75: CBC000000000000106 | AT75: CBC000000000004382 | AV75: CBC000000000004998 | AW75: CBC000000000001217 | AX75: CBC000000000004753 | AY75: CBC000000000001654 | AZ75: CBC000000000003904 | BB75: CBC000000000005248 | BC75: CBC000000000001288 | BD75: CBC000000000002714 | BE75: CBC000000000003726 | BH75: CBC000000000003600 | BN75: CBC000000000000319 | BO75: CBC000000000002454 | BR75: CBC000000000004471 | BS75: CBC000000000002995 | BV75: CBC000000000000726 | CG75: CBC000000000003395
D76: CBC000000000001453 | N76: CBC000000000000526 | O76: CBC000000000001825 | Q76: CBC000000000002542 | S76: CBC000000000000973 | X76: CBC000000000001972 | AM76: CBC000000000004245 | AN76: CBC000000000001729 | AP76: CBC000000000000096 | AT76: CBC000000000005469 | AV76: CBC000000000004703 | AW76: CBC000000000000941 | AX76: CBC000000000003050 | AY76: CBC000000000001672 | AZ76: CBC000000000002973 | BB76: CBC000000000003749 | BC76: CBC000000000001312 | BD76: CBC000000000002718 | BE76: CBC000000000003724 | BH76: CBC000000000004626 | BN76: CBC000000000000390 | BO76: CBC000000000002774 | BR76: CBC000000000004482 | BS76: CBC000000000003993 | BV76: CBC000000000001017 | CG76: CBC000000000003153
D77: CBC000000000004522 | N77: CBC000000000000497 | O77: CBC000000000002594 | Q77: CBC000000000002320 | S77: CBC000000000000882 | X77: CBC000000000005025 | AM77: CBC000000000005060 | AN77: CBC000000000000624 | AP77: CBC000000000000093 | AT77: CBC000000000003622 | AV77: CBC000000000004994 | AW77: CBC000000000000940 | AX77: CBC000000000002406 | AY77: CBC000000000001684 | AZ77: CBC000000000002859 | BC77: CBC000000000000897 | BD77: CBC000000000003859 | BE77: CBC000000000003728 | BH77: CBC000000000005343 | BN77: CBC000000000001840 | BO77: CBC000000000002477 | BR77: CBC000000000005210 | BS77: CBC000000000004015 | BV77: CBC000000000000755 | CG77: CBC000000000003264
D78: CBC000000000001203 | N78: CBC000000000000536 | O78: CBC000000000001641 | Q78: CBC000000000004348 | S78: CBC000000000000736 | X78: CBC000000000000014 | AM78: CBC000000000003280 | AN78: CBC000000000001183 | AP78: CBC000000000000087 | AT78: CBC000000000003177 | AV78: CBC000000000005000 | AW78: CBC000000000001736 | AX78: CBC000000000003052 | AY78: CBC000000000001656 | AZ78: CBC000000000001526 | BC78: CBC000000000001350 | BD78: CBC000000000002456 | BE78: CBC000000000003725 | BH78: CBC000000000003498 | BN78: CBC000000000000412 | BO78: CBC000000000002780 | BR78: CBC000000000005235 | BS78: CBC000000000003020 | BV78: CBC000000000001883 | CG78: CBC000000000003188
D79: CBC000000000001326 | N79: CBC000000000000507 | O79: CBC000000000001831 | Q79: CBC000000000003126 | S79: CBC000000000000662 | X79: CBC000000000004415 | AM79: CBC000000000004558 | AN79: CBC000000000005246 | AP79: CBC000000000000078 | AT79: CBC000000000004516 | AV79: CBC000000000004655 | AW79: CBC000000000001222 | AY79: CBC000000000001500 | AZ79: CBC000000000002900 | BC79: CBC000000000001321 | BD79: CBC000000000002715 | BE79: CBC000000000003730 | BH79: CBC000000000003506 | BN79: CBC000000000000392 | BO79: CBC000000000002628 | BR79: CBC000000000004953 | BS79: CBC000000000004052 | BV79: CBC000000000000980
D80: CBC000000000001136 | N80: CBC000000000000544 | O80: CBC000000000001828 | Q80: CBC000000000002618 | S80: CBC000000000000580 | X80: CBC000000000004992 | AM80: CBC000000000003273 | AN80: CBC000000000001712 | AP80: CBC000000000003230 | AT80: CBC000000000003416 | AV80: CBC000000000005004 | AW80: CBC000000000000946 | AY80: CBC000000000001484 | AZ80: CBC000000000001172 | BC80: CBC000000000000491 | BD80: CBC000000000000865 | BE80: CBC000000000003732 | BH80: CBC000000000002991 | BN80: CBC000000000000104 | BO80: CBC000000000003585 | BR80: CBC000000000004378 | BS80: CBC000000000002524 | BV80: CBC000000000001109
D81: CBC000000000001329 | N81: CBC000000000005169 | O81: CBC000000000001829 | Q81: CBC000000000003129 | S81: CBC000000000000993 | X81: CBC000000000002113 | AM81: CBC000000000003974 | AN81: CBC000000000000518 | AP81: CBC000000000003228 | AT81: CBC000000000003770 | AV81: CBC000000000004656 | AW81: CBC000000000001236 | AY81: CBC000000000001670 | AZ81: CBC000000000003923 | BC81: CBC000000000004692 | BD81: CBC000000000001898 | BE81: CBC000000000003729 | BH81: CBC000000000005319 | BN81: CBC000000000000255 | BO81: CBC000000000002937 | BR81: CBC000000000004473 | BS81: CBC000000000002087 | BV81: CBC000000000001709
D82: CBC000000000001058 | N82: CBC000000000005150 | O82: CBC000000000001834 | Q82: CBC000000000004045 | S82: CBC000000000001544 | X82: CBC000000000000708 | AM82: CBC000000000005064 | AN82: CBC000000000001989 | AP82: CBC000000000003340 | AT82: CBC000000000004176 | AV82: CBC000000000005013 | AW82: CBC000000000001352 | AY82: CBC000000000003236 | AZ82: CBC000000000003905 | BC82: CBC000000000003048 | BD82: CBC000000000003826 | BE82: CBC000000000003721 | BH82: CBC000000000004749 | BN82: CBC000000000002985 | BO82: CBC000000000002657 | BR82: CBC000000000004472 | BS82: CBC000000000002088 | BV82: CBC000000000001595
D83: CBC000000000001542 | N83: CBC000000000004030 | O83: CBC000000000001237 | Q83: CBC000000000002058 | S83: CBC000000000000983 | X83: CBC000000000005133 | AM83: CBC000000000003966 | AN83: CBC000000000000470 | AP83: CBC000000000003202 | AT83: CBC000000000003959 | AV83: CBC000000000004705 | AW83: CBC000000000000943 | AY83: CBC000000000001104 | AZ83: CBC000000000003931 | BC83: CBC000000000002136 | BD83: CBC000000000003862 | BE83: CBC000000000003733 | BH83: CBC000000000002428 | BN83: CBC000000000000107 | BO83: CBC000000000004883 | BR83: CBC000000000005196 | BS83: CBC000000000002980 | BV83: CBC000000000001885
D84: CBC000000000001319 | N84: CBC000000000000549 | O84: CBC000000000001842 | Q84: CBC000000000002493 | S84: CBC000000000001003 | X84: CBC000000000005502 | AM84: CBC000000000003272 | AN84: CBC000000000001771 | AP84: CBC000000000003341 | AT84: CBC000000000003804 | AV84: CBC000000000004706 | AW84: CBC000000000000948 | AY84: CBC000000000004205 | AZ84: CBC000000000002785 | BC84: CBC000000000001374 | BD84: CBC000000000003860 | BE84: CBC000000000004451 | BH84: CBC000000000005511 | BN84: CBC000000000005527 | BO84: CBC000000000002963 | BR84: CBC000000000004249 | BS84: CBC000000000003997 | BV84: CBC000000000000761
D85: CBC000000000004047 | N85: CBC000000000005459 | O85: CBC000000000001837 | Q85: CBC000000000002067 | S85: CBC000000000001393 | X85: CBC000000000005122 | AM85: CBC000000000003266 | AN85: CBC000000000000557 | AP85: CBC000000000003344 | AT85: CBC000000000003270 | AV85: CBC000000000004658 | AW85: CBC000000000001241 | AY85: CBC000000000001531 | AZ85: CBC000000000002850 | BC85: CBC000000000000291 | BD85: CBC000000000003847 | BE85: CBC000000000004223 | BH85: CBC000000000005489 | BN85: CBC000000000000496 | BO85: CBC000000000005177 | BR85: CBC000000000004252 | BS85: CBC000000000002215 | BV85: CBC000000000001089
D86: CBC000000000001402 | N86: CBC000000000005460 | O86: CBC000000000002597 | Q86: CBC000000000002311 | S86: CBC000000000001234 | X86: CBC000000000005360 | AM86: CBC000000000004956 | AN86: CBC000000000001780 | AP86: CBC000000000000070 | AT86: CBC000000000005315 | AV86: CBC000000000004659 | AW86: CBC000000000001249 | AY86: CBC000000000003421 | AZ86: CBC000000000002854 | BC86: CBC000000000000444 | BD86: CBC000000000003844 | BE86: CBC000000000004446 | BH86: CBC000000000004625 | BN86: CBC000000000000500 | BO86: CBC000000000002652 | BR86: CBC000000000005208 | BS86: CBC000000000003663 | BV86: CBC000000000001698
D87: CBC000000000001287 | N87: CBC000000000005471 | O87: CBC000000000001841 | Q87: CBC000000000002216 | S87: CBC000000000002176 | X87: CBC000000000001865 | AM87: CBC000000000005066 | AN87: CBC000000000001730 | AP87: CBC000000000003342 | AT87: CBC000000000004800 | AV87: CBC000000000004660 | AW87: CBC000000000000960 | AY87: CBC000000000005272 | AZ87: CBC000000000002853 | BC87: CBC000000000000301 | BD87: CBC000000000002181 | BE87: CBC000000000005340 | BH87: CBC000000000002972 | BN87: CBC000000000000505 | BO87: CBC000000000003111 | BR87: CBC000000000004054 | BS87: CBC000000000003011 | BV87: CBC000000000001701
D88: CBC000000000001400 | N88: CBC000000000003355 | O88: CBC000000000002604 | Q88: CBC000000000002710 | S88: CBC000000000001289 | X88: CBC000000000000614 | AM88: CBC000000000004058 | AN88: CBC000000000001476 | AP88: CBC000000000003343 | AT88: CBC000000000004804 | AV88: CBC000000000004707 | AW88: CBC000000000000955 | AY88: CBC000000000001643 | AZ88: CBC000000000001192 | BC88: CBC000000000002134 | BD88: CBC000000000002182 | BE88: CBC000000000003555 | BH88: CBC000000000002961 | BN88: CBC000000000003422 | BO88: CBC000000000003403 | BR88: CBC000000000005229 | BS88: CBC000000000005554 | BV88: CBC000000000001699
D89: CBC000000000001430 | N89: CBC000000000005192 | O89: CBC000000000005312 | Q89: CBC000000000002024 | S89: CBC000000000001107 | X89: CBC000000000000709 | AN89: CBC000000000001652 | AP89: CBC000000000000065 | AT89: CBC000000000004500 | AV89: CBC000000000004661 | AW89: CBC000000000000962 | AY89: CBC000000000002574 | AZ89: CBC000000000002896 | BC89: CBC000000000002133 | BD89: CBC000000000002722 | BE89: CBC000000000004629 | BH89: CBC000000000003589 | BN89: CBC000000000000113 | BO89: CBC000000000002959 | BR89: CBC000000000005199 | BS89: CBC000000000002085 | BV89: CBC000000000001028
D90: CBC000000000001134 | N90: CBC000000000005147 | O90: CBC000000000005262 | Q90: CBC000000000001975 | S90: CBC000000000000957 | X90: CBC000000000004306 | AN90: CBC000000000000467 | AP90: CBC000000000003193 | AT90: CBC000000000004509 | AV90: CBC000000000004708 | AW90: CBC000000000000964 | AY90: CBC000000000002830 | AZ90: CBC000000000003912 | BC90: CBC000000000002132 | BD90: CBC000000000004529 | BE90: CBC000000000004870 | BH90: CBC000000000002670 | BN90: CBC000000000000119 | BO90: CBC000000000005026 | BR90: CBC000000000004474 | BS90: CBC000000000004012 | BV90: CBC000000000001691
D91: CBC000000000001447 | N91: CBC000000000000050 | O91: CBC000000000002601 | Q91: CBC000000000002337 | S91: CBC000000000002051 | X91: CBC000000000005347 | AN91: CBC000000000001811 | AT91: CBC000000000004366 | AV91: CBC000000000004663 | AW91: CBC000000000001264 | AY91: CBC000000000001739 | AZ91: CBC000000000004271 | BC91: CBC000000000000469 | BD91: CBC000000000002423 | BE91: CBC000000000003446 | BH91: CBC000000000005496 | BN91: CBC000000000000329 | BO91: CBC000000000003392 | BR91: CBC000000000005207 | BS91: CBC000000000002996 | BV91: CBC000000000005107
D92: CBC000000000001559 | N92: CBC000000000002271 | O92: CBC000000000002567 | Q92: CBC000000000002213 | S92: CBC000000000001433 | X92: CBC000000000005357 | AN92: CBC000000000000663 | AT92: CBC000000000003799 | AV92: CBC000000000005031 | AW92: CBC000000000000976 | AY92: CBC000000000001114 | AZ92: CBC000000000002767 | BC92: CBC000000000001357 | BD92: CBC000000000000843 | BE92: CBC000000000003639 | BH92: CBC000000000003354 | BN92: CBC000000000000331 | BO92: CBC000000000004964 | BR92: CBC000000000004386 | BS92: CBC000000000003014 | BV92: CBC000000000001687
D93: CBC000000000001190 | N93: CBC000000000000023 | O93: CBC000000000001731 | Q93: CBC000000000003125 | S93: CBC000000000001371 | X93: CBC000000000005358 | AN93: CBC000000000001994 | AT93: CBC000000000003587 | AV93: CBC000000000004664 | AW93: CBC000000000001356 | AY93: CBC000000000001068 | AZ93: CBC000000000002845 | BC93: CBC000000000002150 | BD93: CBC000000000002171 | BE93: CBC000000000004425 | BH93: CBC000000000004761 | BN93: CBC000000000000333 | BO93: CBC000000000004007 | BR93: CBC000000000004256 | BS93: CBC000000000002086 | BV93: CBC000000000001490
D94: CBC000000000001441 | N94: CBC000000000000015 | O94: CBC000000000002614 | Q94: CBC000000000003054 | S94: CBC000000000001521 | X94: CBC000000000003039 | AN94: CBC000000000001995 | AT94: CBC000000000004917 | AV94: CBC000000000005033 | AW94: CBC000000000000572 | AY94: CBC000000000001460 | AZ94: CBC000000000001225 | BC94: CBC000000000000356 | BD94: CBC000000000003829 | BE94: CBC000000000003070 | BH94: CBC000000000003572 | BN94: CBC000000000000346 | BO94: CBC000000000002295 | BR94: CBC000000000004257 | BV94: CBC000000000001516
D95: CBC000000000001569 | N95: CBC000000000005118 | O95: CBC000000000002615 | Q95: CBC000000000004448 | S95: CBC000000000002054 | X95: CBC000000000001050 | AN95: CBC000000000002662 | AT95: CBC000000000003775 | AV95: CBC000000000004665 | AW95: CBC000000000001734 | AY95: CBC000000000001673 | AZ95: CBC000000000001255 | BC95: CBC000000000001379 | BD95: CBC000000000003865 | BE95: CBC000000000004247 | BH95: CBC000000000005512 | BN95: CBC000000000000351 | BO95: CBC000000000003534 | BR95: CBC000000000004258 | BV95: CBC000000000000969
D96: CBC000000000001388 | N96: CBC000000000005148 | O96: CBC000000000001951 | Q96: CBC000000000002286 | S96: CBC000000000005562 | X96: CBC000000000001096 | AN96: CBC000000000000584 | AT96: CBC000000000004333 | AV96: CBC000000000004098 | AW96: CBC000000000001738 | AY96: CBC000000000001681 | AZ96: CBC000000000002837 | BC96: CBC000000000001330 | BD96: CBC000000000000848 | BE96: CBC000000000003378 | BH96: CBC000000000003598 | BN96: CBC000000000000353 | BO96: CBC000000000002740 | BR96: CBC000000000004262 | BV96: CBC000000000000961
D97: CBC000000000001307 | N97: CBC000000000000566 | O97: CBC000000000001888 | Q97: CBC000000000004476 | S97: CBC000000000001616 | X97: CBC000000000001042 | AN97: CBC000000000001958 | AT97: CBC000000000003788 | AV97: CBC000000000004667 | AW97: CBC000000000000818 | AY97: CBC000000000001690 | AZ97: CBC000000000002801 | BC97: CBC000000000003561 | BD97: CBC000000000003867 | BE97: CBC000000000004300 | BH97: CBC000000000005346 | BN97: CBC000000000003972 | BO97: CBC000000000004368 | BR97: CBC000000000004071 | BV97: CBC000000000000855
D98: CBC000000000000672 | N98: CBC000000000005137 | O98: CBC000000000002603 | Q98: CBC000000000002647 | S98: CBC000000000001380 | X98: CBC000000000003034 | AN98: CBC000000000000481 | AT98: CBC000000000003778 | AV98: CBC000000000004668 | AW98: CBC000000000000996 | AY98: CBC000000000001689 | AZ98: CBC000000000002814 | BC98: CBC000000000002526 | BD98: CBC000000000003843 | BE98: CBC000000000002711 | BH98: CBC000000000005495 | BN98: CBC000000000000361 | BR98: CBC000000000005220 | BV98: CBC000000000000781
D99: CBC000000000001332 | N99: CBC000000000000057 | O99: CBC000000000001896 | Q99: CBC000000000002079 | X99: CBC000000000001839 | AN99: CBC000000000002193 | AT99: CBC000000000004871 | AV99: CBC000000000004102 | AW99: CBC000000000001274 | AY99: CBC000000000001627 | AZ99: CBC000000000003911 | BC99: CBC000000000001370 | BD99: CBC000000000002730 | BE99: CBC000000000004826 | BH99: CBC000000000003701 | BN99: CBC000000000000210 | BR99: CBC000000000004263 | BV99: CBC000000000000799
D100: CBC000000000001098 | N100: CBC000000000000048 | O100: CBC000000000001844 | Q100: CBC000000000002534 | X100: CBC000000000005131 | AN100: CBC000000000001927 | AT100: CBC000000000004501 | AV100: CBC000000000004669 | AW100: CBC000000000001208 | AY100: CBC000000000001679 | AZ100: CBC000000000002777 | BC100: CBC000000000001391 | BD100: CBC000000000003873 | BE100: CBC000000000003941 | BH100: CBC000000000003588 | BN100: CBC000000000000214 | BR100: CBC000000000004265 | BV100: CBC000000000001708
...

Sheet CITY
A1: _0128_ILOCOS_NORTE | B1: _12801_ADAMS | C1: _12802_BACARRA | D1: _12803_BADOC | E1: _12804_BANGUI | F1: _12811_BANNA_ESPIRITU | G1: _12806_BURGOS | H1: _12807_CARASI | I1: _12805_CITY_OF_BATAC | J1: _12808_CURRIMAO | K1: _12809_DINGRAS | L1: _12810_DUMALNEG | M1: _12812_LAOAG_CITY | N1: _12813_MARCOS | O1: _12814_NUEVA_ERA | P1: _12815_PAGUDPUD | Q1: _12816_PAOAY | R1: _12817_PASUQUIN | S1: _12818_PIDDIG | T1: _12819_PINILI | U1: _12820_SAN_NICOLAS | V1: _12821_SARRAT | W1: _12822_SOLSONA | X1: _12823_VINTAR
A2: _0129_ILOCOS_SUR | B2: _12901_ALILEM | C2: _12902_BANAYOYO | D2: _12903_BANTAY | E2: _12904_BURGOS | F2: _12905_CABUGAO | G2: _12907_CAOAYAN | H2: _12908_CERVANTES | I2: _12906_CITY_OF_CANDON | J2: _12934_CITY_OF_VIGAN_ | K2: _12909_GALIMUYOD | L2: _12910_GREGORIO_DEL_PILAR_CONCEPCION | M2: _12911_LIDLIDDA | N2: _12912_MAGSINGAL | O2: _12913_NAGBUKEL | P2: _12914_NARVACAN | Q2: _12915_QUIRINO_ANGKAKI | R2: _12916_SALCEDO_BAUGEN | S2: _12917_SAN_EMILIO | T2: _12918_SAN_ESTEBAN | U2: _12919_SAN_ILDEFONSO | V2: _12920_SAN_JUAN_LAPOG | W2: _12921_SAN_VICENTE | X2: _12922_SANTA | Y2: _12923_SANTA_CATALINA | Z2: _12924_SANTA_CRUZ | AA2: _12925_SANTA_LUCIA | AB2: _12926_SANTA_MARIA | AC2: _12927_SANTIAGO | AD2: _12928_SANTO_DOMINGO | AE2: _12929_SIGAY | AF2: _12930_SINAIT | AG2: _12931_SUGPON | AH2: _12932_SUYO | AI2: _12933_TAGUDIN
A3: _0133_LA_UNION | B3: _13301_AGOO | C3: _13302_ARINGAY | D3: _13303_BACNOTAN | E3: _13304_BAGULIN | F3: _13305_BALAOAN | G3: _13306_BANGAR | H3: _13307_BAUANG | I3: _13308_BURGOS | J3: _13309_CABA | K3: _13314_CITY_OF_SAN_FERNANDO | L3: _13310_LUNA | M3: _13311_NAGUILIAN | N3: _13312_PUGO | O3: _13313_ROSARIO | P3: _13315_SAN_GABRIEL | Q3: _13316_SAN_JUAN | R3: _13317_SANTO_TOMAS | S3: _13318_SANTOL | T3: _13319_SUDIPEN | U3: _13320_TUBAO | V3: =dirty!$L$13 -> _12803_BADOC
A4: _0155_PANGASINAN | B4: _15501_AGNO | C4: _15502_AGUILAR | D4: _15504_ALCALA | E4: _15505_ANDA | F4: _15506_ASINGAN | G4: _15507_BALUNGAO | H4: _15508_BANI | I4: _15509_BASISTA | J4: _15510_BAUTISTA | K4: _15511_BAYAMBANG | L4: _15512_BINALONAN | M4: _15513_BINMALEY | N4: _15514_BOLINAO | O4: _15515_BUGALLON | P4: _15516_BURGOS | Q4: _15517_CALASIAO | R4: _15503_CITY_OF_ALAMINOS | S4: _15546_CITY_OF_URDANETA | T4: _15518_DAGUPAN_CITY | U4: _15519_DASOL | V4: _15520_INFANTA | W4: _15521_LABRADOR | X4: _15548_LAOAC | Y4: _15522_LINGAYEN | Z4: _15523_MABINI | AA4: _15524_MALASIQUI | AB4: _15525_MANAOAG | AC4: _15526_MANGALDAN | AD4: _15527_MANGATAREM | AE4: _15528_MAPANDAN | AF4: _15529_NATIVIDAD | AG4: _15530_POZORRUBIO | AH4: _15531_ROSALES | AI4: _15532_SAN_CARLOS_CITY | AJ4: _15533_SAN_FABIAN | AK4: _15534_SAN_JACINTO | AL4: _15535_SAN_MANUEL | AM4: _15536_SAN_NICOLAS | AN4: _15537_SAN_QUINTIN | AO4: _15538_SANTA_BARBARA | AP4: _15539_SANTA_MARIA | AQ4: _15540_SANTO_TOMAS | AR4: _15541_SISON | AS4: _15542_SUAL | AT4: _15543_TAYUG | AU4: _15544_UMINGAN | AV4: _15545_URBIZTONDO | AW4: _15547_VILLASIS
A5: _0209_BATANES | B5: _20901_BASCO | C5: _20902_ITBAYAT | D5: _20903_IVANA | E5: _20904_MAHATAO | F5: _20905_SABTANG | G5: _20906_UYUGAN
A6: _0215_CAGAYAN | B6: _21501_ABULUG | C6: _21502_ALCALA | D6: _21503_ALLACAPAN | E6: _21504_AMULUNG | F6: _21505_APARRI | G6: _21506_BAGGAO | H6: _21507_BALLESTEROS | I6: _21508_BUGUEY | J6: _21509_CALAYAN | K6: _21510_CAMALANIUGAN | L6: _21511_CLAVERIA | M6: _21512_ENRILE | N6: _21513_GATTARAN | O6: _21514_GONZAGA | P6: _21515_IGUIG | Q6: _21516_LAL_LO | R6: _21517_LASAM | S6: _21518_PAMPLONA | T6: _21519_PEÑABLANCA | U6: _21520_PIAT | V6: _21521_RIZAL | W6: _21522_SANCHEZ_MIRA | X6: _21523_SANTA_ANA | Y6: _21524_SANTA_PRAXEDES | Z6: _21525_SANTA_TERESITA | AA6: _21526_SANTO_NIÑO_FAIRE | AB6: _21527_SOLANA | AC6: _21528_TUAO | AD6: _21529_TUGUEGARAO_CITY
A7: _0231_ISABELA | B7: _23101_ALICIA | C7: _23102_ANGADANAN | D7: _23103_AURORA | E7: _23104_BENITO_SOLIVEN | F7: _23105_BURGOS | G7: _23106_CABAGAN | H7: _23107_CABATUAN | I7: _23108_CITY_OF_CAUAYAN | J7: _23135_CITY_OF_SANTIAGO | K7: _23109_CORDON | L7: _23118_DELFIN_ALBANO_MAGSAYSAY | M7: _23110_DINAPIGUE | N7: _23111_DIVILACAN | O7: _23112_ECHAGUE | P7: _23113_GAMU | Q7: _23114_ILAGAN_CITY | R7: _23115_JONES | S7: _23116_LUNA | T7: _23117_MACONACON | U7: _23119_MALLIG | V7: _23120_NAGUILIAN | W7: _23121_PALANAN | X7: _23122_QUEZON | Y7: _23123_QUIRINO | Z7: _23124_RAMON | AA7: _23125_REINA_MERCEDES | AB7: _23126_ROXAS | AC7: _23127_SAN_AGUSTIN | AD7: _23128_SAN_GUILLERMO | AE7: _23129_SAN_ISIDRO | AF7: _23130_SAN_MANUEL | AG7: _23131_SAN_MARIANO | AH7: _23132_SAN_MATEO | AI7: _23133_SAN_PABLO | AJ7: _23134_SANTA_MARIA | AK7: _23136_SANTO_TOMAS | AL7: _23137_TUMAUINI
A8: _0250_NUEVA_VIZCAYA | B8: _25015_ALFONSO_CASTANEDA | C8: _25001_AMBAGUIO | D8: _25002_ARITAO | E8: _25003_BAGABAG | F8: _25004_BAMBANG | G8: _25005_BAYOMBONG | H8: _25006_DIADI | I8: _25007_DUPAX_DEL_NORTE | J8: _25008_DUPAX_DEL_SUR | K8: _25009_KASIBU | L8: _25010_KAYAPA | M8: _25011_QUEZON | N8: _25012_SANTA_FE | O8: _25013_SOLANO | P8: _25014_VILLAVERDE
A9: _0257_QUIRINO | B9: _25701_AGLIPAY | C9: _25702_CABARROGUIS | D9: _25703_DIFFUN | E9: _25704_MADDELA | F9: _25706_NAGTIPUNAN | G9: _25705_SAGUDAY
A10: _0308_BATAAN | B10: _30801_ABUCAY | C10: _30802_BAGAC | D10: _30803_CITY_OF_BALANGA | E10: _30804_DINALUPIHAN | F10: _30805_HERMOSA | G10: _30806_LIMAY | H10: _30807_MARIVELES | I10: _30808_MORONG | J10: _30809_ORANI | K10: _30810_ORION | L10: _30811_PILAR | M10: _30812_SAMAL
A11: _0314_BULACAN | B11: _31401_ANGAT | C11: _31402_BALAGTAS | D11: _31403_BALIUAG | E11: _31404_BOCAUE | F11: _31405_BULACAN | G11: _31406_BUSTOS | H11: _31407_CALUMPIT | I11: _31410_CITY_OF_MALOLOS | J11: _31412_CITY_OF_MEYCAUAYAN | K11: _31420_CITY_OF_SAN_JOSE_DEL_MONTE | L11: _31424_DOÑA_REMEDIOS_TRINIDAD | M11: _31408_GUIGUINTO | N11: _31409_HAGONOY | O11: _31411_MARILAO | P11: _31413_NORZAGARAY | Q11: _31414_OBANDO | R11: _31415_PANDI | S11: _31416_PAOMBONG | T11: _31417_PLARIDEL | U11: _31418_PULILAN | V11: _31419_SAN_ILDEFONSO | W11: _31421_SAN_MIGUEL | X11: _31422_SAN_RAFAEL | Y11: _31423_SANTA_MARIA
A12: _0349_NUEVA_ECIJA | B12: _34901_ALIAGA | C12: _34902_BONGABON | D12: _34903_CABANATUAN_CITY | E12: _34904_CABIAO | F12: _34905_CARRANGLAN | G12: _34908_CITY_OF_GAPAN | H12: _34906_CUYAPO | I12: _34907_GABALDON | J12: _34909_GENERAL_MAMERTO_NATIVIDAD | K12: _34910_GENERAL_TINIO_PAPAYA | L12: _34911_GUIMBA | M12: _34912_JAEN | N12: _34913_LAUR | O12: _34914_LICAB | P12: _34915_LLANERA | Q12: _34916_LUPAO | R12: _34918_NAMPICUAN | S12: _34919_PALAYAN_CITY | T12: _34920_PANTABANGAN | U12: _34921_PEÑARANDA | V12: _34922_QUEZON | W12: _34923_RIZAL | X12: _34924_SAN_ANTONIO | Y12: _34925_SAN_ISIDRO | Z12: _34926_SAN_JOSE_CITY | AA12: _34927_SAN_LEONARDO | AB12: _34928_SANTA_ROSA | AC12: _34929_SANTO_DOMINGO | AD12: _34917_SCIENCE_CITY_OF_MUÑOZ | AE12: _34930_TALAVERA | AF12: _34931_TALUGTUG | AG12: _34932_ZARAGOZA
A13: _0354_PAMPANGA | B13: _35401_ANGELES_CITY | C13: _35402_APALIT | D13: _35403_ARAYAT | E13: _35404_BACOLOR | F13: _35405_CANDABA | G13: _35416_CITY_OF_SAN_FERNANDO | H13: _35406_FLORIDABLANCA | I13: _35407_GUAGUA | J13: _35408_LUBAO | K13: _35409_MABALACAT_CITY | L13: _35410_MACABEBE | M13: _35411_MAGALANG | N13: _35412_MASANTOL | O13: _35413_MEXICO | P13: _35414_MINALIN | Q13: _35415_PORAC | R13: _35417_SAN_LUIS | S13: _35418_SAN_SIMON | T13: _35419_SANTA_ANA | U13: _35420_SANTA_RITA | V13: _35421_SANTO_TOMAS | W13: _35422_SASMUAN_SEXMOAN
A14: _0369_TARLAC | B14: _36901_ANAO | C14: _36902_BAMBAN | D14: _36903_CAMILING | E14: _36904_CAPAS | F14: _36916_CITY_OF_TARLAC | G14: _36905_CONCEPCION | H14: _36906_GERONA | I14: _36907_LA_PAZ | J14: _36908_MAYANTOC | K14: _36909_MONCADA | L14: _36910_PANIQUI | M14: _36911_PURA | N14: _36912_RAMOS | O14: _36913_SAN_CLEMENTE | P14: _36918_SAN_JOSE | Q14: _36914_SAN_MANUEL | R14: _36915_SANTA_IGNACIA | S14: _36917_VICTORIA
A15: _0371_ZAMBALES | B15: _37101_BOTOLAN | C15: _37102_CABANGAN | D15: _37103_CANDELARIA | E15: _37104_CASTILLEJOS | F15: _37105_IBA | G15: _37106_MASINLOC | H15: _37107_OLONGAPO_CITY | I15: _37108_PALAUIG | J15: _37109_SAN_ANTONIO | K15: _37110_SAN_FELIPE | L15: _37111_SAN_MARCELINO | M15: _37112_SAN_NARCISO | N15: _37113_SANTA_CRUZ | O15: _37114_SUBIC
A16: _0377_AURORA | B16: _37701_BALER | C16: _37702_CASIGURAN | D16: _37703_DILASAG | E16: _37704_DINALUNGAN | F16: _37705_DINGALAN | G16: _37706_DIPACULAO | H16: _37707_MARIA_AURORA | I16: _37708_SAN_LUIS
A17: _0410_BATANGAS | B17: _41001_AGONCILLO | C17: _41002_ALITAGTAG | D17: _41003_BALAYAN | E17: _41004_BALETE | F17: _41005_BATANGAS_CITY | G17: _41006_BAUAN | H17: _41007_CALACA | I17: _41008_CALATAGAN | J17: _41031_CITY_OF_TANAUAN | K17: _41009_CUENCA | L17: _41010_IBAAN | M17: _41011_LAUREL | N17: _41012_LEMERY | O17: _41013_LIAN | P17: _41014_LIPA_CITY | Q17: _41015_LOBO | R17: _41016_MABINI | S17: _41017_MALVAR | T17: _41018_MATAASNAKAHOY | U17: _41019_NASUGBU | V17: _41020_PADRE_GARCIA | W17: _41021_ROSARIO | X17: _41022_SAN_JOSE | Y17: _41023_SAN_JUAN | Z17: _41024_SAN_LUIS | AA17: _41025_SAN_NICOLAS | AB17: _41026_SAN_PASCUAL | AC17: _41027_SANTA_TERESITA | AD17: _41028_SANTO_TOMAS | AE17: _41029_TAAL | AF17: _41030_TALISAY | AG17: _41032_TAYSAN | AH17: _41033_TINGLOY | AI17: _41034_TUY
A18: _0421_CAVITE | B18: _42101_ALFONSO | C18: _42102_AMADEO | D18: _42103_BACOOR_CITY | E18: _42104_CARMONA | F18: _42105_CAVITE_CITY | G18: _42106_CITY_OF_DASMARIÑAS | H18: _42123_GEN._MARIANO_ALVAREZ | I18: _42107_GENERAL_EMILIO_AGUINALDO | J18: _42108_GENERAL_TRIAS | K18: _42109_IMUS_CITY | L18: _42110_INDANG | M18: _42111_KAWIT | N18: _42112_MAGALLANES | O18: _42113_MARAGONDON | P18: _42114_MENDEZ_MENDEZ_NUÑEZ | Q18: _42115_NAIC | R18: _42116_NOVELETA | S18: _42117_ROSARIO | T18: _42118_SILANG | U18: _42119_TAGAYTAY_CITY | V18: _42120_TANZA | W18: _42121_TERNATE | X18: _42122_TRECE_MARTIRES_CITY
A19: _0434_LAGUNA | B19: _43401_ALAMINOS | C19: _43402_BAY | D19: _43404_CABUYAO_CITY | E19: _43406_CALAUAN | F19: _43407_CAVINTI | G19: _43403_CITY_OF_BIÑAN | H19: _43405_CITY_OF_CALAMBA | I19: _43425_CITY_OF_SAN_PEDRO | J19: _43428_CITY_OF_SANTA_ROSA | K19: _43408_FAMY | L19: _43409_KALAYAAN | M19: _43410_LILIW | N19: _43411_LOS_BAÑOS | O19: _43412_LUISIANA | P19: _43413_LUMBAN | Q19: _43414_MABITAC | R19: _43415_MAGDALENA | S19: _43416_MAJAYJAY | T19: _43417_NAGCARLAN | U19: _43418_PAETE | V19: _43419_PAGSANJAN | W19: _43420_PAKIL | X19: _43421_PANGIL | Y19: _43422_PILA | Z19: _43423_RIZAL | AA19: _43424_SAN_PABLO_CITY | AB19: _43426_SANTA_CRUZ | AC19: _43427_SANTA_MARIA | AD19: _43429_SINILOAN | AE19: _43430_VICTORIA
A20: _0456_QUEZON | B20: _45601_AGDANGAN | C20: _45602_ALABAT | D20: _45603_ATIMONAN | E20: _45605_BUENAVISTA | F20: _45606_BURDEOS | G20: _45607_CALAUAG | H20: _45608_CANDELARIA | I20: _45610_CATANAUAN | J20: _45647_CITY_OF_TAYABAS | K20: _45615_DOLORES | L20: _45616_GENERAL_LUNA | M20: _45617_GENERAL_NAKAR | N20: _45618_GUINAYANGAN | O20: _45619_GUMACA | P20: _45620_INFANTA | Q20: _45621_JOMALIG | R20: _45622_LOPEZ | S20: _45623_LUCBAN | T20: _45624_LUCENA_CITY | U20: _45625_MACALELON | V20: _45627_MAUBAN | W20: _45628_MULANAY | X20: _45629_PADRE_BURGOS | Y20: _45630_PAGBILAO | Z20: _45631_PANUKULAN | AA20: _45632_PATNANUNGAN | AB20: _45633_PEREZ | AC20: _45634_PITOGO | AD20: _45635_PLARIDEL | AE20: _45636_POLILLO | AF20: _45637_QUEZON | AG20: _45638_REAL | AH20: _45639_SAMPALOC | AI20: _45640_SAN_ANDRES | AJ20: _45641_SAN_ANTONIO | AK20: _45642_SAN_FRANCISCO_AURORA | AL20: _45644_SAN_NARCISO | AM20: _45645_SARIAYA | AN20: _45646_TAGKAWAYAN | AO20: _45648_TIAONG | AP20: _45649_UNISAN
A21: _0458_RIZAL | B21: _45801_ANGONO | C21: _45803_BARAS | D21: _45804_BINANGONAN | E21: _45805_CAINTA | F21: _45806_CARDONA | G21: _45802_CITY_OF_ANTIPOLO | H21: _45807_JALA_JALA | I21: _45809_MORONG | J21: _45810_PILILLA | K21: _45808_RODRIGUEZ_MONTALBAN | L21: _45811_SAN_MATEO | M21: _45812_TANAY | N21: _45813_TAYTAY | O21: _45814_TERESA
A22: _0505_ALBAY | B22: _50501_BACACAY | C22: _50502_CAMALIG | D22: _50508_CITY_OF_LIGAO | E22: _50517_CITY_OF_TABACO | F22: _50503_DARAGA | G22: _50504_GUINOBATAN | H22: _50505_JOVELLAR | I22: _50506_LEGAZPI_CITY | J22: _50507_LIBON | K22: _50509_MALILIPOT | L22: _50510_MALINAO | M22: _50511_MANITO | N22: _50512_OAS | O22: _50513_PIO_DURAN | P22: _50514_POLANGUI | Q22: _50515_RAPU_RAPU | R22: _50516_SANTO_DOMINGO | S22: _50518_TIWI
A23: _0516_CAMARINES_NORTE | B23: _51601_BASUD | C23: _51602_CAPALONGA | D23: _51603_DAET_ | E23: _51605_JOSE_PANGANIBAN | F23: _51606_LABO | G23: _51607_MERCEDES | H23: _51608_PARACALE | I23: _51604_SAN_LORENZO_RUIZ | J23: _51609_SAN_VICENTE | K23: _51610_SANTA_ELENA | L23: _51611_TALISAY | M23: _51612_VINZONS
A24: _0517_CAMARINES_SUR | B24: _51701_BAAO | C24: _51702_BALATAN | D24: _51703_BATO | E24: _51704_BOMBON | F24: _51705_BUHI | G24: _51706_BULA | H24: _51707_CABUSAO | I24: _51708_CALABANGA | J24: _51709_CAMALIGAN | K24: _51710_CANAMAN | L24: _51711_CARAMOAN | M24: _51712_DEL_GALLEGO | N24: _51713_GAINZA | O24: _51714_GARCHITORENA | P24: _51715_GOA | Q24: _51716_IRIGA_CITY | R24: _51717_LAGONOY | S24: _51718_LIBMANAN | T24: _51719_LUPI | U24: _51720_MAGARAO | V24: _51721_MILAOR | W24: _51722_MINALABAC | X24: _51723_NABUA | Y24: _51724_NAGA_CITY | Z24: _51725_OCAMPO | AA24: _51726_PAMPLONA | AB24: _51727_PASACAO | AC24: _51728_PILI | AD24: _51729_PRESENTACION | AE24: _51730_RAGAY | AF24: _51731_SAGÑAY | AG24: _51732_SAN_FERNANDO | AH24: _51733_SAN_JOSE | AI24: _51734_SIPOCOT | AJ24: _51735_SIRUMA | AK24: _51736_TIGAON | AL24: _51737_TINAMBAC
A25: _0520_CATANDUANES | B25: _52001_BAGAMANOC | C25: _52002_BARAS | D25: _52003_BATO | E25: _52004_CARAMORAN | F25: _52005_GIGMOTO | G25: _52006_PANDAN | H25: _52007_PANGANIBAN | I25: _52008_SAN_ANDRES | J25: _52009_SAN_MIGUEL | K25: _52010_VIGA | L25: _52011_VIRAC
A26: _0541_MASBATE | B26: _54101_AROROY | C26: _54102_BALENO | D26: _54103_BALUD | E26: _54104_BATUAN | F26: _54105_CATAINGAN | G26: _54106_CAWAYAN | H26: _54111_CITY_OF_MASBATE | I26: _54107_CLAVERIA | J26: _54108_DIMASALANG | K26: _54109_ESPERANZA | L26: _54110_MANDAON | M26: _54112_MILAGROS | N26: _54113_MOBO | O26: _54114_MONREAL | P26: _54115_PALANAS | Q26: _54116_PIO_V_CORPUZ | R26: _54117_PLACER | S26: _54118_SAN_FERNANDO | T26: _54119_SAN_JACINTO | U26: _54120_SAN_PASCUAL | V26: _54121_USON
A27: _0562_SORSOGON | B27: _56202_BARCELONA | C27: _56203_BULAN | D27: _56204_BULUSAN | E27: _56205_CASIGURAN | F27: _56206_CASTILLA | G27: _56216_CITY_OF_SORSOGON | H27: _56207_DONSOL | I27: _56208_GUBAT | J27: _56209_IROSIN | K27: _56210_JUBAN | L27: _56211_MAGALLANES | M27: _56212_MATNOG | N27: _56213_PILAR | O27: _56214_PRIETO_DIAZ | P27: _56215_SANTA_MAGDALENA
A28: _0604_AKLAN | B28: _60401_ALTAVAS | C28: _60402_BALETE | D28: _60403_BANGA | E28: _60404_BATAN | F28: _60405_BURUANGA | G28: _60406_IBAJAY | H28: _60407_KALIBO | I28: _60408_LEZO | J28: _60409_LIBACAO | K28: _60410_MADALAG | L28: _60411_MAKATO | M28: _60412_MALAY | N28: _60413_MALINAO | O28: _60414_NABAS | P28: _60415_NEW_WASHINGTON | Q28: _60416_NUMANCIA | R28: _60417_TANGALAN
A29: _0606_ANTIQUE | B29: _60601_ANINI_Y | C29: _60602_BARBAZA | D29: _60603_BELISON | E29: _60604_BUGASONG | F29: _60605_CALUYA | G29: _60606_CULASI | H29: _60608_HAMTIC | I29: _60609_LAUA_AN | J29: _60610_LIBERTAD | K29: _60611_PANDAN | L29: _60612_PATNONGON | M29: _60613_SAN_JOSE | N29: _60614_SAN_REMIGIO | O29: _60615_SEBASTE | P29: _60616_SIBALOM | Q29: _60617_TIBIAO | R29: _60607_TOBIAS_FORNIER_DAO | S29: _60618_VALDERRAMA | T29: _60617_TIBIAO | U29: _60607_TOBIAS_FORNIER_DAO | V29: _60618_VALDERRAMA
A30: _0619_CAPIZ | B30: _61901_CUARTERO | C30: _61902_DAO | D30: _61903_DUMALAG | E30: _61904_DUMARAO | F30: _61905_IVISAN | G30: _61906_JAMINDAN | H30: _61907_MA_AYON | I30: _61908_MAMBUSAO | J30: _61909_PANAY | K30: _61910_PANITAN | L30: _61911_PILAR | M30: _61912_PONTEVEDRA | N30: _61913_PRESIDENT_ROXAS | O30: _61914_ROXAS_CITY | P30: _61915_SAPI_AN | Q30: _61916_SIGMA | R30: _61917_TAPAZ
A31: _0630_ILOILO | B31: _63001_AJUY | C31: _63002_ALIMODIAN | D31: _63003_ANILAO | E31: _63004_BADIANGAN | F31: _63005_BALASAN | G31: _63006_BANATE | H31: _63007_BAROTAC_NUEVO | I31: _63008_BAROTAC_VIEJO | J31: _63009_BATAD | K31: _63010_BINGAWAN | L31: _63012_CABATUAN | M31: _63013_CALINOG | N31: _63014_CARLES | O31: _63035_CITY_OF_PASSI | P31: _63015_CONCEPCION | Q31: _63016_DINGLE | R31: _63017_DUEÑAS | S31: _63018_DUMANGAS | T31: _63019_ESTANCIA | U31: _63020_GUIMBAL | V31: _63021_IGBARAS | W31: _63022_ILOILO_CITY | X31: _63023_JANIUAY | Y31: _63025_LAMBUNAO | Z31: _63026_LEGANES | AA31: _63027_LEMERY | AB31: _63028_LEON | AC31: _63029_MAASIN | AD31: _63030_MIAGAO | AE31: _63031_MINA | AF31: _63032_NEW_LUCENA | AG31: _63034_OTON | AH31: _63036_PAVIA | AI31: _63037_POTOTAN | AJ31: _63038_SAN_DIONISIO | AK31: _63039_SAN_ENRIQUE | AL31: _63040_SAN_JOAQUIN | AM31: _63041_SAN_MIGUEL | AN31: _63042_SAN_RAFAEL | AO31: _63043_SANTA_BARBARA | AP31: _63044_SARA | AQ31: _63045_TIGBAUAN | AR31: _63046_TUBUNGAN | AS31: _63047_ZARRAGA | AT31: _63045_TIGBAUAN | AU31: _63046_TUBUNGAN | AV31: _63047_ZARRAGA
A32: _0679_GUIMARAS | B32: _67901_BUENAVISTA | C32: _67902_JORDAN_ | D32: _67903_NUEVA_VALENCIA | E32: _67904_SAN_LORENZO | F32: _67905_SIBUNAG
A33: _0645_NEGROS_OCCIDENTAL | B33: _64501_BACOLOD_CITY | C33: _64502_BAGO_CITY | D33: _64503_BINALBAGAN | E33: _64504_CADIZ_CITY | F33: _64505_CALATRAVA | G33: _64506_CANDONI | H33: _64507_CAUAYAN | I33: _64509_CITY_OF_ESCALANTE | J33: _64510_CITY_OF_HIMAMAYLAN | K33: _64515_CITY_OF_KABANKALAN | L33: _64527_CITY_OF_SIPALAY | M33: _64528_CITY_OF_TALISAY | N33: _64531_CITY_OF_VICTORIAS | O33: _64508_ENRIQUE_B_MAGALONA_SARAVIA | P33: _64511_HINIGARAN | Q33: _64512_HINOBA_AN_ASIA | R33: _64513_ILOG | S33: _64514_ISABELA | T33: _64516_LA_CARLOTA_CITY | U33: _64517_LA_CASTELLANA | V33: _64518_MANAPLA | W33: _64519_MOISES_PADILLA_MAGALLON | X33: _64520_MURCIA | Y33: _64521_PONTEVEDRA | Z33: _64522_PULUPANDAN | AA33: _64523_SAGAY_CITY | AB33: _64532_SALVADOR_BENEDICTO | AC33: _64524_SAN_CARLOS_CITY | AD33: _64525_SAN_ENRIQUE | AE33: _64526_SILAY_CITY | AF33: _64529_TOBOSO | AG33: _64530_VALLADOLID | AH33: _64529_TOBOSO | AI33: _64530_VALLADOLID
A34: _0712_BOHOL | B34: _71201_ALBURQUERQUE | C34: _71202_ALICIA | D34: _71203_ANDA | E34: _71204_ANTEQUERA | F34: _71205_BACLAYON | G34: _71206_BALILIHAN | H34: _71207_BATUAN | I34: _71248_BIEN_UNIDO | J34: _71208_BILAR | K34: _71209_BUENAVISTA | L34: _71210_CALAPE | M34: _71211_CANDIJAY | N34: _71212_CARMEN | O34: _71213_CATIGBIAN | P34: _71214_CLARIN | Q34: _71215_CORELLA | R34: _71216_CORTES | S34: _71217_DAGOHOY | T34: _71218_DANAO | U34: _71219_DAUIS | V34: _71220_DIMIAO | W34: _71221_DUERO | X34: _71222_GARCIA_HERNANDEZ | Y34: _71223_GUINDULMAN | Z34: _71224_INABANGA | AA34: _71225_JAGNA | AB34: _71226_JETAFE | AC34: _71227_LILA | AD34: _71228_LOAY | AE34: _71229_LOBOC | AF34: _71230_LOON | AG34: _71231_MABINI | AH34: _71232_MARIBOJOC | AI34: _71233_PANGLAO | AJ34: _71234_PILAR | AK34: _71235_PRES_CARLOS_P_GARCIA_PITOGO | AL34: _71236_SAGBAYAN_BORJA | AM34: _71237_SAN_ISIDRO | AN34: _71238_SAN_MIGUEL | AO34: _71239_SEVILLA | AP34: _71240_SIERRA_BULLONES | AQ34: _71241_SIKATUNA | AR34: _71242_TAGBILARAN_CITY | AS34: _71243_TALIBON | AT34: _71244_TRINIDAD | AU34: _71245_TUBIGON | AV34: _71246_UBAY | AW34: _71247_VALENCIA
A35: _0722_CEBU | B35: _72201_ALCANTARA | C35: _72202_ALCOY | D35: _72203_ALEGRIA | E35: _72204_ALOGUINSAN | F35: _72205_ARGAO | G35: _72206_ASTURIAS | H35: _72207_BADIAN | I35: _72208_BALAMBAN | J35: _72209_BANTAYAN | K35: _72210_BARILI | L35: _72212_BOLJOON | M35: _72213_BORBON | N35: _72215_CARMEN | O35: _72216_CATMON | P35: _72217_CEBU_CITY | Q35: _72211_CITY_OF_BOGO | R35: _72214_CITY_OF_CARCAR | S35: _72234_CITY_OF_NAGA | T35: _72250_CITY_OF_TALISAY | U35: _72218_COMPOSTELA | V35: _72219_CONSOLACION | W35: _72220_CORDOVA | X35: _72221_DAANBANTAYAN | Y35: _72222_DALAGUETE | Z35: _72223_DANAO_CITY | AA35: _72224_DUMANJUG | AB35: _72225_GINATILAN | AC35: _72226_LAPU_LAPU_CITY_OPON | AD35: _72227_LILOAN | AE35: _72228_MADRIDEJOS | AF35: _72229_MALABUYOC | AG35: _72230_MANDAUE_CITY | AH35: _72231_MEDELLIN | AI35: _72232_MINGLANILLA | AJ35: _72233_MOALBOAL | AK35: _72235_OSLOB | AL35: _72236_PILAR | AM35: _72237_PINAMUNGAHAN | AN35: _72238_PORO | AO35: _72239_RONDA | AP35: _72240_SAMBOAN | AQ35: _72241_SAN_FERNANDO | AR35: _72242_SAN_FRANCISCO | AS35: _72243_SAN_REMIGIO | AT35: _72244_SANTA_FE | AU35: _72245_SANTANDER | AV35: _72246_SIBONGA | AW35: _72247_SOGOD | AX35: _72248_TABOGON | AY35: _72249_TABUELAN | AZ35: _72251_TOLEDO_CITY | BA35: _72252_TUBURAN | BB35: _72253_TUDELA
A36: _0761_SIQUIJOR | B36: _76101_ENRIQUE_VILLANUEVA | C36: _76102_LARENA | D36: _76103_LAZI | E36: _76104_MARIA | F36: _76105_SAN_JUAN | G36: _76106_SIQUIJOR
A37: _0746_NEGROS_ORIENTAL | B37: _74601_AMLAN_AYUQUITAN | C37: _74602_AYUNGON | D37: _74603_BACONG | E37: _74604_BAIS_CITY | F37: _74605_BASAY | G37: _74607_BINDOY_PAYABON | H37: _74608_CANLAON_CITY | I37: _74606_CITY_OF_BAYAWAN | J37: _74611_CITY_OF_GUIHULNGAN | K37: _74621_CITY_OF_TANJAY | L37: _74609_DAUIN | M37: _74610_DUMAGUETE_CITY | N37: _74612_JIMALALUD | O37: _74613_LA_LIBERTAD | P37: _74614_MABINAY | Q37: _74615_MANJUYOD | R37: _74616_PAMPLONA | S37: _74617_SAN_JOSE | T37: _74618_SANTA_CATALINA | U37: _74619_SIATON | V37: _74620_SIBULAN | W37: _74622_TAYASAN | X37: _74623_VALENCIA_LUZURRIAGA | Y37: _74624_VALLEHERMOSO | Z37: _74625_ZAMBOANGUITA
A38: _0826_EASTERN_SAMAR | B38: _82601_ARTECHE | C38: _82602_BALANGIGA | D38: _82603_BALANGKAYAN | E38: _82605_CAN_AVID | F38: _82604_CITY_OF_BORONGAN | G38: _82606_DOLORES | H38: _82607_GENERAL_MACARTHUR | I38: _82608_GIPORLOS | J38: _82609_GUIUAN | K38: _82610_HERNANI | L38: _82611_JIPAPAD | M38: _82612_LAWAAN | N38: _82613_LLORENTE | O38: _82614_MASLOG | P38: _82615_MAYDOLONG | Q38: _82616_MERCEDES | R38: _82617_ORAS | S38: _82618_QUINAPONDAN | T38: _82619_SALCEDO | U38: _82620_SAN_JULIAN | V38: _82621_SAN_POLICARPO | W38: _82622_SULAT | X38: _82623_TAFT
A39: _0837_LEYTE | B39: _83701_ABUYOG | C39: _83702_ALANGALANG | D39: _83703_ALBUERA | E39: _83705_BABATNGON | F39: _83706_BARUGO | G39: _83707_BATO | H39: _83710_BURAUEN | I39: _83713_CALUBIAN | J39: _83714_CAPOOCAN | K39: _83715_CARIGARA | L39: _83708_CITY_OF_BAYBAY | M39: _83717_DAGAMI | N39: _83718_DULAG | O39: _83719_HILONGOS | P39: _83720_HINDANG | Q39: _83721_INOPACAN | R39: _83722_ISABEL | S39: _83723_JARO | T39: _83724_JAVIER_BUGHO | U39: _83725_JULITA | V39: _83726_KANANGA | W39: _83728_LA_PAZ | X39: _83729_LEYTE | Y39: _83730_MACARTHUR | Z39: _83731_MAHAPLAG | AA39: _83733_MATAG_OB | AB39: _83734_MATALOM | AC39: _83735_MAYORGA | AD39: _83736_MERIDA | AE39: _83738_ORMOC_CITY | AF39: _83739_PALO | AG39: _83740_PALOMPON | AH39: _83741_PASTRANA | AI39: _83742_SAN_ISIDRO | AJ39: _83743_SAN_MIGUEL | AK39: _83744_SANTA_FE | AL39: _83745_TABANGO | AM39: _83746_TABONTABON | AN39: _83747_TACLOBAN_CITY | AO39: _83748_TANAUAN | AP39: _83749_TOLOSA | AQ39: _83750_TUNGA | AR39: _83751_VILLABA
A40: _0848_NORTHERN_SAMAR | B40: _84801_ALLEN | C40: _84802_BIRI | D40: _84803_BOBON | E40: _84804_CAPUL | F40: _84805_CATARMAN | G40: _84806_CATUBIG | H40: _84807_GAMAY | I40: _84808_LAOANG | J40: _84809_LAPINIG | K40: _84810_LAS_NAVAS | L40: _84811_LAVEZARES | M40: _84824_LOPE_DE_VEGA | N40: _84812_MAPANAS | O40: _84813_MONDRAGON | P40: _84814_PALAPAG | Q40: _84815_PAMBUJAN | R40: _84816_ROSARIO | S40: _84817_SAN_ANTONIO | T40: _84818_SAN_ISIDRO | U40: _84819_SAN_JOSE | V40: _84820_SAN_ROQUE | W40: _84821_SAN_VICENTE | X40: _84822_SILVINO_LOBOS | Y40: _84823_VICTORIA
A41: _0860_SAMAR_WESTERN_SAMAR | B41: _86001_ALMAGRO | C41: _86002_BASEY | D41: _86003_CALBAYOG_CITY | E41: _86004_CALBIGA | F41: _86005_CITY_OF_CATBALOGAN | G41: _86006_DARAM | H41: _86007_GANDARA | I41: _86008_HINABANGAN | J41: _86009_JIABONG | K41: _86010_MARABUT | L41: _86011_MATUGUINAO | M41: _86012_MOTIONG | N41: _86026_PAGSANGHAN | O41: _86022_PARANAS_WRIGHT | P41: _86013_PINABACDAO | Q41: _86025_SAN_JORGE | R41: _86014_SAN_JOSE_DE_BUAN | S41: _86015_SAN_SEBASTIAN | T41: _86016_SANTA_MARGARITA | U41: _86017_SANTA_RITA | V41: _86018_SANTO_NIÑO | W41: _86024_TAGAPUL_AN | X41: _86019_TALALORA | Y41: _86020_TARANGNAN | Z41: _86021_VILLAREAL | AA41: _86023_ZUMARRAGA
A42: _0864_SOUTHERN_LEYTE | B42: _86401_ANAHAWAN | C42: _86402_BONTOC | D42: _86407_CITY_OF_MAASIN | E42: _86403_HINUNANGAN | F42: _86404_HINUNDAYAN | G42: _86405_LIBAGON | H42: _86406_LILOAN | I42: _86419_LIMASAWA | J42: _86408_MACROHON | K42: _86409_MALITBOG | L42: _86410_PADRE_BURGOS | M42: _86411_PINTUYAN | N42: _86412_SAINT_BERNARD | O42: _86413_SAN_FRANCISCO | P42: _86414_SAN_JUAN_CABALIAN | Q42: _86415_SAN_RICARDO | R42: _86416_SILAGO | S42: _86417_SOGOD | T42: _86418_TOMAS_OPPUS
A43: _0878_BILIRAN | B43: _87801_ALMERIA | C43: _87802_BILIRAN | D43: _87803_CABUCGAYAN | E43: _87804_CAIBIRAN | F43: _87805_CULABA | G43: _87806_KAWAYAN | H43: _87807_MARIPIPI | I43: _87808_NAVAL
A44: _0972_ZAMBOANGA_DEL_NORTE | B44: _97226_BACUNGAN_LEON_T_POSTIGO | C44: _97224_BALIGUIAN | D44: _97201_DAPITAN_CITY | E44: _97202_DIPOLOG_CITY | F44: _97225_GODOD | G44: _97223_GUTALAC | H44: _97222_JOSE_DALMAN_PONOT | I44: _97227_KALAWIT | J44: _97203_KATIPUNAN | K44: _97204_LA_LIBERTAD | L44: _97205_LABASON | M44: _97206_LILOY | N44: _97207_MANUKAN | O44: _97208_MUTIA | P44: _97209_PIÑAN_NEW_PIÑAN | Q44: _97210_POLANCO | R44: _97211_PRES_MANUEL_A_ROXAS | S44: _97212_RIZAL | T44: _97213_SALUG | U44: _97214_SERGIO_OSMENA_SR | V44: _97215_SIAYAN | W44: _97216_SIBUCO | X44: _97217_SIBUTAD | Y44: _97218_SINDANGAN | Z44: _97219_SIOCON | AA44: _97220_SIRAWAI | AB44: _97221_TAMPILISAN
A45: _0973_ZAMBOANGA_DEL_SUR | B45: _97302_AURORA | C45: _97303_BAYOG | D45: _97305_DIMATALING | E45: _97306_DINAS | F45: _97307_DUMALINAO | G45: _97308_DUMINGAG | H45: _97343_GUIPOS | I45: _97337_JOSEFINA | J45: _97311_KUMALARANG | K45: _97312_LABANGAN | L45: _97333_LAKEWOOD | M45: _97313_LAPUYAN | N45: _97315_MAHAYAG | O45: _97317_MARGOSATUBIG | P45: _97318_MIDSALIP | Q45: _97319_MOLAVE | R45: _97322_PAGADIAN_CITY | S45: _97338_PITOGO | T45: _97323_RAMON_MAGSAYSAY_LIARGO | U45: _97324_SAN_MIGUEL | V45: _97325_SAN_PABLO | W45: _97340_SOMINOT_DON_MARIANO_MARCOS | X45: _97327_TABINA | Y45: _97328_TAMBULIG | Z45: _97344_TIGBAO | AA45: _97330_TUKURAN | AB45: _97341_VINCENZO_A_SAGUN | AC45: _97332_ZAMBOANGA_CITY
A46: _0983_ZAMBOANGA_SIBUGAY | B46: _98301_ALICIA | C46: _98302_BUUG | D46: _98303_DIPLAHAN | E46: _98304_IMELDA | F46: _98305_IPIL_ | G46: _98306_KABASALAN | H46: _98307_MABUHAY | I46: _98308_MALANGAS | J46: _98309_NAGA | K46: _98310_OLUTANGA | L46: _98311_PAYAO | M46: _98312_ROSELLER_LIM | N46: _98313_SIAY | O46: _98314_TALUSAN | P46: _98315_TITAY | Q46: _98316_TUNGAWAN
A47: _0997_CITY_OF_ISABELA | B47: _99701_CITY_OF_ISABELA
A48: _1013_BUKIDNON | B48: _101301_BAUNGON | C48: _101322_CABANGLASAN | D48: _101312_CITY_OF_MALAYBALAY | E48: _101321_CITY_OF_VALENCIA | F48: _101302_DAMULOG | G48: _101303_DANGCAGAN | H48: _101304_DON_CARLOS | I48: _101305_IMPASUG_ONG | J48: _101306_KADINGILAN | K48: _101307_KALILANGAN | L48: _101308_KIBAWE | M48: _101309_KITAOTAO | N48: _101310_LANTAPAN | O48: _101311_LIBONA | P48: _101313_MALITBOG | Q48: _101314_MANOLO_FORTICH | R48: _101315_MARAMAG | S48: _101316_PANGANTUCAN | T48: _101317_QUEZON | U48: _101318_SAN_FERNANDO | V48: _101319_SUMILAO | W48: _101320_TALAKAG
A49: _1018_CAMIGUIN | B49: _101801_CATARMAN | C49: _101802_GUINSILIBAN | D49: _101803_MAHINOG | E49: _101804_MAMBAJAO | F49: _101805_SAGAY
A50: _1035_LANAO_DEL_NORTE | B50: _103501_BACOLOD | C50: _103502_BALOI | D50: _103503_BAROY | E50: _103504_ILIGAN_CITY | F50: _103505_KAPATAGAN | G50: _103507_KAUSWAGAN | H50: _103508_KOLAMBUGAN | I50: _103509_LALA | J50: _103510_LINAMON | K50: _103511_MAGSAYSAY | L50: _103512_MAIGO | M50: _103513_MATUNGAO | N50: _103514_MUNAI | O50: _103515_NUNUNGAN | P50: _103516_PANTAO_RAGAT | Q50: _103523_PANTAR | R50: _103517_POONA_PIAGAPO | S50: _103518_SALVADOR | T50: _103519_SAPAD | U50: _103506_SULTAN_NAGA_DIMAPORO_KAROMATAN | V50: _103520_TAGOLOAN | W50: _103521_TANGCAL | X50: _103522_TUBOD
A51: _1042_MISAMIS_OCCIDENTAL | B51: _104201_ALORAN | C51: _104202_BALIANGAO | D51: _104203_BONIFACIO | E51: _104204_CALAMBA | F51: _104205_CLARIN | G51: _104206_CONCEPCION | H51: _104217_DON_VICTORIANO_CHIONGBIAN_DON_MARIANO_MARCOS | I51: _104207_JIMENEZ | J51: _104208_LOPEZ_JAENA | K51: _104209_OROQUIETA_CITY | L51: _104210_OZAMIS_CITY | M51: _104211_PANAON | N51: _104212_PLARIDEL | O51: _104213_SAPANG_DALAGA | P51: _104214_SINACABAN | Q51: _104215_TANGUB_CITY | R51: _104216_TUDELA
A52: _1043_MISAMIS_ORIENTAL | B52: _104301_ALUBIJID | C52: _104302_BALINGASAG | D52: _104303_BALINGOAN | E52: _104304_BINUANGAN | F52: _104305_CAGAYAN_DE_ORO_CITY | G52: _104307_CITY_OF_EL_SALVADOR | H52: _104306_CLAVERIA | I52: _104308_GINGOOG_CITY | J52: _104309_GITAGUM | K52: _104310_INITAO | L52: _104311_JASAAN | M52: _104312_KINOGUITAN | N52: _104313_LAGONGLONG | O52: _104314_LAGUINDINGAN | P52: _104315_LIBERTAD | Q52: _104316_LUGAIT | R52: _104317_MAGSAYSAY_LINUGOS | S52: _104318_MANTICAO | T52: _104319_MEDINA | U52: _104320_NAAWAN | V52: _104321_OPOL | W52: _104322_SALAY | X52: _104323_SUGBONGCOGON | Y52: _104324_TAGOLOAN | Z52: _104325_TALISAYAN | AA52: _104326_VILLANUEVA
A53: _1123_DAVAO_DEL_NORTE | B53: _112301_ASUNCION_SAUG | C53: _112323_BRAULIO_E_DUJALI | D53: _112303_CARMEN | E53: _112315_CITY_OF_PANABO | F53: _112319_CITY_OF_TAGUM | G53: _112317_ISLAND_GARDEN_CITY_OF_SAMAL | H53: _112305_KAPALONG | I53: _112314_NEW_CORELLA | J53: _112324_SAN_ISIDRO | K53: _112318_SANTO_TOMAS | L53: _112322_TALAINGOD
A54: _1124_DAVAO_DEL_SUR | B54: _112401_BANSALAN | C54: _112403_CITY_OF_DIGOS | D54: _112402_DAVAO_CITY | E54: _112404_HAGONOY | F54: _112406_KIBLAWAN | G54: _112407_MAGSAYSAY | H54: _112408_MALALAG | I54: _112410_MATANAO | J54: _112411_PADADA | K54: _112412_SANTA_CRUZ | L54: _112414_SULOP
A55: _1125_DAVAO_ORIENTAL | B55: _112501_BAGANGA | C55: _112502_BANAYBANAY | D55: _112503_BOSTON | E55: _112504_CARAGA | F55: _112505_CATEEL | G55: _112509_CITY_OF_MATI | H55: _112506_GOVERNOR_GENEROSO | I55: _112507_LUPON | J55: _112508_MANAY | K55: _112510_SAN_ISIDRO | L55: _112511_TARRAGONA
A56: _1182_COMPOSTELA_VALLEY | B56: _118201_COMPOSTELA | C56: _118202_LAAK_SAN_VICENTE | D56: _118203_MABINI_DOÑA_ALICIA | E56: _118204_MACO | F56: _118205_MARAGUSAN_SAN_MARIANO | G56: _118206_MAWAB | H56: _118207_MONKAYO | I56: _118208_MONTEVISTA | J56: _118209_NABUNTURAN | K56: _118210_NEW_BATAAN | L56: _118211_PANTUKAN
A57: _1186_DAVAO_OCCIDENTAL | B57: _118601_DON_MARCELINO | C57: _118602_JOSE_ABAD_SANTOS_TRINIDAD | D57: _118603_MALITA | E57: _118604_SANTA_MARIA | F57: _118605_SARANGANI
A58: _1247_NORTH_COTABATO | B58: _124701_ALAMADA | C58: _124717_ALEOSAN | D58: _124715_ANTIPAS | E58: _124718_ARAKAN | F58: _124716_BANISILAN | G58: _124702_CARMEN | H58: _124704_CITY_OF_KIDAPAWAN | I58: _124703_KABACAN | J58: _124705_LIBUNGAN | K58: _124710_MLANG | L58: _124706_MAGPET | M58: _124707_MAKILALA | N58: _124708_MATALAM | O58: _124709_MIDSAYAP | P58: _124711_PIGKAWAYAN | Q58: _124712_PIKIT | R58: _124713_PRESIDENT_ROXAS | S58: _124714_TULUNAN
A59: _1263_SOUTH_COTABATO | B59: _126302_BANGA | C59: _126306_CITY_OF_KORONADAL | D59: _126303_GENERAL_SANTOS_CITY | E59: _126319_LAKE_SEBU | F59: _126311_NORALA | G59: _126312_POLOMOLOK | H59: _126318_SANTO_NIÑO | I59: _126313_SURALLAH | J59: _126316_TBOLI | K59: _126314_TAMPAKAN | L59: _126315_TANTANGAN | M59: _126317_TUPI
A60: _1265_SULTAN_KUDARAT | B60: _126501_BAGUMBAYAN | C60: _126511_CITY_OF_TACURONG | D60: _126502_COLUMBIO | E60: _126503_ESPERANZA | F60: _126504_ISULAN | G60: _126505_KALAMANSIG | H60: _126508_LAMBAYONG_MARIANO_MARCOS | I60: _126506_LEBAK | J60: _126507_LUTAYAN | K60: _126509_PALIMBANG | L60: _126510_PRESIDENT_QUIRINO | M60: _126512_SEN._NINOY_AQUINO
A61: _1280_SARANGANI | B61: _128001_ALABEL | C61: _128002_GLAN | D61: _128003_KIAMBA | E61: _128004_MAASIM | F61: _128005_MAITUM | G61: _128006_MALAPATAN | H61: _128007_MALUNGON
A62: _1298_COTABATO_CITY | B62: _129804_COTABATO_CITY
A63: _1339_NCR_CITY_OF_MANILA_FIRST_DISTRICT | B63: _133900_CITY_OF_MANILA
A64: _1374_NCR_SECOND_DISTRICT | B64: _137401_CITY_OF_MANDALUYONG | C64: _137402_CITY_OF_MARIKINA | D64: _137403_CITY_OF_PASIG | E64: _137405_CITY_OF_SAN_JUAN | F64: _137404_QUEZON_CITY
A65: _1375_NCR_THIRD_DISTRICT | B65: _137501_CALOOCAN_CITY | C65: _137502_CITY_OF_MALABON | D65: _137503_CITY_OF_NAVOTAS | E65: _137504_CITY_OF_VALENZUELA
A66: _1376_NCR_FOURTH_DISTRICT | B66: _137601_CITY_OF_LAS_PIÑAS | C66: _137602_CITY_OF_MAKATI | D66: _137603_CITY_OF_MUNTINLUPA | E66: _137604_CITY_OF_PARAÑAQUE | F66: _137605_PASAY_CITY | G66: _137606_PATEROS | H66: _137607_TAGUIG_CITY
A67: _1401_ABRA | B67: _140101_BANGUED | C67: _140102_BOLINEY | D67: _140103_BUCAY | E67: _140104_BUCLOC | F67: _140105_DAGUIOMAN | G67: _140106_DANGLAS | H67: _140107_DOLORES | I67: _140108_LA_PAZ | J67: _140109_LACUB | K67: _140110_LAGANGILANG | L67: _140111_LAGAYAN | M67: _140112_LANGIDEN | N67: _140113_LICUAN_BAAY_LICUAN | O67: _140114_LUBA | P67: _140115_MALIBCONG | Q67: _140116_MANABO | R67: _140117_PENARRUBIA | S67: _140118_PIDIGAN | T67: _140119_PILAR | U67: _140120_SALLAPADAN | V67: _140121_SAN_ISIDRO | W67: _140122_SAN_JUAN | X67: _140123_SAN_QUINTIN | Y67: _140124_TAYUM | Z67: _140125_TINEG | AA67: _140126_TUBO | AB67: _140127_VILLAVICIOSA
A68: _1411_BENGUET | B68: _141101_ATOK | C68: _141102_BAGUIO_CITY | D68: _141103_BAKUN | E68: _141104_BOKOD | F68: _141105_BUGUIAS | G68: _141106_ITOGON | H68: _141107_KABAYAN | I68: _141108_KAPANGAN | J68: _141109_KIBUNGAN | K68: _141110_LA_TRINIDAD | L68: _141111_MANKAYAN | M68: _141112_SABLAN | N68: _141113_TUBA | O68: _141114_TUBLAY
A69: _1427_IFUGAO | B69: _142708_AGUINALDO | C69: _142707_ALFONSO_LISTA_POTIA | D69: _142711_ASIPULO | E69: _142701_BANAUE | F69: _142709_HINGYON | G69: _142702_HUNGDUAN | H69: _142703_KIANGAN | I69: _142704_LAGAWE | J69: _142705_LAMUT | K69: _142706_MAYOYAO | L69: _142710_TINOC
A70: _1432_KALINGA | B70: _143201_BALBALAN | C70: _143213_CITY_OF_TABUK | D70: _143206_LUBUAGAN | E70: _143208_PASIL | F70: _143209_PINUKPUK | G70: _143211_RIZAL_LIWAN | H70: _143214_TANUDAN | I70: _143215_TINGLAYAN
A71: _1444_MOUNTAIN_PROVINCE | B71: _144401_BARLIG | C71: _144402_BAUKO | D71: _144403_BESAO | E71: _144404_BONTOC | F71: _144405_NATONIN | G71: _144406_PARACELIS | H71: _144407_SABANGAN | I71: _144408_SADANGA | J71: _144409_SAGADA | K71: _144410_TADIAN
A72: _1481_APAYAO | B72: _148101_CALANASAN_BAYAG | C72: _148102_CONNER | D72: _148103_FLORA | E72: _148104_KABUGAO | F72: _148105_LUNA | G72: _148106_PUDTOL | H72: _148107_SANTA_MARCELA
A73: _1507_BASILAN | B73: _150708_AKBAR | C73: _150709_AL_BARKA | D73: _150702_CITY_OF_LAMITAN | E73: _150710_HADJI_MOHAMMAD_AJUL | F73: _150712_HADJI_MUHTAMAD | G73: _150703_LANTAWAN | H73: _150704_MALUSO | I73: _150705_SUMISIP | J73: _150713_TABUAN_LASA | K73: _150706_TIPO_TIPO | L73: _150707_TUBURAN | M73: _150711_UNGKAYA_PUKAN
A74: _1536_LANAO_DEL_SUR | B74: _153601_BACOLOD_KALAWI_BACOLOD_GRANDE | C74: _153602_BALABAGAN | D74: _153603_BALINDONG_WATU | E74: _153604_BAYANG | F74: _153605_BINIDAYAN | G74: _153633_BUADIPOSO_BUNTONG | H74: _153606_BUBONG | I74: _153637_BUMBARAN | J74: _153607_BUTIG | K74: _153632_CALANOGAS | L74: _153624_DITSAAN_RAMAIN | M74: _153609_GANASSI | N74: _153610_KAPAI | O74: _153639_KAPATAGAN | P74: _153611_LUMBA_BAYABAO_MAGUING | Q74: _153641_LUMBACA_UNAYAN | R74: _153612_LUMBATAN | S74: _153636_LUMBAYANAGUE | T74: _153613_MADALUM | U74: _153614_MADAMBA | V74: _153634_MAGUING | W74: _153615_MALABANG | X74: _153616_MARANTAO | Y74: _153617_MARAWI_CITY | Z74: _153631_MAROGONG | AA74: _153618_MASIU | AB74: _153619_MULONDO | AC74: _153620_PAGAYAWAN_TATARIKAN | AD74: _153621_PIAGAPO | AE74: _153635_PICONG_SULTAN_GUMANDER | AF74: _153622_POONA_BAYABAO_GATA | AG74: _153623_PUALAS | AH74: _153625_SAGUIARAN | AI74: _153640_SULTAN_DUMALONDONG | AJ74: _153638_TAGOLOAN_II | AK74: _153626_TAMPARAN | AL74: _153627_TARAKA | AM74: _153628_TUBARAN | AN74: _153629_TUGAYA | AO74: _153630_WAO
